Workbook

Sheet DCA-Anexo I-AB
A2: QDCC
A3: BALANÇO ANUAL (DCA)
A4: VERSÃO: v14
A5: VIGÊNCIA: 05/01/2026
A7: Ente: 2908101 - Cocos/BA
A8: Poder: E - Executivo
A9: Instituição: 4063 - Prefeitura Municipal de Cocos - BA
A10: Exercício: 2025
A11: Periodicidade: ANUAL
A12: Período: Período único (anual)
A14: Grupo: Balanço Patrimonial - Ativo e Passivo
A15: Quadro: Balanço Patrimonial
A16: Rótulo: Padrão
A17: Balanço Patrimonial | B17: Valores
B18: 31/12/2025
A19: Ativo
A20: Ativo
A21: 1.0.0.0.0.00.00 - Ativo | B21: =+'DCA-Anexo I-AB'!B22+'DCA-Anexo I-AB'!B227 -> 54031265
A22: 1.1.0.0.0.00.00 - Ativo Circulante | B22: =+'DCA-Anexo I-AB'!B23+'DCA-Anexo I-AB'!B32+'DCA-Anexo I-AB'!B75+'DCA-Anexo I-AB'!B124+'DCA-Anexo I-AB'!B135+'DCA-Anexo I-AB'!B152+'DCA-Anexo I-AB'!B172+'DCA-Anexo I-AB'!B169 -> 11601960
A23: 1.1.1.0.0.00.00 - Caixa e Equivalentes de Caixa | B23: =+'DCA-Anexo I-AB'!B24+'DCA-Anexo I-AB'!B27+'DCA-Anexo I-AB'!B29 -> 7883059.6
A24: 1.1.1.1.0.00.00 - Caixa e Equivalentes de Caixa em Moeda Nacional | B24: =+'DCA-Anexo I-AB'!B25+'DCA-Anexo I-AB'!B26 -> 7883059.6
A25: 1.1.1.1.1.00.00 - Caixa e Equivalentes de Caixa em Moeda Nacional - Consolidação | B25: 7883059.6
A26: 1.1.1.1.2.00.00 - Caixa e Equivalentes de Caixa em Moeda Nacional - Intra OFSS
A27: 1.1.1.2.0.00.00 - Caixa e Equivalentes de Caixa em Moeda Estrangeira | B27: =+'DCA-Anexo I-AB'!B28 -> 0
A28: 1.1.1.2.1.00.00 - Caixa e Equivalentes de Caixa em Moeda Estrangeira - Consolidação
A29: 1.1.1.3.0.00.00 - Caixa e Equivalentes de Caixa - Valores Restituíveis e Vinculados | B29: =+'DCA-Anexo I-AB'!B30+'DCA-Anexo I-AB'!B31 -> 0
A30: 1.1.1.3.1.00.00 - Depósitos Restituíveis e Valores Vinculados - Consolidação
A31: 1.1.1.3.2.00.00 - Valores Restituíveis - Intra OFSS
A32: 1.1.2.0.0.00.00 - Créditos a Curto Prazo | B32: =+'DCA-Anexo I-AB'!B33+'DCA-Anexo I-AB'!B39+'DCA-Anexo I-AB'!B45+'DCA-Anexo I-AB'!B51+'DCA-Anexo I-AB'!B57+'DCA-Anexo I-AB'!B63-'DCA-Anexo I-AB'!B69 -> 3718900.3
A33: 1.1.2.1.0.00.00 - Créditos Tributários a Receber | B33: =+'DCA-Anexo I-AB'!B34+'DCA-Anexo I-AB'!B35+'DCA-Anexo I-AB'!B36+'DCA-Anexo I-AB'!B37+'DCA-Anexo I-AB'!B38 -> 1647985.1
A34: 1.1.2.1.1.00.00 - Créditos Tributários a Receber - Consolidação | B34: 1647985.1
A35: 1.1.2.1.2.00.00 - Créditos Tributários a Receber - Intra OFSS
A36: 1.1.2.1.3.00.00 - Créditos Tributários a Receber - Inter OFSS - União
A37: 1.1.2.1.4.00.00 - Créditos Tributários a Receber - Inter OFSS – Estado
A38: 1.1.2.1.5.00.00 - Créditos Tributários a Receber - Inter OFSS - Município
A39: 1.1.2.2.0.00.00 - Clientes | B39: =+'DCA-Anexo I-AB'!B40+'DCA-Anexo I-AB'!B41+'DCA-Anexo I-AB'!B42+'DCA-Anexo I-AB'!B43+'DCA-Anexo I-AB'!B44 -> 0
A40: 1.1.2.2.1.00.00 - Clientes - Consolidação
A41: 1.1.2.2.2.00.00 - Clientes - Intra OFSS
A42: 1.1.2.2.3.00.00 - Clientes - Inter OFSS - União
A43: 1.1.2.2.4.00.00 - Clientes - Inter OFSS - Estado
A44: 1.1.2.2.5.00.00 - Clientes - Inter OFSS - Município
A45: 1.1.2.3.0.00.00 - Créditos de Transferências a Receber | B45: =+'DCA-Anexo I-AB'!B46+'DCA-Anexo I-AB'!B47+'DCA-Anexo I-AB'!B48+'DCA-Anexo I-AB'!B49+'DCA-Anexo I-AB'!B50 -> 1904430.7
A46: 1.1.2.3.1.00.00 - Créditos de Transferências a Receber - Consolidação | B46: 1904430.7
A47: 1.1.2.3.2.00.00 - Créditos de Transferências a Receber - Intra OFSS
A48: 1.1.2.3.3.00.00 - Créditos de Transferências a Receber - Inter OFSS - União
A49: 1.1.2.3.4.00.00 - Créditos de Transferências a Receber - Inter OFSS - Estado
A50: 1.1.2.3.5.00.00 - Créditos de Transferências a Receber - Inter OFSS - Município
A51: 1.1.2.4.0.00.00 - Empréstimos e Financiamentos Concedidos | B51: =+'DCA-Anexo I-AB'!B52+'DCA-Anexo I-AB'!B53+'DCA-Anexo I-AB'!B54+'DCA-Anexo I-AB'!B55+'DCA-Anexo I-AB'!B56 -> 0
A52: 1.1.2.4.1.00.00 - Empréstimos e Financiamentos Concedidos - Consolidação
A53: 1.1.2.4.2.00.00 - Empréstimos e Financiamentos Concedidos - Intra OFSS
A54: 1.1.2.4.3.00.00 - Empréstimos e Financiamentos Concedidos - Inter OFSS - União
A55: 1.1.2.4.4.00.00 - Empréstimos e Financiamentos Concedidos - Inter OFSS - Estado
A56: 1.1.2.4.5.00.00 - Empréstimos e Financiamentos Concedidos - Inter OFSS - Município
A57: 1.1.2.5.0.00.00 - Dívida Ativa Tributária | B57: =+'DCA-Anexo I-AB'!B58+'DCA-Anexo I-AB'!B59+'DCA-Anexo I-AB'!B60+'DCA-Anexo I-AB'!B61+'DCA-Anexo I-AB'!B62 -> 88962.11
A58: 1.1.2.5.1.00.00 - Dívida Ativa Tributária - Consolidação | B58: 88962.11
A59: 1.1.2.5.2.00.00 - Dívida Ativa Tributária - Intra OFSS
A60: 1.1.2.5.3.00.00 - Dívida Ativa Tributária - Inter OFSS - União
A61: 1.1.2.5.4.00.00 - Dívida Ativa Tributária - Inter OFSS - Estado
A62: 1.1.2.5.5.00.00 - Dívida Ativa Tributária - Inter OFSS - Município
A63: 1.1.2.6.0.00.00 - Dívida Ativa Não Tributária | B63: =+'DCA-Anexo I-AB'!B64+'DCA-Anexo I-AB'!B65+'DCA-Anexo I-AB'!B66+'DCA-Anexo I-AB'!B67+'DCA-Anexo I-AB'!B68 -> 77522.34
A64: 1.1.2.6.1.00.00 - Dívida Ativa Não Tributária - Consolidação | B64: 77522.34
A65: 1.1.2.6.2.00.00 - Dívida Ativa Não Tributária - Intra OFSS
A66: 1.1.2.6.3.00.00 - Dívida Ativa Não Tributária - Inter OFSS - União
A67: 1.1.2.6.4.00.00 - Dívida Ativa Não Tributária - Inter OFSS - Estado
A68: 1.1.2.6.5.00.00 - Dívida Ativa Não Tributária - Inter OFSS - Município
A69: 1.1.2.9.0.00.00 - (-) Ajuste de Perdas de Créditos a Curto Prazo | B69: =+'DCA-Anexo I-AB'!B70+'DCA-Anexo I-AB'!B71+'DCA-Anexo I-AB'!B72+'DCA-Anexo I-AB'!B73+'DCA-Anexo I-AB'!B74 -> 0
A70: 1.1.2.9.1.00.00 - (-) Ajuste de Perdas de Créditos a Curto Prazo - Consolidação | B70: 0
A71: 1.1.2.9.2.00.00 - (-) Ajuste de Perdas de Créditos a Curto Prazo - Intra OFSS
A72: 1.1.2.9.3.00.00 - (-) Ajuste de Perdas de Créditos a Curto Prazo - Inter OFSS - União
A73: 1.1.2.9.4.00.00 - (-) Ajuste de Perdas de Créditos a Curto Prazo - Inter OFSS - Estado
A74: 1.1.2.9.5.00.00 - (-) Ajuste de Perdas de Créditos a Curto Prazo - Inter OFSS - Município
A75: 1.1.3.0.0.00.00 - Demais Créditos e Valores a Curto Prazo | B75: =+'DCA-Anexo I-AB'!B76+'DCA-Anexo I-AB'!B82+'DCA-Anexo I-AB'!B88+'DCA-Anexo I-AB'!B94+'DCA-Anexo I-AB'!B100+'DCA-Anexo I-AB'!B106+'DCA-Anexo I-AB'!B112-'DCA-Anexo I-AB'!B118 -> 0
A76: 1.1.3.1.0.00.00 - Adiantamentos Concedidos | B76: =+'DCA-Anexo I-AB'!B77+'DCA-Anexo I-AB'!B78+'DCA-Anexo I-AB'!B79+'DCA-Anexo I-AB'!B80+'DCA-Anexo I-AB'!B81 -> 0
A77: 1.1.3.1.1.00.00 - Adiantamentos Concedidos - Consolidação | B77: 0
A78: 1.1.3.1.2.00.00 - Adiantamentos Concedidos - Intra OFSS
A79: 1.1.3.1.3.00.00 - Adiantamentos Concedidos - Inter OFSS - União
A80: 1.1.3.1.4.00.00 - Adiantamentos Concedidos - Inter OFSS - Estado
A81: 1.1.3.1.5.00.00 - Adiantamentos Concedidos - Inter OFSS - Município
A82: 1.1.3.2.0.00.00 - Tributos a Recuperar/Compensar | B82: =+'DCA-Anexo I-AB'!B83+'DCA-Anexo I-AB'!B84+'DCA-Anexo I-AB'!B85+'DCA-Anexo I-AB'!B86+'DCA-Anexo I-AB'!B87 -> 0
A83: 1.1.3.2.1.00.00 - Tributos a Recuperar/Compensar - Consolidação | B83: 0
A84: 1.1.3.2.2.00.00 - Tributos a Recuperar/Compensar - Intra OFSS
A85: 1.1.3.2.3.00.00 - Tributos a Recuperar/Compensar - Inter OFSS - União
A86: 1.1.3.2.4.00.00 - Tributos a Recuperar/Compensar - Inter OFSS - Estado
A87: 1.1.3.2.5.00.00 - Tributos a Recuperar/Compensar - Inter OFSS - Município
A88: 1.1.3.3.0.00.00 - Créditos a Receber por Descentralização da Prestação de Serviços Públicos | B88: =+'DCA-Anexo I-AB'!B89+'DCA-Anexo I-AB'!B90+'DCA-Anexo I-AB'!B91+'DCA-Anexo I-AB'!B92+'DCA-Anexo I-AB'!B93 -> 0
A89: 1.1.3.3.1.00.00 - Créditos a Receber por Descentralização da Prestação de Serviços Públicos - Consolidação | B89: 0
A90: 1.1.3.3.2.00.00 - Créditos a Receber por Descentralização da Prestação de Serviços Públicos - Intra OFSS
A91: 1.1.3.3.3.00.00 - Créditos a Receber por Descentralização da Prestação de Serviços Públicos - Inter OFSS - União
A92: 1.1.3.3.4.00.00 - Créditos a Receber por Descentralização da Prestação de Serviços Públicos - Inter OFSS - Estado
A93: 1.1.3.3.5.00.00 - Créditos a Receber por Descentralização da Prestação de Serviços Públicos - Inter OFSS - Município
A94: 1.1.3.4.0.00.00 - Créditos por Danos ao Patrimônio | B94: =+'DCA-Anexo I-AB'!B95+'DCA-Anexo I-AB'!B96+'DCA-Anexo I-AB'!B97+'DCA-Anexo I-AB'!B98+'DCA-Anexo I-AB'!B99 -> 0
A95: 1.1.3.4.1.00.00 - Créditos por Danos ao Patrimônio - Consolidação | B95: 0
A96: 1.1.3.4.2.00.00 - Créditos por Danos ao Patrimônio - Intra OFSS
A97: 1.1.3.4.3.00.00 - Créditos por Danos ao Patrimônio - Inter OFSS - União
A98: 1.1.3.4.4.00.00 - Créditos por Danos ao Patrimônio - Inter OFSS - Estado
A99: 1.1.3.4.5.00.00 - Créditos por Danos ao Patrimônio - Inter OFSS - Município
A100: 1.1.3.5.0.00.00 - Depósitos Restituíveis e Valores Vinculados - A Receber | B100: =+'DCA-Anexo I-AB'!B101+'DCA-Anexo I-AB'!B102+'DCA-Anexo I-AB'!B103+'DCA-Anexo I-AB'!B104+'DCA-Anexo I-AB'!B105 -> 0
A101: 1.1.3.5.1.00.00 - Depósitos Restituíveis e Valores Vinculados - Consolidação | B101: 0
A102: 1.1.3.5.2.00.00 - Depósitos Restituíveis e Valores Vinculados - Intra OFSS
A103: 1.1.3.5.3.00.00 - Depósitos Restituíveis e Valores Vinculados - Inter OFSS - União
...

Sheet formulas
A1: [DCA-Anexo I-AB]
A2: 'DCA-Anexo I-AB'!B22=+'DCA-Anexo I-AB'!B23+'DCA-Anexo I-AB'!B32+'DCA-Anexo I-AB'!B75+'DCA-Anexo I-AB'!B124+'DCA-Anexo I-AB'!B135+'DCA-Anexo I-AB'!B152+'DCA-Anexo I-AB'!B172+'DCA-Anexo I-AB'!B169
A3: 'DCA-Anexo I-AB'!B23=+'DCA-Anexo I-AB'!B24+'DCA-Anexo I-AB'!B27+'DCA-Anexo I-AB'!B29
A4: 'DCA-Anexo I-AB'!B24=+'DCA-Anexo I-AB'!B25+'DCA-Anexo I-AB'!B26
A5: 'DCA-Anexo I-AB'!B27=+'DCA-Anexo I-AB'!B28
A6: 'DCA-Anexo I-AB'!B32=+'DCA-Anexo I-AB'!B33+'DCA-Anexo I-AB'!B39+'DCA-Anexo I-AB'!B45+'DCA-Anexo I-AB'!B51+'DCA-Anexo I-AB'!B57+'DCA-Anexo I-AB'!B63-'DCA-Anexo I-AB'!B69
A7: 'DCA-Anexo I-AB'!B33=+'DCA-Anexo I-AB'!B34+'DCA-Anexo I-AB'!B35+'DCA-Anexo I-AB'!B36+'DCA-Anexo I-AB'!B37+'DCA-Anexo I-AB'!B38
A8: 'DCA-Anexo I-AB'!B39=+'DCA-Anexo I-AB'!B40+'DCA-Anexo I-AB'!B41+'DCA-Anexo I-AB'!B42+'DCA-Anexo I-AB'!B43+'DCA-Anexo I-AB'!B44
A9: 'DCA-Anexo I-AB'!B45=+'DCA-Anexo I-AB'!B46+'DCA-Anexo I-AB'!B47+'DCA-Anexo I-AB'!B48+'DCA-Anexo I-AB'!B49+'DCA-Anexo I-AB'!B50
A10: 'DCA-Anexo I-AB'!B51=+'DCA-Anexo I-AB'!B52+'DCA-Anexo I-AB'!B53+'DCA-Anexo I-AB'!B54+'DCA-Anexo I-AB'!B55+'DCA-Anexo I-AB'!B56
A11: 'DCA-Anexo I-AB'!B57=+'DCA-Anexo I-AB'!B58+'DCA-Anexo I-AB'!B59+'DCA-Anexo I-AB'!B60+'DCA-Anexo I-AB'!B61+'DCA-Anexo I-AB'!B62
A12: 'DCA-Anexo I-AB'!B63=+'DCA-Anexo I-AB'!B64+'DCA-Anexo I-AB'!B65+'DCA-Anexo I-AB'!B66+'DCA-Anexo I-AB'!B67+'DCA-Anexo I-AB'!B68
... A2455: 'DCA-Anexo I-E'!F204=+'DCA-Anexo I-E'!F205+'DCA-Anexo I-E'!F206+'DCA-Anexo I-E'!F207+'DCA-Anexo I-E'!F208+'DCA-Anexo I-E'!F209+'DCA-Anexo I-E'!F210+'DCA-Anexo I-E'!F211+'DCA-Anexo I-E'!F212

Sheet DCA-Anexo I-C
A2: QDCC
A3: BALANÇO ANUAL (DCA)
A4: VERSÃO: v14
A5: VIGÊNCIA: 05/01/2026
A7: Ente: 2908101 - Cocos/BA
A8: Poder: E - Executivo
A9: Instituição: 4063 - Prefeitura Municipal de Cocos - BA
A10: Exercício: 2025
A11: Periodicidade: ANUAL
A12: Período: Período único (anual)
A14: Grupo: Balanço Orçamentário - Receitas Orçamentárias
A15: Quadro: Receitas Orçamentárias
A16: Rótulo: Padrão
A17: Receitas Orçamentárias | B17: Execução da Receita
B18: Receitas Brutas Realizadas | C18: Deduções - Transferências Constitucionais | D18: Deduções - FUNDEB | E18: Outras Deduções da Receita
A19: Receitas Orçamentárias
A20: RECEITAS (EXCETO INTRA-ORÇAMENTÁRIAS) (I) | B20: =+'DCA-Anexo I-C'!B21+'DCA-Anexo I-C'!B690 -> 1.5097371e+08 | C20: =+'DCA-Anexo I-C'!C21+'DCA-Anexo I-C'!C690 -> 0 | D20: =+'DCA-Anexo I-C'!D21+'DCA-Anexo I-C'!D690 -> 15193653 | E20: =+'DCA-Anexo I-C'!E21+'DCA-Anexo I-C'!E690 -> 0
A21: 1.0.0.0.00.0.0 - Receitas Correntes | B21: =+'DCA-Anexo I-C'!B22+'DCA-Anexo I-C'!B90+'DCA-Anexo I-C'!B253+'DCA-Anexo I-C'!B378+'DCA-Anexo I-C'!B379+'DCA-Anexo I-C'!B380+'DCA-Anexo I-C'!B417+'DCA-Anexo I-C'!B551 -> 1.4973449e+08 | C21: =+'DCA-Anexo I-C'!C22+'DCA-Anexo I-C'!C90+'DCA-Anexo I-C'!C253+'DCA-Anexo I-C'!C378+'DCA-Anexo I-C'!C379+'DCA-Anexo I-C'!C380+'DCA-Anexo I-C'!C417+'DCA-Anexo I-C'!C551 -> 0 | D21: =+'DCA-Anexo I-C'!D22+'DCA-Anexo I-C'!D90+'DCA-Anexo I-C'!D253+'DCA-Anexo I-C'!D378+'DCA-Anexo I-C'!D379+'DCA-Anexo I-C'!D380+'DCA-Anexo I-C'!D417+'DCA-Anexo I-C'!D551 -> 15193653 | E21: =+'DCA-Anexo I-C'!E22+'DCA-Anexo I-C'!E90+'DCA-Anexo I-C'!E253+'DCA-Anexo I-C'!E378+'DCA-Anexo I-C'!E379+'DCA-Anexo I-C'!E380+'DCA-Anexo I-C'!E417+'DCA-Anexo I-C'!E551 -> 0
A22: 1.1.0.0.00.0.0 - Impostos, Taxas e Contribuições de Melhoria | B22: =+'DCA-Anexo I-C'!B23+'DCA-Anexo I-C'!B59+'DCA-Anexo I-C'!B83 -> 9603959.8 | C22: =+'DCA-Anexo I-C'!C23+'DCA-Anexo I-C'!C59+'DCA-Anexo I-C'!C83 -> 0 | D22: =+'DCA-Anexo I-C'!D23+'DCA-Anexo I-C'!D59+'DCA-Anexo I-C'!D83 -> 0 | E22: =+'DCA-Anexo I-C'!E23+'DCA-Anexo I-C'!E59+'DCA-Anexo I-C'!E83 -> 0
A23: 1.1.1.0.00.0.0 - Impostos | B23: =+'DCA-Anexo I-C'!B24+'DCA-Anexo I-C'!B27+'DCA-Anexo I-C'!B33+'DCA-Anexo I-C'!B41+'DCA-Anexo I-C'!B55+'DCA-Anexo I-C'!B58 -> 9413468.2 | C23: =+'DCA-Anexo I-C'!C24+'DCA-Anexo I-C'!C27+'DCA-Anexo I-C'!C33+'DCA-Anexo I-C'!C41+'DCA-Anexo I-C'!C55+'DCA-Anexo I-C'!C58 -> 0 | D23: =+'DCA-Anexo I-C'!D24+'DCA-Anexo I-C'!D27+'DCA-Anexo I-C'!D33+'DCA-Anexo I-C'!D41+'DCA-Anexo I-C'!D55+'DCA-Anexo I-C'!D58 -> 0 | E23: =+'DCA-Anexo I-C'!E24+'DCA-Anexo I-C'!E27+'DCA-Anexo I-C'!E33+'DCA-Anexo I-C'!E41+'DCA-Anexo I-C'!E55+'DCA-Anexo I-C'!E58 -> 0
A24: 1.1.1.1.00.0.0 - Impostos sobre o Comércio Exterior | B24: =+'DCA-Anexo I-C'!B25+'DCA-Anexo I-C'!B26 -> 0 | C24: =+'DCA-Anexo I-C'!C25+'DCA-Anexo I-C'!C26 -> 0 | D24: =+'DCA-Anexo I-C'!D25+'DCA-Anexo I-C'!D26 -> 0 | E24: =+'DCA-Anexo I-C'!E25+'DCA-Anexo I-C'!E26 -> 0
A25: 1.1.1.1.01.0.0 - Imposto sobre a Importação
A26: 1.1.1.1.02.0.0 - Imposto sobre a Exportação
A27: 1.1.1.2.00.0.0 - Impostos sobre o Patrimônio | B27: =+'DCA-Anexo I-C'!B28+'DCA-Anexo I-C'!B29+'DCA-Anexo I-C'!B30+'DCA-Anexo I-C'!B31+'DCA-Anexo I-C'!B32 -> 809281.85 | C27: =+'DCA-Anexo I-C'!C28+'DCA-Anexo I-C'!C29+'DCA-Anexo I-C'!C30+'DCA-Anexo I-C'!C31+'DCA-Anexo I-C'!C32 -> 0 | D27: =+'DCA-Anexo I-C'!D28+'DCA-Anexo I-C'!D29+'DCA-Anexo I-C'!D30+'DCA-Anexo I-C'!D31+'DCA-Anexo I-C'!D32 -> 0 | E27: =+'DCA-Anexo I-C'!E28+'DCA-Anexo I-C'!E29+'DCA-Anexo I-C'!E30+'DCA-Anexo I-C'!E31+'DCA-Anexo I-C'!E32 -> 0
A28: 1.1.1.2.01.0.0 - Imposto sobre a Propriedade Territorial Rural
A29: 1.1.1.2.50.0.0 - Imposto sobre a Propriedade Predial e Territorial Urbana | B29: 146001.28
A30: 1.1.1.2.51.0.0 - Imposto sobre a Propriedade de Veículos Automotores
A31: 1.1.1.2.52.0.0 - Imposto sobre Transmissão “Causa Mortis” e Doação de Bens e Direitos
A32: 1.1.1.2.53.0.0 - Impostos sobre Transmissão "Inter Vivos" de Bens Imóveis e de Direitos Reais sobre Imóveis | B32: 663280.57
A33: 1.1.1.3.00.0.0 - Impostos sobre a Renda e Proventos de Qualquer Natureza | B33: =+'DCA-Anexo I-C'!B34+'DCA-Anexo I-C'!B35+'DCA-Anexo I-C'!B36 -> 2414848.6 | C33: =+'DCA-Anexo I-C'!C34+'DCA-Anexo I-C'!C35+'DCA-Anexo I-C'!C36 -> 0 | D33: =+'DCA-Anexo I-C'!D34+'DCA-Anexo I-C'!D35+'DCA-Anexo I-C'!D36 -> 0 | E33: =+'DCA-Anexo I-C'!E34+'DCA-Anexo I-C'!E35+'DCA-Anexo I-C'!E36 -> 0
A34: 1.1.1.3.01.0.0 - Imposto sobre a Renda de Pessoa Física - IRPF
A35: 1.1.1.3.02.0.0 - Imposto sobre a Renda de Pessoa Jurídica - IRPJ - Líquida de Incentivos
A36: 1.1.1.3.03.0.0 - Imposto sobre a Renda - Retido na Fonte | B36: =+'DCA-Anexo I-C'!B37+'DCA-Anexo I-C'!B38+'DCA-Anexo I-C'!B39+'DCA-Anexo I-C'!B40 -> 2414848.6 | C36: =+'DCA-Anexo I-C'!C37+'DCA-Anexo I-C'!C38+'DCA-Anexo I-C'!C39+'DCA-Anexo I-C'!C40 -> 0 | D36: =+'DCA-Anexo I-C'!D37+'DCA-Anexo I-C'!D38+'DCA-Anexo I-C'!D39+'DCA-Anexo I-C'!D40 -> 0 | E36: =+'DCA-Anexo I-C'!E37+'DCA-Anexo I-C'!E38+'DCA-Anexo I-C'!E39+'DCA-Anexo I-C'!E40 -> 0
A37: 1.1.1.3.03.1.0 - Imposto sobre a Renda - Retido na Fonte - Trabalho | B37: 581523.18
A38: 1.1.1.3.03.2.0 - Imposto sobre a Renda - Retido na Fonte - Capital
A39: 1.1.1.3.03.3.0 - Imposto sobre a Renda - Retido na Fonte - Remessa ao Exterior
A40: 1.1.1.3.03.4.0 - Imposto sobre a Renda - Retido na Fonte - Outros Rendimentos | B40: 1833325.4
A41: 1.1.1.4.00.0.0 - Impostos sobre a Produção e Circulação de Mercadorias e Serviços | B41: =+'DCA-Anexo I-C'!B42+'DCA-Anexo I-C'!B48+'DCA-Anexo I-C'!B51+'DCA-Anexo I-C'!B54 -> 6189337.8 | C41: =+'DCA-Anexo I-C'!C42+'DCA-Anexo I-C'!C48+'DCA-Anexo I-C'!C51+'DCA-Anexo I-C'!C54 -> 0 | D41: =+'DCA-Anexo I-C'!D42+'DCA-Anexo I-C'!D48+'DCA-Anexo I-C'!D51+'DCA-Anexo I-C'!D54 -> 0 | E41: =+'DCA-Anexo I-C'!E42+'DCA-Anexo I-C'!E48+'DCA-Anexo I-C'!E51+'DCA-Anexo I-C'!E54 -> 0
A42: 1.1.1.4.01.0.0 - Imposto sobre Produtos Industrializados - IPI | B42: =+'DCA-Anexo I-C'!B43+'DCA-Anexo I-C'!B44+'DCA-Anexo I-C'!B45+'DCA-Anexo I-C'!B46+'DCA-Anexo I-C'!B47 -> 0 | C42: =+'DCA-Anexo I-C'!C43+'DCA-Anexo I-C'!C44+'DCA-Anexo I-C'!C45+'DCA-Anexo I-C'!C46+'DCA-Anexo I-C'!C47 -> 0 | D42: =+'DCA-Anexo I-C'!D43+'DCA-Anexo I-C'!D44+'DCA-Anexo I-C'!D45+'DCA-Anexo I-C'!D46+'DCA-Anexo I-C'!D47 -> 0 | E42: =+'DCA-Anexo I-C'!E43+'DCA-Anexo I-C'!E44+'DCA-Anexo I-C'!E45+'DCA-Anexo I-C'!E46+'DCA-Anexo I-C'!E47 -> 0
A43: 1.1.1.4.01.1.0 - Imposto sobre Produtos Industrializados - IPI - Fumo
A44: 1.1.1.4.01.2.0 - Imposto sobre Produtos Industrializados - IPI- Bebidas
A45: 1.1.1.4.01.3.0 - Imposto sobre Produtos Industrializados - IPI - Automóveis
A46: 1.1.1.4.01.4.0 - Imposto sobre Produtos Industrializados - IPI - Vinculados à Importação
A47: 1.1.1.4.01.5.0 - Imposto sobre Produtos Industrializados - IPI - Outros Produtos
A48: 1.1.1.4.50.0.0 - Impostos sobre a Produção e Circulação de Mercadorias e Serviços | B48: =+'DCA-Anexo I-C'!B49+'DCA-Anexo I-C'!B50 -> 0 | C48: =+'DCA-Anexo I-C'!C49+'DCA-Anexo I-C'!C50 -> 0 | D48: =+'DCA-Anexo I-C'!D49+'DCA-Anexo I-C'!D50 -> 0 | E48: =+'DCA-Anexo I-C'!E49+'DCA-Anexo I-C'!E50 -> 0
A49: 1.1.1.4.50.1.0 - Imposto sobre Operações Relativas à Circulação de Mercadorias e sobre Prestações de Serviços de Transporte Interestadual e Intermunicipal e de Comunicação
A50: 1.1.1.4.50.2.0 - Adicional ICMS - Fundo Estadual de Combate à Pobreza
A51: 1.1.1.4.51.0.0 - Impostos sobre Serviços | B51: =+'DCA-Anexo I-C'!B52+'DCA-Anexo I-C'!B53 -> 6189337.8 | C51: =+'DCA-Anexo I-C'!C52+'DCA-Anexo I-C'!C53 -> 0 | D51: =+'DCA-Anexo I-C'!D52+'DCA-Anexo I-C'!D53 -> 0 | E51: =+'DCA-Anexo I-C'!E52+'DCA-Anexo I-C'!E53 -> 0
A52: 1.1.1.4.51.1.0 - Imposto sobre Serviços de Qualquer Natureza - ISSQN | B52: 6189337.8
A53: 1.1.1.4.51.2.0 - Adicional ISS - Fundo Municipal de Combate à Pobreza
A54: 1.1.1.4.52.0.0 - Imposto sobre Vendas a Varejo de Combustíveis Líquidos e Gasosos (IVVC)
A55: 1.1.1.5.00.0.0 - Impostos sobre Operações de Crédito, Câmbio e Seguro, ou Relativas a Títulos ou Valores Mobiliários | B55: =+'DCA-Anexo I-C'!B56+'DCA-Anexo I-C'!B57 -> 0 | C55: =+'DCA-Anexo I-C'!C56+'DCA-Anexo I-C'!C57 -> 0 | D55: =+'DCA-Anexo I-C'!D56+'DCA-Anexo I-C'!D57 -> 0 | E55: =+'DCA-Anexo I-C'!E56+'DCA-Anexo I-C'!E57 -> 0
A56: 1.1.1.5.01.0.0 - Imposto sobre Operações Financeiras Incidente sobre o Ouro - IOF-Ouro
A57: 1.1.1.5.02.0.0 - Imposto sobre Operações Financeiras - IOF - Demais Operações
A58: 1.1.1.9.00.0.0 - Outros Impostos
A59: 1.1.2.0.00.0.0 - Taxas | B59: =+'DCA-Anexo I-C'!B60+'DCA-Anexo I-C'!B76 -> 190491.56 | C59: =+'DCA-Anexo I-C'!C60+'DCA-Anexo I-C'!C76 -> 0 | D59: =+'DCA-Anexo I-C'!D60+'DCA-Anexo I-C'!D76 -> 0 | E59: =+'DCA-Anexo I-C'!E60+'DCA-Anexo I-C'!E76 -> 0
A60: 1.1.2.1.00.0.0 - Taxas pelo Exercício do Poder de Polícia | B60: =+'DCA-Anexo I-C'!B61+'DCA-Anexo I-C'!B62+'DCA-Anexo I-C'!B67+'DCA-Anexo I-C'!B68+'DCA-Anexo I-C'!B69+'DCA-Anexo I-C'!B70+'DCA-Anexo I-C'!B71+'DCA-Anexo I-C'!B72+'DCA-Anexo I-C'!B73+'DCA-Anexo I-C'!B74+'DCA-Anexo I-C'!B75 -> 189091.26 | C60: =+'DCA-Anexo I-C'!C61+'DCA-Anexo I-C'!C62+'DCA-Anexo I-C'!C67+'DCA-Anexo I-C'!C68+'DCA-Anexo I-C'!C69+'DCA-Anexo I-C'!C70+'DCA-Anexo I-C'!C71+'DCA-Anexo I-C'!C72+'DCA-Anexo I-C'!C73+'DCA-Anexo I-C'!C74+'DCA-Anexo I-C'!C75 -> 0 | D60: =+'DCA-Anexo I-C'!D61+'DCA-Anexo I-C'!D62+'DCA-Anexo I-C'!D67+'DCA-Anexo I-C'!D68+'DCA-Anexo I-C'!D69+'DCA-Anexo I-C'!D70+'DCA-Anexo I-C'!D71+'DCA-Anexo I-C'!D72+'DCA-Anexo I-C'!D73+'DCA-Anexo I-C'!D74+'DCA-Anexo I-C'!D75 -> 0 | E60: =+'DCA-Anexo I-C'!E61+'DCA-Anexo I-C'!E62+'DCA-Anexo I-C'!E67+'DCA-Anexo I-C'!E68+'DCA-Anexo I-C'!E69+'DCA-Anexo I-C'!E70+'DCA-Anexo I-C'!E71+'DCA-Anexo I-C'!E72+'DCA-Anexo I-C'!E73+'DCA-Anexo I-C'!E74+'DCA-Anexo I-C'!E75 -> 0
A61: 1.1.2.1.01.0.0 - Taxas de Inspeção, Controle e Fiscalização | B61: 150479.11
A62: 1.1.2.1.02.0.0 - Taxas de Fiscalização das Telecomunicações | B62: =+'DCA-Anexo I-C'!B63+'DCA-Anexo I-C'!B64+'DCA-Anexo I-C'!B65+'DCA-Anexo I-C'!B66 -> 0 | C62: =+'DCA-Anexo I-C'!C63+'DCA-Anexo I-C'!C64+'DCA-Anexo I-C'!C65+'DCA-Anexo I-C'!C66 -> 0 | D62: =+'DCA-Anexo I-C'!D63+'DCA-Anexo I-C'!D64+'DCA-Anexo I-C'!D65+'DCA-Anexo I-C'!D66 -> 0 | E62: =+'DCA-Anexo I-C'!E63+'DCA-Anexo I-C'!E64+'DCA-Anexo I-C'!E65+'DCA-Anexo I-C'!E66 -> 0
A63: 1.1.2.1.02.1.0 - Taxa de Fiscalização de Instalação - TFI - Não Proveniente da Utilização de Posições Orbitais
A64: 1.1.2.1.02.2.0 - Taxa de Fiscalização de Funcionamento - TFF - Não Proveniente da Utilização de Posições Orbitais
A65: 1.1.2.1.02.3.0 - Taxa de Fiscalização de Instalação - TFI - Proveniente da Utilização de Posições Orbitais
A66: 1.1.2.1.02.4.0 - Taxa de Fiscalização de Funcionamento - TFF - Proveniente da Utilização de Posições Orbitais
A67: 1.1.2.1.03.0.0 - Taxa de Controle e Fiscalização de Produtos Químicos
A68: 1.1.2.1.04.0.0 - Taxa de Controle e Fiscalização Ambiental | B68: 19673.64
A69: 1.1.2.1.05.0.0 - Taxa de Controle e Fiscalização da Pesca e Aquicultura
A70: 1.1.2.1.06.0.0 - Taxa de Utilização do Sistema Integrado de Comércio Exterior – SISCOMEX
A71: 1.1.2.1.07.0.0 - Taxa de Utilização do Mercante - TUM
A72: 1.1.2.1.08.0.0 - Taxa de Fiscalização devida pela Exploração Comercial de Loteria de Apostas de Quota Fixa
A73: 1.1.2.1.09.0.0 - Taxa de Autorização para a Distribuição Gratuita de Prêmios
A74: 1.1.2.1.50.0.0 - Taxa de Fiscalização de Vigilância Sanitária | B74: 18938.51
A75: 1.1.2.1.51.0.0 - Taxa de Saúde Suplementar
A76: 1.1.2.2.00.0.0 - Taxas pela Prestação de Serviços | B76: =+'DCA-Anexo I-C'!B77+'DCA-Anexo I-C'!B78+'DCA-Anexo I-C'!B79+'DCA-Anexo I-C'!B80+'DCA-Anexo I-C'!B81+'DCA-Anexo I-C'!B82 -> 1400.3 | C76: =+'DCA-Anexo I-C'!C77+'DCA-Anexo I-C'!C78+'DCA-Anexo I-C'!C79+'DCA-Anexo I-C'!C80+'DCA-Anexo I-C'!C81+'DCA-Anexo I-C'!C82 -> 0 | D76: =+'DCA-Anexo I-C'!D77+'DCA-Anexo I-C'!D78+'DCA-Anexo I-C'!D79+'DCA-Anexo I-C'!D80+'DCA-Anexo I-C'!D81+'DCA-Anexo I-C'!D82 -> 0 | E76: =+'DCA-Anexo I-C'!E77+'DCA-Anexo I-C'!E78+'DCA-Anexo I-C'!E79+'DCA-Anexo I-C'!E80+'DCA-Anexo I-C'!E81+'DCA-Anexo I-C'!E82 -> 0
A77: 1.1.2.2.01.0.0 - Taxas pela Prestação de Serviços em Geral | B77: 1400.3
A78: 1.1.2.2.02.0.0 - Emolumentos e Custas Judiciais
A79: 1.1.2.2.50.0.0 - Taxas Judiciais
A80: 1.1.2.2.51.0.0 - Taxas Extrajudiciais
A81: 1.1.2.2.52.0.0 - Taxa de Estudo de Impacto de Vizinhança (EIV)
A82: 1.1.2.2.53.0.0 - Taxa pela Prestação de Serviços de Limpeza Pública e Manejo de Resíduos Sólidos
A83: 1.1.3.0.00.0.0 - Contribuição de Melhoria | B83: =+'DCA-Anexo I-C'!B84 -> 0 | C83: =+'DCA-Anexo I-C'!C84 -> 0 | D83: =+'DCA-Anexo I-C'!D84 -> 0 | E83: =+'DCA-Anexo I-C'!E84 -> 0
A84: 1.1.3.1.00.0.0 - Contribuição de Melhoria | B84: =+'DCA-Anexo I-C'!B85+'DCA-Anexo I-C'!B86+'DCA-Anexo I-C'!B87+'DCA-Anexo I-C'!B88+'DCA-Anexo I-C'!B89 -> 0 | C84: =+'DCA-Anexo I-C'!C85+'DCA-Anexo I-C'!C86+'DCA-Anexo I-C'!C87+'DCA-Anexo I-C'!C88+'DCA-Anexo I-C'!C89 -> 0 | D84: =+'DCA-Anexo I-C'!D85+'DCA-Anexo I-C'!D86+'DCA-Anexo I-C'!D87+'DCA-Anexo I-C'!D88+'DCA-Anexo I-C'!D89 -> 0 | E84: =+'DCA-Anexo I-C'!E85+'DCA-Anexo I-C'!E86+'DCA-Anexo I-C'!E87+'DCA-Anexo I-C'!E88+'DCA-Anexo I-C'!E89 -> 0
A85: 1.1.3.1.50.0.0 - Contribuição de Melhoria para Expansão da Rede de Água Potável e Esgoto Sanitário
A86: 1.1.3.1.51.0.0 - Contribuição de Melhoria para Expansão da Rede de Iluminação Pública na Cidade
A87: 1.1.3.1.52.0.0 - Contribuição de Melhoria para Expansão de Rede de Iluminação Pública Rural
A88: 1.1.3.1.53.0.0 - Contribuição de Melhoria para Pavimentação e Obras Complementares
A89: 1.1.3.1.99.0.0 - Outras Contribuições de Melhoria
A90: 1.2.0.0.00.0.0 - Contribuições | B90: =+'DCA-Anexo I-C'!B91+'DCA-Anexo I-C'!B228+'DCA-Anexo I-C'!B251+'DCA-Anexo I-C'!B252 -> 0 | C90: =+'DCA-Anexo I-C'!C91+'DCA-Anexo I-C'!C228+'DCA-Anexo I-C'!C251+'DCA-Anexo I-C'!C252 -> 0 | D90: =+'DCA-Anexo I-C'!D91+'DCA-Anexo I-C'!D228+'DCA-Anexo I-C'!D251+'DCA-Anexo I-C'!D252 -> 0 | E90: =+'DCA-Anexo I-C'!E91+'DCA-Anexo I-C'!E228+'DCA-Anexo I-C'!E251+'DCA-Anexo I-C'!E252 -> 0
A91: 1.2.1.0.00.0.0 - Contribuições Sociais | B91: =+'DCA-Anexo I-C'!B92+'DCA-Anexo I-C'!B96+'DCA-Anexo I-C'!B100+'DCA-Anexo I-C'!B104+'DCA-Anexo I-C'!B108+'DCA-Anexo I-C'!B156+'DCA-Anexo I-C'!B172+'DCA-Anexo I-C'!B194 -> 0 | C91: =+'DCA-Anexo I-C'!C92+'DCA-Anexo I-C'!C96+'DCA-Anexo I-C'!C100+'DCA-Anexo I-C'!C104+'DCA-Anexo I-C'!C108+'DCA-Anexo I-C'!C156+'DCA-Anexo I-C'!C172+'DCA-Anexo I-C'!C194 -> 0 | D91: =+'DCA-Anexo I-C'!D92+'DCA-Anexo I-C'!D96+'DCA-Anexo I-C'!D100+'DCA-Anexo I-C'!D104+'DCA-Anexo I-C'!D108+'DCA-Anexo I-C'!D156+'DCA-Anexo I-C'!D172+'DCA-Anexo I-C'!D194 -> 0 | E91: =+'DCA-Anexo I-C'!E92+'DCA-Anexo I-C'!E96+'DCA-Anexo I-C'!E100+'DCA-Anexo I-C'!E104+'DCA-Anexo I-C'!E108+'DCA-Anexo I-C'!E156+'DCA-Anexo I-C'!E172+'DCA-Anexo I-C'!E194 -> 0
A92: 1.2.1.1.00.0.0 - Contribuição para Financiamento da Seguridade Social - COFINS | B92: =+'DCA-Anexo I-C'!B93+'DCA-Anexo I-C'!B94+'DCA-Anexo I-C'!B95 -> 0 | C92: =+'DCA-Anexo I-C'!C93+'DCA-Anexo I-C'!C94+'DCA-Anexo I-C'!C95 -> 0 | D92: =+'DCA-Anexo I-C'!D93+'DCA-Anexo I-C'!D94+'DCA-Anexo I-C'!D95 -> 0 | E92: =+'DCA-Anexo I-C'!E93+'DCA-Anexo I-C'!E94+'DCA-Anexo I-C'!E95 -> 0
A93: 1.2.1.1.01.0.0 - Contribuição para Financiamento da Seguridade Social - COFINS sobre o Faturamento - Contribuintes Não Optantes pelo Simples Nacional
A94: 1.2.1.1.02.0.0 - Contribuição para Financiamento da Seguridade Social - COFINS sobre o Faturamento - SIMPLES
A95: 1.2.1.1.49.0.0 - Contribuição para Financiamento da Seguridade Social - COFINS sobre o Faturamento - Parcelamentos
A96: 1.2.1.2.00.0.0 - Contribuição para o Programa de Integração Social e para Programa de Formação de Patrimônio do Servidor Público PIS/PASEP | B96: =+'DCA-Anexo I-C'!B97+'DCA-Anexo I-C'!B98+'DCA-Anexo I-C'!B99 -> 0 | C96: =+'DCA-Anexo I-C'!C97+'DCA-Anexo I-C'!C98+'DCA-Anexo I-C'!C99 -> 0 | D96: =+'DCA-Anexo I-C'!D97+'DCA-Anexo I-C'!D98+'DCA-Anexo I-C'!D99 -> 0 | E96: =+'DCA-Anexo I-C'!E97+'DCA-Anexo I-C'!E98+'DCA-Anexo I-C'!E99 -> 0
A97: 1.2.1.2.01.0.0 - Contribuição para o PIS/PASEP - Contribuintes Não Optantes pelo Simples Nacional
A98: 1.2.1.2.02.0.0 - Contribuição para o PIS/PASEP - Contribuintes Optantes pelo Simples Nacional
A99: 1.2.1.2.49.0.0 - Contribuição para o PIS/PASEP - Parcelamentos
A100: 1.2.1.3.00.0.0 - Contribuição Social sobre o Lucro Líquido - CSLL | B100: =+'DCA-Anexo I-C'!B101+'DCA-Anexo I-C'!B102+'DCA-Anexo I-C'!B103 -> 0 | C100: =+'DCA-Anexo I-C'!C101+'DCA-Anexo I-C'!C102+'DCA-Anexo I-C'!C103 -> 0 | D100: =+'DCA-Anexo I-C'!D101+'DCA-Anexo I-C'!D102+'DCA-Anexo I-C'!D103 -> 0 | E100: =+'DCA-Anexo I-C'!E101+'DCA-Anexo I-C'!E102+'DCA-Anexo I-C'!E103 -> 0
A101: 1.2.1.3.01.0.0 - Contribuição Social sobre o Lucro Líquido - CSLL - Contribuintes Não Optantes pelo Simples Nacional
A102: 1.2.1.3.02.0.0 - Contribuição Social sobre o Lucro Líquido - CSLL - Contribuintes Optantes pelo Simples Nacional
A103: 1.2.1.3.49.0.0 - Contribuição Social sobre o Lucro Líquido - CSLL - Parcelamentos
...

Sheet DCA-Anexo I-D
A2: QDCC
A3: BALANÇO ANUAL (DCA)
A4: VERSÃO: v14
A5: VIGÊNCIA: 05/01/2026
A7: Ente: 2908101 - Cocos/BA
A8: Poder: E - Executivo
A9: Instituição: 4063 - Prefeitura Municipal de Cocos - BA
A10: Exercício: 2025
A11: Periodicidade: ANUAL
A12: Período: Período único (anual)
A14: Grupo: Balanço Orçamentário - Despesas Orçamentárias
A15: Quadro: Despesas Orçamentárias
A16: Rótulo: Padrão
A17: Despesas Orçamentárias | B17: Execução da Despesa
B18: Despesas Empenhadas | C18: Despesas Liquidadas | D18: Despesas Pagas | E18: Inscrição de Restos a Pagar Não Processados | F18: Inscrição de Restos a Pagar Processados
A19: Despesas Orçamentárias
A20: Total Geral da Despesa | B20: =+'DCA-Anexo I-D'!B21+'DCA-Anexo I-D'!B235 -> 145272093 | C20: =+'DCA-Anexo I-D'!C21+'DCA-Anexo I-D'!C235 -> 145272093 | D20: =+'DCA-Anexo I-D'!D21+'DCA-Anexo I-D'!D235 -> 1.3632376e+08 | E20: =+'DCA-Anexo I-D'!E21+'DCA-Anexo I-D'!E235 -> 0 | F20: =+'DCA-Anexo I-D'!F21+'DCA-Anexo I-D'!F235 -> 8948337.3
A21: 3.0.00.00.00 - Despesas Correntes | B21: =+'DCA-Anexo I-D'!B22+'DCA-Anexo I-D'!B145+'DCA-Anexo I-D'!B103 -> 1.3482931e+08 | C21: =+'DCA-Anexo I-D'!C22+'DCA-Anexo I-D'!C145+'DCA-Anexo I-D'!C103 -> 1.3482931e+08 | D21: =+'DCA-Anexo I-D'!D22+'DCA-Anexo I-D'!D145+'DCA-Anexo I-D'!D103 -> 1.2590038e+08 | E21: =+'DCA-Anexo I-D'!E22+'DCA-Anexo I-D'!E145+'DCA-Anexo I-D'!E103 -> 0 | F21: =+'DCA-Anexo I-D'!F22+'DCA-Anexo I-D'!F145+'DCA-Anexo I-D'!F103 -> 8928935.3
A22: 3.1.00.00.00 - Pessoal e Encargos Sociais | B22: =+'DCA-Anexo I-D'!B34+'DCA-Anexo I-D'!B45+'DCA-Anexo I-D'!B36+'DCA-Anexo I-D'!B46+'DCA-Anexo I-D'!B37+'DCA-Anexo I-D'!B26+'DCA-Anexo I-D'!B100+'DCA-Anexo I-D'!B98+'DCA-Anexo I-D'!B31+'DCA-Anexo I-D'!B23+'DCA-Anexo I-D'!B102+'DCA-Anexo I-D'!B24+'DCA-Anexo I-D'!B75+'DCA-Anexo I-D'!B32+'DCA-Anexo I-D'!B99+'DCA-Anexo I-D'!B44+'DCA-Anexo I-D'!B25+'DCA-Anexo I-D'!B27+'DCA-Anexo I-D'!B101+'DCA-Anexo I-D'!B28+'DCA-Anexo I-D'!B40+'DCA-Anexo I-D'!B38+'DCA-Anexo I-D'!B35+'DCA-Anexo I-D'!B39+'DCA-Anexo I-D'!B30+'DCA-Anexo I-D'!B33+'DCA-Anexo I-D'!B43+'DCA-Anexo I-D'!B29+'DCA-Anexo I-D'!B42+'DCA-Anexo I-D'!B41+'DCA-Anexo I-D'!B97 -> 59121162 | C22: =+'DCA-Anexo I-D'!C34+'DCA-Anexo I-D'!C45+'DCA-Anexo I-D'!C36+'DCA-Anexo I-D'!C46+'DCA-Anexo I-D'!C37+'DCA-Anexo I-D'!C26+'DCA-Anexo I-D'!C100+'DCA-Anexo I-D'!C98+'DCA-Anexo I-D'!C31+'DCA-Anexo I-D'!C23+'DCA-Anexo I-D'!C102+'DCA-Anexo I-D'!C24+'DCA-Anexo I-D'!C75+'DCA-Anexo I-D'!C32+'DCA-Anexo I-D'!C99+'DCA-Anexo I-D'!C44+'DCA-Anexo I-D'!C25+'DCA-Anexo I-D'!C27+'DCA-Anexo I-D'!C101+'DCA-Anexo I-D'!C28+'DCA-Anexo I-D'!C40+'DCA-Anexo I-D'!C38+'DCA-Anexo I-D'!C35+'DCA-Anexo I-D'!C39+'DCA-Anexo I-D'!C30+'DCA-Anexo I-D'!C33+'DCA-Anexo I-D'!C43+'DCA-Anexo I-D'!C29+'DCA-Anexo I-D'!C42+'DCA-Anexo I-D'!C41+'DCA-Anexo I-D'!C97 -> 59121162 | D22: =+'DCA-Anexo I-D'!D34+'DCA-Anexo I-D'!D45+'DCA-Anexo I-D'!D36+'DCA-Anexo I-D'!D46+'DCA-Anexo I-D'!D37+'DCA-Anexo I-D'!D26+'DCA-Anexo I-D'!D100+'DCA-Anexo I-D'!D98+'DCA-Anexo I-D'!D31+'DCA-Anexo I-D'!D23+'DCA-Anexo I-D'!D102+'DCA-Anexo I-D'!D24+'DCA-Anexo I-D'!D75+'DCA-Anexo I-D'!D32+'DCA-Anexo I-D'!D99+'DCA-Anexo I-D'!D44+'DCA-Anexo I-D'!D25+'DCA-Anexo I-D'!D27+'DCA-Anexo I-D'!D101+'DCA-Anexo I-D'!D28+'DCA-Anexo I-D'!D40+'DCA-Anexo I-D'!D38+'DCA-Anexo I-D'!D35+'DCA-Anexo I-D'!D39+'DCA-Anexo I-D'!D30+'DCA-Anexo I-D'!D33+'DCA-Anexo I-D'!D43+'DCA-Anexo I-D'!D29+'DCA-Anexo I-D'!D42+'DCA-Anexo I-D'!D41+'DCA-Anexo I-D'!D97 -> 58738355 | E22: =+'DCA-Anexo I-D'!E34+'DCA-Anexo I-D'!E45+'DCA-Anexo I-D'!E36+'DCA-Anexo I-D'!E46+'DCA-Anexo I-D'!E37+'DCA-Anexo I-D'!E26+'DCA-Anexo I-D'!E100+'DCA-Anexo I-D'!E98+'DCA-Anexo I-D'!E31+'DCA-Anexo I-D'!E23+'DCA-Anexo I-D'!E102+'DCA-Anexo I-D'!E24+'DCA-Anexo I-D'!E75+'DCA-Anexo I-D'!E32+'DCA-Anexo I-D'!E99+'DCA-Anexo I-D'!E44+'DCA-Anexo I-D'!E25+'DCA-Anexo I-D'!E27+'DCA-Anexo I-D'!E101+'DCA-Anexo I-D'!E28+'DCA-Anexo I-D'!E40+'DCA-Anexo I-D'!E38+'DCA-Anexo I-D'!E35+'DCA-Anexo I-D'!E39+'DCA-Anexo I-D'!E30+'DCA-Anexo I-D'!E33+'DCA-Anexo I-D'!E43+'DCA-Anexo I-D'!E29+'DCA-Anexo I-D'!E42+'DCA-Anexo I-D'!E41+'DCA-Anexo I-D'!E97 -> 0 | F22: =+'DCA-Anexo I-D'!F34+'DCA-Anexo I-D'!F45+'DCA-Anexo I-D'!F36+'DCA-Anexo I-D'!F46+'DCA-Anexo I-D'!F37+'DCA-Anexo I-D'!F26+'DCA-Anexo I-D'!F100+'DCA-Anexo I-D'!F98+'DCA-Anexo I-D'!F31+'DCA-Anexo I-D'!F23+'DCA-Anexo I-D'!F102+'DCA-Anexo I-D'!F24+'DCA-Anexo I-D'!F75+'DCA-Anexo I-D'!F32+'DCA-Anexo I-D'!F99+'DCA-Anexo I-D'!F44+'DCA-Anexo I-D'!F25+'DCA-Anexo I-D'!F27+'DCA-Anexo I-D'!F101+'DCA-Anexo I-D'!F28+'DCA-Anexo I-D'!F40+'DCA-Anexo I-D'!F38+'DCA-Anexo I-D'!F35+'DCA-Anexo I-D'!F39+'DCA-Anexo I-D'!F30+'DCA-Anexo I-D'!F33+'DCA-Anexo I-D'!F43+'DCA-Anexo I-D'!F29+'DCA-Anexo I-D'!F42+'DCA-Anexo I-D'!F41+'DCA-Anexo I-D'!F97 -> 382806.31
A23: 3.1.20.00.00 - Transferências à União
A24: 3.1.22.00.00 - Execução orçamentária delegada à União
A25: 3.1.30.00.00 - Transferências a Estados e ao Distrito Federal
A26: 3.1.31.00.00 - Transferências a Estados e ao Distrito Federal - fundo a fundo
A27: 3.1.32.00.00 - Execução orçamentária delegada a Estados e ao Distrito Federal
A28: 3.1.35.00.00 - Transferências fundo a fundo aos Estados e ao Distrito Federal à conta de recursos de que tratam os §§ 1º e 2º do art. 24 da Lei Complementar nº 141, de 2012 - Restos a Pagar Cancelados
A29: 3.1.36.00.00 - Transferências fundo a fundo aos Estados e ao Distrito Federal à conta de recursos de que trata o art. 25 da Lei Complementar nº 141, de 2012 - diferença do mínimo não aplicado em exercícios anteriores
A30: 3.1.40.00.00 - Transferências a Municípios
A31: 3.1.41.00.00 - Transferências a Municípios - fundo a fundo
A32: 3.1.42.00.00 - Execução orçamentária delegada a Municípios
A33: 3.1.45.00.00 - Transferências fundo a fundo aos Municípios à conta de recursos de que tratam os §§ 1º e 2º do art. 24 da Lei Complementar nº 141, de 2012 - Restos a Pagar Cancelados
A34: 3.1.46.00.00 - Transferências fundo a fundo aos Municípios à conta de recursos de que trata o art. 25 da Lei Complementar nº 141, de 2012 - diferença do mínimo não aplicado em exercícios anteriores
... A45: 3.1.80.00.00 - Transferências ao Exterior
A46: 3.1.90.00.00 - Aplicações Diretas | B46: =+'DCA-Anexo I-D'!B47+'DCA-Anexo I-D'!B48+'DCA-Anexo I-D'!B49+'DCA-Anexo I-D'!B50+'DCA-Anexo I-D'!B51+'DCA-Anexo I-D'!B52+'DCA-Anexo I-D'!B53+'DCA-Anexo I-D'!B66+'DCA-Anexo I-D'!B67+'DCA-Anexo I-D'!B68+'DCA-Anexo I-D'!B69+'DCA-Anexo I-D'!B70+'DCA-Anexo I-D'!B71+'DCA-Anexo I-D'!B72+'DCA-Anexo I-D'!B73+'DCA-Anexo I-D'!B74+'DCA-Anexo I-D'!B54 -> 59121162 | C46: =+'DCA-Anexo I-D'!C47+'DCA-Anexo I-D'!C48+'DCA-Anexo I-D'!C49+'DCA-Anexo I-D'!C50+'DCA-Anexo I-D'!C51+'DCA-Anexo I-D'!C52+'DCA-Anexo I-D'!C53+'DCA-Anexo I-D'!C66+'DCA-Anexo I-D'!C67+'DCA-Anexo I-D'!C68+'DCA-Anexo I-D'!C69+'DCA-Anexo I-D'!C70+'DCA-Anexo I-D'!C71+'DCA-Anexo I-D'!C72+'DCA-Anexo I-D'!C73+'DCA-Anexo I-D'!C74+'DCA-Anexo I-D'!C54 -> 59121162 | D46: =+'DCA-Anexo I-D'!D47+'DCA-Anexo I-D'!D48+'DCA-Anexo I-D'!D49+'DCA-Anexo I-D'!D50+'DCA-Anexo I-D'!D51+'DCA-Anexo I-D'!D52+'DCA-Anexo I-D'!D53+'DCA-Anexo I-D'!D66+'DCA-Anexo I-D'!D67+'DCA-Anexo I-D'!D68+'DCA-Anexo I-D'!D69+'DCA-Anexo I-D'!D70+'DCA-Anexo I-D'!D71+'DCA-Anexo I-D'!D72+'DCA-Anexo I-D'!D73+'DCA-Anexo I-D'!D74+'DCA-Anexo I-D'!D54 -> 58738355 | E46: =+'DCA-Anexo I-D'!E47+'DCA-Anexo I-D'!E48+'DCA-Anexo I-D'!E49+'DCA-Anexo I-D'!E50+'DCA-Anexo I-D'!E51+'DCA-Anexo I-D'!E52+'DCA-Anexo I-D'!E53+'DCA-Anexo I-D'!E66+'DCA-Anexo I-D'!E67+'DCA-Anexo I-D'!E68+'DCA-Anexo I-D'!E69+'DCA-Anexo I-D'!E70+'DCA-Anexo I-D'!E71+'DCA-Anexo I-D'!E72+'DCA-Anexo I-D'!E73+'DCA-Anexo I-D'!E74+'DCA-Anexo I-D'!E54 -> 0 | F46: =+'DCA-Anexo I-D'!F47+'DCA-Anexo I-D'!F48+'DCA-Anexo I-D'!F49+'DCA-Anexo I-D'!F50+'DCA-Anexo I-D'!F51+'DCA-Anexo I-D'!F52+'DCA-Anexo I-D'!F53+'DCA-Anexo I-D'!F66+'DCA-Anexo I-D'!F67+'DCA-Anexo I-D'!F68+'DCA-Anexo I-D'!F69+'DCA-Anexo I-D'!F70+'DCA-Anexo I-D'!F71+'DCA-Anexo I-D'!F72+'DCA-Anexo I-D'!F73+'DCA-Anexo I-D'!F74+'DCA-Anexo I-D'!F54 -> 382806.31
A47: 3.1.90.01.00 - Aposentadorias do RPPS, Reserva Remunerada e Reformas dos Militares
A48: 3.1.90.03.00 - Pensões do RPPS e do Militar
A49: 3.1.90.04.00 - Contratação por Tempo Determinado | B49: 4552017.7 | C49: 4552017.7 | D49: 4552017.7
A50: 3.1.90.07.00 - Contribuição a Entidades Fechadas de Previdência
A51: 3.1.90.08.00 - Outros Benefícios Assistenciais do Servidor e do Militar
A52: 3.1.90.11.00 - Vencimentos e Vantagens Fixas - Pessoal Civil | B52: 48680902 | C52: 48680902 | D52: 48680902
A53: 3.1.90.12.00 - Vencimentos e Vantagens Fixas - Pessoal Militar
A54: 3.1.90.13.00 - Obrigações Patronais | B54: =+'DCA-Anexo I-D'!B65+'DCA-Anexo I-D'!B58+'DCA-Anexo I-D'!B59+'DCA-Anexo I-D'!B55+'DCA-Anexo I-D'!B56+'DCA-Anexo I-D'!B57+'DCA-Anexo I-D'!B60+'DCA-Anexo I-D'!B61+'DCA-Anexo I-D'!B62+'DCA-Anexo I-D'!B63+'DCA-Anexo I-D'!B64 -> 5842845.2 | C54: =+'DCA-Anexo I-D'!C65+'DCA-Anexo I-D'!C58+'DCA-Anexo I-D'!C59+'DCA-Anexo I-D'!C55+'DCA-Anexo I-D'!C56+'DCA-Anexo I-D'!C57+'DCA-Anexo I-D'!C60+'DCA-Anexo I-D'!C61+'DCA-Anexo I-D'!C62+'DCA-Anexo I-D'!C63+'DCA-Anexo I-D'!C64 -> 5842845.2 | D54: =+'DCA-Anexo I-D'!D65+'DCA-Anexo I-D'!D58+'DCA-Anexo I-D'!D59+'DCA-Anexo I-D'!D55+'DCA-Anexo I-D'!D56+'DCA-Anexo I-D'!D57+'DCA-Anexo I-D'!D60+'DCA-Anexo I-D'!D61+'DCA-Anexo I-D'!D62+'DCA-Anexo I-D'!D63+'DCA-Anexo I-D'!D64 -> 5460038.9 | E54: =+'DCA-Anexo I-D'!E65+'DCA-Anexo I-D'!E58+'DCA-Anexo I-D'!E59+'DCA-Anexo I-D'!E55+'DCA-Anexo I-D'!E56+'DCA-Anexo I-D'!E57+'DCA-Anexo I-D'!E60+'DCA-Anexo I-D'!E61+'DCA-Anexo I-D'!E62+'DCA-Anexo I-D'!E63+'DCA-Anexo I-D'!E64 -> 0 | F54: =+'DCA-Anexo I-D'!F65+'DCA-Anexo I-D'!F58+'DCA-Anexo I-D'!F59+'DCA-Anexo I-D'!F55+'DCA-Anexo I-D'!F56+'DCA-Anexo I-D'!F57+'DCA-Anexo I-D'!F60+'DCA-Anexo I-D'!F61+'DCA-Anexo I-D'!F62+'DCA-Anexo I-D'!F63+'DCA-Anexo I-D'!F64 -> 382806.31
A55: 3.1.90.13.01 - FGTS
A56: 3.1.90.13.02 - Contribuições Previdenciárias - INSS | B56: 5842845.2 | C56: 5842845.2 | D56: 5460038.9 | F56: 382806.31
A57: 3.1.90.13.04 - Contribuição de salário-educação
A58: 3.1.90.13.07 - Contrato por Tempo Determinado
A59: 3.1.90.13.08 - Contribuições Previdenciárias - RPPS - Pessoal Ativo
A60: 3.1.90.13.09 - Seguros de acidentes do trabalho
A61: 3.1.90.13.10 - Contribuições previdenciárias - RPPS - pessoal inativo
A62: 3.1.90.13.11 - FGTS - PDV
A63: 3.1.90.13.18 - Contribuição para o PIS/PASEP s/ folha Pagto.
A64: 3.1.90.13.40 - Encargos de pessoal requisitado de outros Entes
A65: 3.1.90.13.99 - Outras Obrigações Patronais
A66: 3.1.90.16.00 - Outras Despesas Variáveis - Pessoal Civil
A67: 3.1.90.17.00 - Outras Despesas Variáveis - Pessoal Militar
A68: 3.1.90.67.00 - Depósitos Compulsórios
A69: 3.1.90.86.00 - Compensações a Regimes de Previdência
A70: 3.1.90.91.00 - Sentenças Judiciais | B70: 11840.4 | C70: 11840.4 | D70: 11840.4
A71: 3.1.90.92.00 - Despesas de Exercícios Anteriores | B71: 13551.08 | C71: 13551.08 | D71: 13551.08
A72: 3.1.90.94.00 - Indenizações e Restituições Trabalhistas | B72: 20004.99 | C72: 20004.99 | D72: 20004.99
A73: 3.1.90.96.00 - Ressarcimento de Despesas de Pessoal Requisitado
A74: 3.1.90.99.00 - A Classificar
A75: 3.1.91.00.00 - Aplicação Direta Decorrente de Operação entre Órgãos, Fundos e Entidades Integrantes dos Orçamentos Fiscal e da Seguridade Social | B75: =+'DCA-Anexo I-D'!B94+'DCA-Anexo I-D'!B76+'DCA-Anexo I-D'!B92+'DCA-Anexo I-D'!B95+'DCA-Anexo I-D'!B93+'DCA-Anexo I-D'!B78+'DCA-Anexo I-D'!B96+'DCA-Anexo I-D'!B77+'DCA-Anexo I-D'!B91 -> 0 | C75: =+'DCA-Anexo I-D'!C94+'DCA-Anexo I-D'!C76+'DCA-Anexo I-D'!C92+'DCA-Anexo I-D'!C95+'DCA-Anexo I-D'!C93+'DCA-Anexo I-D'!C78+'DCA-Anexo I-D'!C96+'DCA-Anexo I-D'!C77+'DCA-Anexo I-D'!C91 -> 0 | D75: =+'DCA-Anexo I-D'!D94+'DCA-Anexo I-D'!D76+'DCA-Anexo I-D'!D92+'DCA-Anexo I-D'!D95+'DCA-Anexo I-D'!D93+'DCA-Anexo I-D'!D78+'DCA-Anexo I-D'!D96+'DCA-Anexo I-D'!D77+'DCA-Anexo I-D'!D91 -> 0 | E75: =+'DCA-Anexo I-D'!E94+'DCA-Anexo I-D'!E76+'DCA-Anexo I-D'!E92+'DCA-Anexo I-D'!E95+'DCA-Anexo I-D'!E93+'DCA-Anexo I-D'!E78+'DCA-Anexo I-D'!E96+'DCA-Anexo I-D'!E77+'DCA-Anexo I-D'!E91 -> 0 | F75: =+'DCA-Anexo I-D'!F94+'DCA-Anexo I-D'!F76+'DCA-Anexo I-D'!F92+'DCA-Anexo I-D'!F95+'DCA-Anexo I-D'!F93+'DCA-Anexo I-D'!F78+'DCA-Anexo I-D'!F96+'DCA-Anexo I-D'!F77+'DCA-Anexo I-D'!F91 -> 0
A76: 3.1.91.04.00 - Contratação por Tempo Determinado
A77: 3.1.91.08.00 - Outros Benefícios Assistenciais do Servidor e do Militar
A78: 3.1.91.13.00 - Contribuições Patronais | B78: =+'DCA-Anexo I-D'!B79+'DCA-Anexo I-D'!B80+'DCA-Anexo I-D'!B81+'DCA-Anexo I-D'!B82+'DCA-Anexo I-D'!B83+'DCA-Anexo I-D'!B84+'DCA-Anexo I-D'!B85+'DCA-Anexo I-D'!B86+'DCA-Anexo I-D'!B87+'DCA-Anexo I-D'!B88+'DCA-Anexo I-D'!B89+'DCA-Anexo I-D'!B90 -> 0 | C78: =+'DCA-Anexo I-D'!C79+'DCA-Anexo I-D'!C80+'DCA-Anexo I-D'!C81+'DCA-Anexo I-D'!C82+'DCA-Anexo I-D'!C83+'DCA-Anexo I-D'!C84+'DCA-Anexo I-D'!C85+'DCA-Anexo I-D'!C86+'DCA-Anexo I-D'!C87+'DCA-Anexo I-D'!C88+'DCA-Anexo I-D'!C89+'DCA-Anexo I-D'!C90 -> 0 | D78: =+'DCA-Anexo I-D'!D79+'DCA-Anexo I-D'!D80+'DCA-Anexo I-D'!D81+'DCA-Anexo I-D'!D82+'DCA-Anexo I-D'!D83+'DCA-Anexo I-D'!D84+'DCA-Anexo I-D'!D85+'DCA-Anexo I-D'!D86+'DCA-Anexo I-D'!D87+'DCA-Anexo I-D'!D88+'DCA-Anexo I-D'!D89+'DCA-Anexo I-D'!D90 -> 0 | E78: =+'DCA-Anexo I-D'!E79+'DCA-Anexo I-D'!E80+'DCA-Anexo I-D'!E81+'DCA-Anexo I-D'!E82+'DCA-Anexo I-D'!E83+'DCA-Anexo I-D'!E84+'DCA-Anexo I-D'!E85+'DCA-Anexo I-D'!E86+'DCA-Anexo I-D'!E87+'DCA-Anexo I-D'!E88+'DCA-Anexo I-D'!E89+'DCA-Anexo I-D'!E90 -> 0 | F78: =+'DCA-Anexo I-D'!F79+'DCA-Anexo I-D'!F80+'DCA-Anexo I-D'!F81+'DCA-Anexo I-D'!F82+'DCA-Anexo I-D'!F83+'DCA-Anexo I-D'!F84+'DCA-Anexo I-D'!F85+'DCA-Anexo I-D'!F86+'DCA-Anexo I-D'!F87+'DCA-Anexo I-D'!F88+'DCA-Anexo I-D'!F89+'DCA-Anexo I-D'!F90 -> 0
A79: 3.1.91.13.02 - Contribuições previdenciárias - INSS
A80: 3.1.91.13.04 - Contribuição de salário-educação
A81: 3.1.91.13.08 - Contribuições previdenciárias - RPPS - pessoal ativo - plano previdenciário
A82: 3.1.91.13.09 - Seguros de acidentes do trabalho
A83: 3.1.91.13.10 - Contribuições previdenciárias - RPPS - pessoal inativo e pensionista - plano previdenciário
A84: 3.1.91.13.11 - Contribuições previdenciárias - RPPS - pessoal ativo - plano financeiro
A85: 3.1.91.13.12 - Contribuições previdenciárias - RPPS - pessoal inativo e pensionista - plano financeiro
A86: 3.1.91.13.20 - Alíquota suplementar de contribuição previdenciária - pessoal ativo - plano previdenciário
A87: 3.1.91.13.21 - Alíquota suplementar de contribuição previdenciária - pessoal inativo e pensionista - plano previdenciário
A88: 3.1.91.13.22 - Alíquota suplementar de contribuição previdenciária - pessoal ativo - plano financeiro
A89: 3.1.91.13.23 - Alíquota suplementar de contribuição previdenciária - pessoal inativo e pensionista - plano financeiro
A90: 3.1.91.13.99 - Outras Obrigações Patronais - Intraorçamentária
... A102: 3.1.99.00.00 - A Definir
A103: 3.2.00.00.00 - Juros e Encargos da Dívida | B103: =+'DCA-Anexo I-D'!B104+'DCA-Anexo I-D'!B105+'DCA-Anexo I-D'!B106+'DCA-Anexo I-D'!B107+'DCA-Anexo I-D'!B108+'DCA-Anexo I-D'!B109+'DCA-Anexo I-D'!B110+'DCA-Anexo I-D'!B111+'DCA-Anexo I-D'!B112+'DCA-Anexo I-D'!B113+'DCA-Anexo I-D'!B114+'DCA-Anexo I-D'!B115+'DCA-Anexo I-D'!B116+'DCA-Anexo I-D'!B117+'DCA-Anexo I-D'!B118+'DCA-Anexo I-D'!B119+'DCA-Anexo I-D'!B121+'DCA-Anexo I-D'!B124+'DCA-Anexo I-D'!B125+'DCA-Anexo I-D'!B126+'DCA-Anexo I-D'!B138+'DCA-Anexo I-D'!B140+'DCA-Anexo I-D'!B141+'DCA-Anexo I-D'!B127+'DCA-Anexo I-D'!B142+'DCA-Anexo I-D'!B143+'DCA-Anexo I-D'!B144+'DCA-Anexo I-D'!B120+'DCA-Anexo I-D'!B122+'DCA-Anexo I-D'!B123+'DCA-Anexo I-D'!B139 -> 0 | C103: =+'DCA-Anexo I-D'!C104+'DCA-Anexo I-D'!C105+'DCA-Anexo I-D'!C106+'DCA-Anexo I-D'!C107+'DCA-Anexo I-D'!C108+'DCA-Anexo I-D'!C109+'DCA-Anexo I-D'!C110+'DCA-Anexo I-D'!C111+'DCA-Anexo I-D'!C112+'DCA-Anexo I-D'!C113+'DCA-Anexo I-D'!C114+'DCA-Anexo I-D'!C115+'DCA-Anexo I-D'!C116+'DCA-Anexo I-D'!C117+'DCA-Anexo I-D'!C118+'DCA-Anexo I-D'!C119+'DCA-Anexo I-D'!C121+'DCA-Anexo I-D'!C124+'DCA-Anexo I-D'!C125+'DCA-Anexo I-D'!C126+'DCA-Anexo I-D'!C138+'DCA-Anexo I-D'!C140+'DCA-Anexo I-D'!C141+'DCA-Anexo I-D'!C127+'DCA-Anexo I-D'!C142+'DCA-Anexo I-D'!C143+'DCA-Anexo I-D'!C144+'DCA-Anexo I-D'!C120+'DCA-Anexo I-D'!C122+'DCA-Anexo I-D'!C123+'DCA-Anexo I-D'!C139 -> 0 | D103: =+'DCA-Anexo I-D'!D104+'DCA-Anexo I-D'!D105+'DCA-Anexo I-D'!D106+'DCA-Anexo I-D'!D107+'DCA-Anexo I-D'!D108+'DCA-Anexo I-D'!D109+'DCA-Anexo I-D'!D110+'DCA-Anexo I-D'!D111+'DCA-Anexo I-D'!D112+'DCA-Anexo I-D'!D113+'DCA-Anexo I-D'!D114+'DCA-Anexo I-D'!D115+'DCA-Anexo I-D'!D116+'DCA-Anexo I-D'!D117+'DCA-Anexo I-D'!D118+'DCA-Anexo I-D'!D119+'DCA-Anexo I-D'!D121+'DCA-Anexo I-D'!D124+'DCA-Anexo I-D'!D125+'DCA-Anexo I-D'!D126+'DCA-Anexo I-D'!D138+'DCA-Anexo I-D'!D140+'DCA-Anexo I-D'!D141+'DCA-Anexo I-D'!D127+'DCA-Anexo I-D'!D142+'DCA-Anexo I-D'!D143+'DCA-Anexo I-D'!D144+'DCA-Anexo I-D'!D120+'DCA-Anexo I-D'!D122+'DCA-Anexo I-D'!D123+'DCA-Anexo I-D'!D139 -> 0 | E103: =+'DCA-Anexo I-D'!E104+'DCA-Anexo I-D'!E105+'DCA-Anexo I-D'!E106+'DCA-Anexo I-D'!E107+'DCA-Anexo I-D'!E108+'DCA-Anexo I-D'!E109+'DCA-Anexo I-D'!E110+'DCA-Anexo I-D'!E111+'DCA-Anexo I-D'!E112+'DCA-Anexo I-D'!E113+'DCA-Anexo I-D'!E114+'DCA-Anexo I-D'!E115+'DCA-Anexo I-D'!E116+'DCA-Anexo I-D'!E117+'DCA-Anexo I-D'!E118+'DCA-Anexo I-D'!E119+'DCA-Anexo I-D'!E121+'DCA-Anexo I-D'!E124+'DCA-Anexo I-D'!E125+'DCA-Anexo I-D'!E126+'DCA-Anexo I-D'!E138+'DCA-Anexo I-D'!E140+'DCA-Anexo I-D'!E141+'DCA-Anexo I-D'!E127+'DCA-Anexo I-D'!E142+'DCA-Anexo I-D'!E143+'DCA-Anexo I-D'!E144+'DCA-Anexo I-D'!E120+'DCA-Anexo I-D'!E122+'DCA-Anexo I-D'!E123+'DCA-Anexo I-D'!E139 -> 0 | F103: =+'DCA-Anexo I-D'!F104+'DCA-Anexo I-D'!F105+'DCA-Anexo I-D'!F106+'DCA-Anexo I-D'!F107+'DCA-Anexo I-D'!F108+'DCA-Anexo I-D'!F109+'DCA-Anexo I-D'!F110+'DCA-Anexo I-D'!F111+'DCA-Anexo I-D'!F112+'DCA-Anexo I-D'!F113+'DCA-Anexo I-D'!F114+'DCA-Anexo I-D'!F115+'DCA-Anexo I-D'!F116+'DCA-Anexo I-D'!F117+'DCA-Anexo I-D'!F118+'DCA-Anexo I-D'!F119+'DCA-Anexo I-D'!F121+'DCA-Anexo I-D'!F124+'DCA-Anexo I-D'!F125+'DCA-Anexo I-D'!F126+'DCA-Anexo I-D'!F138+'DCA-Anexo I-D'!F140+'DCA-Anexo I-D'!F141+'DCA-Anexo I-D'!F127+'DCA-Anexo I-D'!F142+'DCA-Anexo I-D'!F143+'DCA-Anexo I-D'!F144+'DCA-Anexo I-D'!F120+'DCA-Anexo I-D'!F122+'DCA-Anexo I-D'!F123+'DCA-Anexo I-D'!F139 -> 0
A104: 3.2.20.00.00 - Transferências à União
A105: 3.2.22.00.00 - Execução orçamentária delegada à União
A106: 3.2.30.00.00 - Transferências a Estados e ao Distrito Federal
A107: 3.2.31.00.00 - Transferências a Estados e ao Distrito Federal - fundo a fundo
A108: 3.2.32.00.00 - Execução orçamentária delegada a Estados e ao Distrito Federal
A109: 3.2.35.00.00 - Transferências fundo a fundo aos Estados e ao Distrito Federal à conta de recursos de que tratam os §§ 1º e 2º do Art. 24 da Lei Complementar nº 141, de 2012
A110: 3.2.36.00.00 - Transferências fundo a fundo aos Estados e ao Distrito Federal à conta de recursos de que trata o Art. 25 da Lei Complementar nº 141, de 2012
A111: 3.2.40.00.00 - Transferências a Municípios
A112: 3.2.41.00.00 - Transferências a Municípios - fundo a fundo
A113: 3.2.42.00.00 - Execução orçamentária delegada a Municípios
A114: 3.2.45.00.00 - Transferências fundo a fundo aos Municípios à conta de recursos de que tratam os §§ 1º e 2º do Art. 24 da Lei Complementar nº 141, de 2012
A115: 3.2.46.00.00 - Transferências fundo a fundo aos Municípios à conta de recursos de que trata o Art. 25 da Lei Complementar nº 141, de 2012
... A126: 3.2.80.00.00 - Transferências ao exterior
A127: 3.2.90.00.00 - Aplicações Diretas | B127: =+'DCA-Anexo I-D'!B134+'DCA-Anexo I-D'!B137+'DCA-Anexo I-D'!B136+'DCA-Anexo I-D'!B132+'DCA-Anexo I-D'!B133+'DCA-Anexo I-D'!B129+'DCA-Anexo I-D'!B135+'DCA-Anexo I-D'!B128+'DCA-Anexo I-D'!B130+'DCA-Anexo I-D'!B131 -> 0 | C127: =+'DCA-Anexo I-D'!C134+'DCA-Anexo I-D'!C137+'DCA-Anexo I-D'!C136+'DCA-Anexo I-D'!C132+'DCA-Anexo I-D'!C133+'DCA-Anexo I-D'!C129+'DCA-Anexo I-D'!C135+'DCA-Anexo I-D'!C128+'DCA-Anexo I-D'!C130+'DCA-Anexo I-D'!C131 -> 0 | D127: =+'DCA-Anexo I-D'!D134+'DCA-Anexo I-D'!D137+'DCA-Anexo I-D'!D136+'DCA-Anexo I-D'!D132+'DCA-Anexo I-D'!D133+'DCA-Anexo I-D'!D129+'DCA-Anexo I-D'!D135+'DCA-Anexo I-D'!D128+'DCA-Anexo I-D'!D130+'DCA-Anexo I-D'!D131 -> 0 | E127: =+'DCA-Anexo I-D'!E134+'DCA-Anexo I-D'!E137+'DCA-Anexo I-D'!E136+'DCA-Anexo I-D'!E132+'DCA-Anexo I-D'!E133+'DCA-Anexo I-D'!E129+'DCA-Anexo I-D'!E135+'DCA-Anexo I-D'!E128+'DCA-Anexo I-D'!E130+'DCA-Anexo I-D'!E131 -> 0 | F127: =+'DCA-Anexo I-D'!F134+'DCA-Anexo I-D'!F137+'DCA-Anexo I-D'!F136+'DCA-Anexo I-D'!F132+'DCA-Anexo I-D'!F133+'DCA-Anexo I-D'!F129+'DCA-Anexo I-D'!F135+'DCA-Anexo I-D'!F128+'DCA-Anexo I-D'!F130+'DCA-Anexo I-D'!F131 -> 0
A128: 3.2.90.21.00 - Juros sobre a Dívida por Contrato
A129: 3.2.90.22.00 - Outros Encargos sobre a Dívida por Contrato
A130: 3.2.90.23.00 - Juros, Deságios e Descontos da Dívida Mobiliária
A131: 3.2.90.24.00 - Outros Encargos sobre a Dívida Mobiliária
A132: 3.2.90.25.00 - Encargos sobre Operações de Crédito por Antecipação da Receita
A133: 3.2.90.26.00 - Obrigações Decorrentes de Política Monetária
A134: 3.2.90.91.00 - Sentenças Judiciais
...

Sheet DCA-Anexo I-E
A2: QDCC
A3: BALANÇO ANUAL (DCA)
A4: VERSÃO: v14
A5: VIGÊNCIA: 05/01/2026
A7: Ente: 2908101 - Cocos/BA
A8: Poder: E - Executivo
A9: Instituição: 4063 - Prefeitura Municipal de Cocos - BA
A10: Exercício: 2025
A11: Periodicidade: ANUAL
A12: Período: Período único (anual)
A14: Grupo: Balanço Orçamentário - Despesas por Função
A15: Quadro: Despesas por Função
A16: Rótulo: Total Geral da Despesa por Função
A17: Despesas por Função | B17: Execução da Despesa
B18: Despesas Empenhadas | C18: Despesas Liquidadas | D18: Despesas Pagas | E18: Inscrição de Restos a Pagar Não Processados | F18: Inscrição de Restos a Pagar Processados
A19: Despesas Exceto Intraorçamentárias | B19: =+'DCA-Anexo I-E'!B20+'DCA-Anexo I-E'!B25+'DCA-Anexo I-E'!B30+'DCA-Anexo I-E'!B35+'DCA-Anexo I-E'!B48+'DCA-Anexo I-E'!B54+'DCA-Anexo I-E'!B60+'DCA-Anexo I-E'!B65+'DCA-Anexo I-E'!B74+'DCA-Anexo I-E'!B81+'DCA-Anexo I-E'!B90+'DCA-Anexo I-E'!B97+'DCA-Anexo I-E'!B108+'DCA-Anexo I-E'!B113+'DCA-Anexo I-E'!B119+'DCA-Anexo I-E'!B125+'DCA-Anexo I-E'!B130+'DCA-Anexo I-E'!B135+'DCA-Anexo I-E'!B143+'DCA-Anexo I-E'!B149+'DCA-Anexo I-E'!B157+'DCA-Anexo I-E'!B162+'DCA-Anexo I-E'!B170+'DCA-Anexo I-E'!B178+'DCA-Anexo I-E'!B183+'DCA-Anexo I-E'!B190+'DCA-Anexo I-E'!B198+'DCA-Anexo I-E'!B204 -> 1.4527209e+08 | C19: =+'DCA-Anexo I-E'!C20+'DCA-Anexo I-E'!C25+'DCA-Anexo I-E'!C30+'DCA-Anexo I-E'!C35+'DCA-Anexo I-E'!C48+'DCA-Anexo I-E'!C54+'DCA-Anexo I-E'!C60+'DCA-Anexo I-E'!C65+'DCA-Anexo I-E'!C74+'DCA-Anexo I-E'!C81+'DCA-Anexo I-E'!C90+'DCA-Anexo I-E'!C97+'DCA-Anexo I-E'!C108+'DCA-Anexo I-E'!C113+'DCA-Anexo I-E'!C119+'DCA-Anexo I-E'!C125+'DCA-Anexo I-E'!C130+'DCA-Anexo I-E'!C135+'DCA-Anexo I-E'!C143+'DCA-Anexo I-E'!C149+'DCA-Anexo I-E'!C157+'DCA-Anexo I-E'!C162+'DCA-Anexo I-E'!C170+'DCA-Anexo I-E'!C178+'DCA-Anexo I-E'!C183+'DCA-Anexo I-E'!C190+'DCA-Anexo I-E'!C198+'DCA-Anexo I-E'!C204 -> 1.4527209e+08 | D19: =+'DCA-Anexo I-E'!D20+'DCA-Anexo I-E'!D25+'DCA-Anexo I-E'!D30+'DCA-Anexo I-E'!D35+'DCA-Anexo I-E'!D48+'DCA-Anexo I-E'!D54+'DCA-Anexo I-E'!D60+'DCA-Anexo I-E'!D65+'DCA-Anexo I-E'!D74+'DCA-Anexo I-E'!D81+'DCA-Anexo I-E'!D90+'DCA-Anexo I-E'!D97+'DCA-Anexo I-E'!D108+'DCA-Anexo I-E'!D113+'DCA-Anexo I-E'!D119+'DCA-Anexo I-E'!D125+'DCA-Anexo I-E'!D130+'DCA-Anexo I-E'!D135+'DCA-Anexo I-E'!D143+'DCA-Anexo I-E'!D149+'DCA-Anexo I-E'!D157+'DCA-Anexo I-E'!D162+'DCA-Anexo I-E'!D170+'DCA-Anexo I-E'!D178+'DCA-Anexo I-E'!D183+'DCA-Anexo I-E'!D190+'DCA-Anexo I-E'!D198+'DCA-Anexo I-E'!D204 -> 1.3632376e+08 | E19: =+'DCA-Anexo I-E'!E20+'DCA-Anexo I-E'!E25+'DCA-Anexo I-E'!E30+'DCA-Anexo I-E'!E35+'DCA-Anexo I-E'!E48+'DCA-Anexo I-E'!E54+'DCA-Anexo I-E'!E60+'DCA-Anexo I-E'!E65+'DCA-Anexo I-E'!E74+'DCA-Anexo I-E'!E81+'DCA-Anexo I-E'!E90+'DCA-Anexo I-E'!E97+'DCA-Anexo I-E'!E108+'DCA-Anexo I-E'!E113+'DCA-Anexo I-E'!E119+'DCA-Anexo I-E'!E125+'DCA-Anexo I-E'!E130+'DCA-Anexo I-E'!E135+'DCA-Anexo I-E'!E143+'DCA-Anexo I-E'!E149+'DCA-Anexo I-E'!E157+'DCA-Anexo I-E'!E162+'DCA-Anexo I-E'!E170+'DCA-Anexo I-E'!E178+'DCA-Anexo I-E'!E183+'DCA-Anexo I-E'!E190+'DCA-Anexo I-E'!E198+'DCA-Anexo I-E'!E204 -> 0 | F19: =+'DCA-Anexo I-E'!F20+'DCA-Anexo I-E'!F25+'DCA-Anexo I-E'!F30+'DCA-Anexo I-E'!F35+'DCA-Anexo I-E'!F48+'DCA-Anexo I-E'!F54+'DCA-Anexo I-E'!F60+'DCA-Anexo I-E'!F65+'DCA-Anexo I-E'!F74+'DCA-Anexo I-E'!F81+'DCA-Anexo I-E'!F90+'DCA-Anexo I-E'!F97+'DCA-Anexo I-E'!F108+'DCA-Anexo I-E'!F113+'DCA-Anexo I-E'!F119+'DCA-Anexo I-E'!F125+'DCA-Anexo I-E'!F130+'DCA-Anexo I-E'!F135+'DCA-Anexo I-E'!F143+'DCA-Anexo I-E'!F149+'DCA-Anexo I-E'!F157+'DCA-Anexo I-E'!F162+'DCA-Anexo I-E'!F170+'DCA-Anexo I-E'!F178+'DCA-Anexo I-E'!F183+'DCA-Anexo I-E'!F190+'DCA-Anexo I-E'!F198+'DCA-Anexo I-E'!F204 -> 8948337.3
A20: 01 - Legislativa | B20: =+'DCA-Anexo I-E'!B21+'DCA-Anexo I-E'!B22+'DCA-Anexo I-E'!B24+'DCA-Anexo I-E'!B23 -> 4989007.9 | C20: =+'DCA-Anexo I-E'!C21+'DCA-Anexo I-E'!C22+'DCA-Anexo I-E'!C24+'DCA-Anexo I-E'!C23 -> 4989007.9 | D20: =+'DCA-Anexo I-E'!D21+'DCA-Anexo I-E'!D22+'DCA-Anexo I-E'!D24+'DCA-Anexo I-E'!D23 -> 4989007.9 | E20: =+'DCA-Anexo I-E'!E21+'DCA-Anexo I-E'!E22+'DCA-Anexo I-E'!E24+'DCA-Anexo I-E'!E23 -> 0 | F20: =+'DCA-Anexo I-E'!F21+'DCA-Anexo I-E'!F22+'DCA-Anexo I-E'!F24+'DCA-Anexo I-E'!F23 -> 0
A21: 01.031 - Ação Legislativa | B21: 4989007.9 | C21: 4989007.9 | D21: 4989007.9
A22: 01.032 - Controle Externo
A23: 01.122 - Administração Geral
A24: FU01 - Demais Subfunções
A25: 02 - Judiciária | B25: =+'DCA-Anexo I-E'!B26+'DCA-Anexo I-E'!B27+'DCA-Anexo I-E'!B29+'DCA-Anexo I-E'!B28 -> 460995.4 | C25: =+'DCA-Anexo I-E'!C26+'DCA-Anexo I-E'!C27+'DCA-Anexo I-E'!C29+'DCA-Anexo I-E'!C28 -> 460995.4 | D25: =+'DCA-Anexo I-E'!D26+'DCA-Anexo I-E'!D27+'DCA-Anexo I-E'!D29+'DCA-Anexo I-E'!D28 -> 358595.4 | E25: =+'DCA-Anexo I-E'!E26+'DCA-Anexo I-E'!E27+'DCA-Anexo I-E'!E29+'DCA-Anexo I-E'!E28 -> 0 | F25: =+'DCA-Anexo I-E'!F26+'DCA-Anexo I-E'!F27+'DCA-Anexo I-E'!F29+'DCA-Anexo I-E'!F28 -> 102400
A26: 02.061 - Ação Judiciária | B26: 460995.4 | C26: 460995.4 | D26: 358595.4 | F26: 102400
A27: 02.062 - Defesa do Interesse Público no Processo Judiciário
A28: 02.122 - Administração Geral
A29: FU02 - Demais Subfunções
A30: 03 - Essencial à Justiça | B30: =+'DCA-Anexo I-E'!B31+'DCA-Anexo I-E'!B32+'DCA-Anexo I-E'!B34+'DCA-Anexo I-E'!B33 -> 0 | C30: =+'DCA-Anexo I-E'!C31+'DCA-Anexo I-E'!C32+'DCA-Anexo I-E'!C34+'DCA-Anexo I-E'!C33 -> 0 | D30: =+'DCA-Anexo I-E'!D31+'DCA-Anexo I-E'!D32+'DCA-Anexo I-E'!D34+'DCA-Anexo I-E'!D33 -> 0 | E30: =+'DCA-Anexo I-E'!E31+'DCA-Anexo I-E'!E32+'DCA-Anexo I-E'!E34+'DCA-Anexo I-E'!E33 -> 0 | F30: =+'DCA-Anexo I-E'!F31+'DCA-Anexo I-E'!F32+'DCA-Anexo I-E'!F34+'DCA-Anexo I-E'!F33 -> 0
A31: 03.091 - Defesa da Ordem Jurídica
A32: 03.092 - Representação Judicial e Extrajudicial
A33: 03.122 - Administração Geral
A34: FU03 - Demais Subfunções
A35: 04 - Administração | B35: =+'DCA-Anexo I-E'!B36+'DCA-Anexo I-E'!B37+'DCA-Anexo I-E'!B38+'DCA-Anexo I-E'!B39+'DCA-Anexo I-E'!B40+'DCA-Anexo I-E'!B41+'DCA-Anexo I-E'!B42+'DCA-Anexo I-E'!B43+'DCA-Anexo I-E'!B44+'DCA-Anexo I-E'!B45+'DCA-Anexo I-E'!B46+'DCA-Anexo I-E'!B47 -> 12767311 | C35: =+'DCA-Anexo I-E'!C36+'DCA-Anexo I-E'!C37+'DCA-Anexo I-E'!C38+'DCA-Anexo I-E'!C39+'DCA-Anexo I-E'!C40+'DCA-Anexo I-E'!C41+'DCA-Anexo I-E'!C42+'DCA-Anexo I-E'!C43+'DCA-Anexo I-E'!C44+'DCA-Anexo I-E'!C45+'DCA-Anexo I-E'!C46+'DCA-Anexo I-E'!C47 -> 12767311 | D35: =+'DCA-Anexo I-E'!D36+'DCA-Anexo I-E'!D37+'DCA-Anexo I-E'!D38+'DCA-Anexo I-E'!D39+'DCA-Anexo I-E'!D40+'DCA-Anexo I-E'!D41+'DCA-Anexo I-E'!D42+'DCA-Anexo I-E'!D43+'DCA-Anexo I-E'!D44+'DCA-Anexo I-E'!D45+'DCA-Anexo I-E'!D46+'DCA-Anexo I-E'!D47 -> 12360224 | E35: =+'DCA-Anexo I-E'!E36+'DCA-Anexo I-E'!E37+'DCA-Anexo I-E'!E38+'DCA-Anexo I-E'!E39+'DCA-Anexo I-E'!E40+'DCA-Anexo I-E'!E41+'DCA-Anexo I-E'!E42+'DCA-Anexo I-E'!E43+'DCA-Anexo I-E'!E44+'DCA-Anexo I-E'!E45+'DCA-Anexo I-E'!E46+'DCA-Anexo I-E'!E47 -> 0 | F35: =+'DCA-Anexo I-E'!F36+'DCA-Anexo I-E'!F37+'DCA-Anexo I-E'!F38+'DCA-Anexo I-E'!F39+'DCA-Anexo I-E'!F40+'DCA-Anexo I-E'!F41+'DCA-Anexo I-E'!F42+'DCA-Anexo I-E'!F43+'DCA-Anexo I-E'!F44+'DCA-Anexo I-E'!F45+'DCA-Anexo I-E'!F46+'DCA-Anexo I-E'!F47 -> 407086.53
A36: 04.121 - Planejamento e Orçamento
A37: 04.122 - Administração Geral | B37: 11177423 | C37: 11177423 | D37: 10842416 | F37: 335007.53
A38: 04.123 - Administração Financeira | B38: 1589887.7 | C38: 1589887.7 | D38: 1517808.7 | F38: 72079
A39: 04.124 - Controle Interno
A40: 04.125 - Normatização e Fiscalização
A41: 04.126 - Tecnologia da Informação
A42: 04.127 - Ordenamento Territorial
A43: 04.128 - Formação de Recursos Humanos
A44: 04.129 - Administração de Receitas
A45: 04.130 - Administração de Concessões
A46: 04.131 - Comunicação Social
A47: FU04 - Demais Subfunções
A48: 05 - Defesa Nacional | B48: =+'DCA-Anexo I-E'!B49+'DCA-Anexo I-E'!B50+'DCA-Anexo I-E'!B51+'DCA-Anexo I-E'!B53+'DCA-Anexo I-E'!B52 -> 0 | C48: =+'DCA-Anexo I-E'!C49+'DCA-Anexo I-E'!C50+'DCA-Anexo I-E'!C51+'DCA-Anexo I-E'!C53+'DCA-Anexo I-E'!C52 -> 0 | D48: =+'DCA-Anexo I-E'!D49+'DCA-Anexo I-E'!D50+'DCA-Anexo I-E'!D51+'DCA-Anexo I-E'!D53+'DCA-Anexo I-E'!D52 -> 0 | E48: =+'DCA-Anexo I-E'!E49+'DCA-Anexo I-E'!E50+'DCA-Anexo I-E'!E51+'DCA-Anexo I-E'!E53+'DCA-Anexo I-E'!E52 -> 0 | F48: =+'DCA-Anexo I-E'!F49+'DCA-Anexo I-E'!F50+'DCA-Anexo I-E'!F51+'DCA-Anexo I-E'!F53+'DCA-Anexo I-E'!F52 -> 0
A49: 05.151 - Defesa Aérea
A50: 05.152 - Defesa Naval
A51: 05.153 - Defesa Terrestre
A52: 05.122 - Administração Geral
A53: FU05 - Demais Subfunções
A54: 06 - Segurança Pública | B54: =+'DCA-Anexo I-E'!B55+'DCA-Anexo I-E'!B56+'DCA-Anexo I-E'!B57+'DCA-Anexo I-E'!B59+'DCA-Anexo I-E'!B58 -> 1957175.6 | C54: =+'DCA-Anexo I-E'!C55+'DCA-Anexo I-E'!C56+'DCA-Anexo I-E'!C57+'DCA-Anexo I-E'!C59+'DCA-Anexo I-E'!C58 -> 1957175.6 | D54: =+'DCA-Anexo I-E'!D55+'DCA-Anexo I-E'!D56+'DCA-Anexo I-E'!D57+'DCA-Anexo I-E'!D59+'DCA-Anexo I-E'!D58 -> 1939453.8 | E54: =+'DCA-Anexo I-E'!E55+'DCA-Anexo I-E'!E56+'DCA-Anexo I-E'!E57+'DCA-Anexo I-E'!E59+'DCA-Anexo I-E'!E58 -> 0 | F54: =+'DCA-Anexo I-E'!F55+'DCA-Anexo I-E'!F56+'DCA-Anexo I-E'!F57+'DCA-Anexo I-E'!F59+'DCA-Anexo I-E'!F58 -> 17721.85
A55: 06.181 - Policiamento | B55: 1957175.6 | C55: 1957175.6 | D55: 1939453.8 | F55: 17721.85
A56: 06.182 - Defesa Civil
A57: 06.183 - Informação e Inteligência
A58: 06.122 - Administração Geral
A59: FU06 - Demais Subfunções
A60: 07 - Relações Exteriores | B60: =+'DCA-Anexo I-E'!B61+'DCA-Anexo I-E'!B62+'DCA-Anexo I-E'!B64+'DCA-Anexo I-E'!B63 -> 0 | C60: =+'DCA-Anexo I-E'!C61+'DCA-Anexo I-E'!C62+'DCA-Anexo I-E'!C64+'DCA-Anexo I-E'!C63 -> 0 | D60: =+'DCA-Anexo I-E'!D61+'DCA-Anexo I-E'!D62+'DCA-Anexo I-E'!D64+'DCA-Anexo I-E'!D63 -> 0 | E60: =+'DCA-Anexo I-E'!E61+'DCA-Anexo I-E'!E62+'DCA-Anexo I-E'!E64+'DCA-Anexo I-E'!E63 -> 0 | F60: =+'DCA-Anexo I-E'!F61+'DCA-Anexo I-E'!F62+'DCA-Anexo I-E'!F64+'DCA-Anexo I-E'!F63 -> 0
A61: 07.211 - Relações Diplomáticas
A62: 07.212 - Cooperação Internacional
A63: 07.122 - Administração Geral
A64: FU07 - Demais Subfunções
A65: 08 - Assistência Social | B65: =+'DCA-Anexo I-E'!B66+'DCA-Anexo I-E'!B67+'DCA-Anexo I-E'!B68+'DCA-Anexo I-E'!B69+'DCA-Anexo I-E'!B73+'DCA-Anexo I-E'!B72+'DCA-Anexo I-E'!B70+'DCA-Anexo I-E'!B71 -> 3512724.4 | C65: =+'DCA-Anexo I-E'!C66+'DCA-Anexo I-E'!C67+'DCA-Anexo I-E'!C68+'DCA-Anexo I-E'!C69+'DCA-Anexo I-E'!C73+'DCA-Anexo I-E'!C72+'DCA-Anexo I-E'!C70+'DCA-Anexo I-E'!C71 -> 3512724.4 | D65: =+'DCA-Anexo I-E'!D66+'DCA-Anexo I-E'!D67+'DCA-Anexo I-E'!D68+'DCA-Anexo I-E'!D69+'DCA-Anexo I-E'!D73+'DCA-Anexo I-E'!D72+'DCA-Anexo I-E'!D70+'DCA-Anexo I-E'!D71 -> 3223693.5 | E65: =+'DCA-Anexo I-E'!E66+'DCA-Anexo I-E'!E67+'DCA-Anexo I-E'!E68+'DCA-Anexo I-E'!E69+'DCA-Anexo I-E'!E73+'DCA-Anexo I-E'!E72+'DCA-Anexo I-E'!E70+'DCA-Anexo I-E'!E71 -> 0 | F65: =+'DCA-Anexo I-E'!F66+'DCA-Anexo I-E'!F67+'DCA-Anexo I-E'!F68+'DCA-Anexo I-E'!F69+'DCA-Anexo I-E'!F73+'DCA-Anexo I-E'!F72+'DCA-Anexo I-E'!F70+'DCA-Anexo I-E'!F71 -> 289030.87
A66: 08.241 - Assistência à Pessoa Idosa | B66: 132479.61 | C66: 132479.61 | D66: 116081.89 | F66: 16397.72
A67: 08.242 - Assistência à Pessoa com Deficiência
A68: 08.243 - Assistência à Criança e ao Adolescente
A69: 08.244 - Assistência Comunitária | B69: 83820.59 | C69: 83820.59 | D69: 82566.64 | F69: 1253.95
A70: 08.245 - Serviços Socioassistenciais | B70: 413318.69 | C70: 413318.69 | D70: 332546.9 | F70: 80771.79
A71: 08.246 - Segurança e Renda
A72: 08.122 - Administração Geral | B72: 2883105.5 | C72: 2883105.5 | D72: 2692498.1 | F72: 190607.41
A73: FU08 - Demais Subfunções
A74: 09 - Previdência Social | B74: =+'DCA-Anexo I-E'!B75+'DCA-Anexo I-E'!B76+'DCA-Anexo I-E'!B77+'DCA-Anexo I-E'!B78+'DCA-Anexo I-E'!B80+'DCA-Anexo I-E'!B79 -> 1064084.5 | C74: =+'DCA-Anexo I-E'!C75+'DCA-Anexo I-E'!C76+'DCA-Anexo I-E'!C77+'DCA-Anexo I-E'!C78+'DCA-Anexo I-E'!C80+'DCA-Anexo I-E'!C79 -> 1064084.5 | D74: =+'DCA-Anexo I-E'!D75+'DCA-Anexo I-E'!D76+'DCA-Anexo I-E'!D77+'DCA-Anexo I-E'!D78+'DCA-Anexo I-E'!D80+'DCA-Anexo I-E'!D79 -> 991518.46 | E74: =+'DCA-Anexo I-E'!E75+'DCA-Anexo I-E'!E76+'DCA-Anexo I-E'!E77+'DCA-Anexo I-E'!E78+'DCA-Anexo I-E'!E80+'DCA-Anexo I-E'!E79 -> 0 | F74: =+'DCA-Anexo I-E'!F75+'DCA-Anexo I-E'!F76+'DCA-Anexo I-E'!F77+'DCA-Anexo I-E'!F78+'DCA-Anexo I-E'!F80+'DCA-Anexo I-E'!F79 -> 72566.07
A75: 09.271 - Previdência Básica | B75: 1064084.5 | C75: 1064084.5 | D75: 991518.46 | F75: 72566.07
A76: 09.272 - Previdência do Regime Estatutário
A77: 09.273 - Previdência Complementar
A78: 09.274 - Previdência Especial
A79: 09.122 - Administração Geral
A80: FU09 - Demais Subfunções
A81: 10 - Saúde | B81: =+'DCA-Anexo I-E'!B82+'DCA-Anexo I-E'!B83+'DCA-Anexo I-E'!B84+'DCA-Anexo I-E'!B85+'DCA-Anexo I-E'!B86+'DCA-Anexo I-E'!B87+'DCA-Anexo I-E'!B89+'DCA-Anexo I-E'!B88 -> 31450552 | C81: =+'DCA-Anexo I-E'!C82+'DCA-Anexo I-E'!C83+'DCA-Anexo I-E'!C84+'DCA-Anexo I-E'!C85+'DCA-Anexo I-E'!C86+'DCA-Anexo I-E'!C87+'DCA-Anexo I-E'!C89+'DCA-Anexo I-E'!C88 -> 31450552 | D81: =+'DCA-Anexo I-E'!D82+'DCA-Anexo I-E'!D83+'DCA-Anexo I-E'!D84+'DCA-Anexo I-E'!D85+'DCA-Anexo I-E'!D86+'DCA-Anexo I-E'!D87+'DCA-Anexo I-E'!D89+'DCA-Anexo I-E'!D88 -> 28325556 | E81: =+'DCA-Anexo I-E'!E82+'DCA-Anexo I-E'!E83+'DCA-Anexo I-E'!E84+'DCA-Anexo I-E'!E85+'DCA-Anexo I-E'!E86+'DCA-Anexo I-E'!E87+'DCA-Anexo I-E'!E89+'DCA-Anexo I-E'!E88 -> 0 | F81: =+'DCA-Anexo I-E'!F82+'DCA-Anexo I-E'!F83+'DCA-Anexo I-E'!F84+'DCA-Anexo I-E'!F85+'DCA-Anexo I-E'!F86+'DCA-Anexo I-E'!F87+'DCA-Anexo I-E'!F89+'DCA-Anexo I-E'!F88 -> 3124995.8
A82: 10.301 - Atenção Básica | B82: 20554590 | C82: 20554590 | D82: 18135089 | F82: 2419500.4
A83: 10.302 - Assistência Hospitalar e Ambulatorial | B83: 9659347.8 | C83: 9659347.8 | D83: 8959516.1 | F83: 699831.69
A84: 10.303 - Suporte Profilático e Terapêutico
A85: 10.304 - Vigilância Sanitária | B85: 1236614.7 | C85: 1236614.7 | D85: 1230951 | F85: 5663.68
A86: 10.305 - Vigilância Epidemiológica
A87: 10.306 - Alimentação e Nutrição
A88: 10.122 - Administração Geral
A89: FU10 - Demais Subfunções
A90: 11 - Trabalho | B90: =+'DCA-Anexo I-E'!B91+'DCA-Anexo I-E'!B92+'DCA-Anexo I-E'!B93+'DCA-Anexo I-E'!B94+'DCA-Anexo I-E'!B96+'DCA-Anexo I-E'!B95 -> 0 | C90: =+'DCA-Anexo I-E'!C91+'DCA-Anexo I-E'!C92+'DCA-Anexo I-E'!C93+'DCA-Anexo I-E'!C94+'DCA-Anexo I-E'!C96+'DCA-Anexo I-E'!C95 -> 0 | D90: =+'DCA-Anexo I-E'!D91+'DCA-Anexo I-E'!D92+'DCA-Anexo I-E'!D93+'DCA-Anexo I-E'!D94+'DCA-Anexo I-E'!D96+'DCA-Anexo I-E'!D95 -> 0 | E90: =+'DCA-Anexo I-E'!E91+'DCA-Anexo I-E'!E92+'DCA-Anexo I-E'!E93+'DCA-Anexo I-E'!E94+'DCA-Anexo I-E'!E96+'DCA-Anexo I-E'!E95 -> 0 | F90: =+'DCA-Anexo I-E'!F91+'DCA-Anexo I-E'!F92+'DCA-Anexo I-E'!F93+'DCA-Anexo I-E'!F94+'DCA-Anexo I-E'!F96+'DCA-Anexo I-E'!F95 -> 0
A91: 11.331 - Proteção e Benefícios ao Trabalhador
A92: 11.332 - Relações de Trabalho
A93: 11.333 - Empregabilidade
A94: 11.334 - Fomento ao Trabalho
A95: 11.122 - Administração Geral
A96: FU11 - Demais Subfunções
A97: 12 - Educação | B97: =+'DCA-Anexo I-E'!B98+'DCA-Anexo I-E'!B99+'DCA-Anexo I-E'!B100+'DCA-Anexo I-E'!B101+'DCA-Anexo I-E'!B102+'DCA-Anexo I-E'!B103+'DCA-Anexo I-E'!B104+'DCA-Anexo I-E'!B105+'DCA-Anexo I-E'!B107+'DCA-Anexo I-E'!B106 -> 52003852 | C97: =+'DCA-Anexo I-E'!C98+'DCA-Anexo I-E'!C99+'DCA-Anexo I-E'!C100+'DCA-Anexo I-E'!C101+'DCA-Anexo I-E'!C102+'DCA-Anexo I-E'!C103+'DCA-Anexo I-E'!C104+'DCA-Anexo I-E'!C105+'DCA-Anexo I-E'!C107+'DCA-Anexo I-E'!C106 -> 52003852 | D97: =+'DCA-Anexo I-E'!D98+'DCA-Anexo I-E'!D99+'DCA-Anexo I-E'!D100+'DCA-Anexo I-E'!D101+'DCA-Anexo I-E'!D102+'DCA-Anexo I-E'!D103+'DCA-Anexo I-E'!D104+'DCA-Anexo I-E'!D105+'DCA-Anexo I-E'!D107+'DCA-Anexo I-E'!D106 -> 50949223 | E97: =+'DCA-Anexo I-E'!E98+'DCA-Anexo I-E'!E99+'DCA-Anexo I-E'!E100+'DCA-Anexo I-E'!E101+'DCA-Anexo I-E'!E102+'DCA-Anexo I-E'!E103+'DCA-Anexo I-E'!E104+'DCA-Anexo I-E'!E105+'DCA-Anexo I-E'!E107+'DCA-Anexo I-E'!E106 -> 0 | F97: =+'DCA-Anexo I-E'!F98+'DCA-Anexo I-E'!F99+'DCA-Anexo I-E'!F100+'DCA-Anexo I-E'!F101+'DCA-Anexo I-E'!F102+'DCA-Anexo I-E'!F103+'DCA-Anexo I-E'!F104+'DCA-Anexo I-E'!F105+'DCA-Anexo I-E'!F107+'DCA-Anexo I-E'!F106 -> 1054629
A98: 12.361 - Ensino Fundamental | B98: 46951174 | C98: 46951174 | D98: 45939291 | F98: 1011883.2
A99: 12.362 - Ensino Médio
A100: 12.363 - Ensino Profissional
A101: 12.364 - Ensino Superior
A102: 12.365 - Educação Infantil | B102: 5052677.4 | C102: 5052677.4 | D102: 5009931.5 | F102: 42745.84
A103: 12.366 - Educação de Jovens e Adultos
...

Sheet DCA-Anexo I-F
A2: QDCC
A3: BALANÇO ANUAL (DCA)
A4: VERSÃO: v14
A5: VIGÊNCIA: 05/01/2026
A7: Ente: 2908101 - Cocos/BA
A8: Poder: E - Executivo
A9: Instituição: 4063 - Prefeitura Municipal de Cocos - BA
A10: Exercício: 2025
A11: Periodicidade: ANUAL
A12: Período: Período único (anual)
A14: Grupo: Balanço Orçamentário - Despesas Orçamentárias - Sub Quadro - Execução dos Restos a Pagar
A15: Quadro: Despesas Orçamentárias
A16: Rótulo: Padrão
A17: Despesas Orçamentárias | B17: Execução da Despesa
B18: Restos a Pagar Não Processados Inscritos em Exercícios Anteriores | C18: Restos a Pagar Não Processados Inscritos em 31 de Dezembro do Exercício Anterior | D18: Restos a Pagar Não Processados Liquidados | E18: Restos a Pagar Não Processados Pagos | F18: Restos a Pagar Não Processados Cancelados | G18: Restos a Pagar Processados Inscritos em Exercícios Anteriores | H18: Restos a Pagar Processados Inscritos em 31 de Dezembro do Exercício Anterior | I18: Restos a Pagar Processados Pagos | J18: Restos a Pagar Processados Cancelados
A19: Despesas Orçamentárias
A20: Total Despesas | B20: =+'DCA-Anexo I-F'!B21+'DCA-Anexo I-F'!B235 -> 62175.76 | C20: =+'DCA-Anexo I-F'!C21+'DCA-Anexo I-F'!C235 -> 20650.4 | D20: =+'DCA-Anexo I-F'!D21+'DCA-Anexo I-F'!D235 -> 20650.4 | E20: =+'DCA-Anexo I-F'!E21+'DCA-Anexo I-F'!E235 -> 20650.4 | F20: =+'DCA-Anexo I-F'!F21+'DCA-Anexo I-F'!F235 -> 0 | G20: =+'DCA-Anexo I-F'!G21+'DCA-Anexo I-F'!G235 -> 678963.1 | H20: =+'DCA-Anexo I-F'!H21+'DCA-Anexo I-F'!H235 -> 513963.84 | I20: =+'DCA-Anexo I-F'!I21+'DCA-Anexo I-F'!I235 -> 511422.29 | J20: =+'DCA-Anexo I-F'!J21+'DCA-Anexo I-F'!J235 -> 0
A21: 3.0.00.00.00 - Despesas Correntes | B21: =+'DCA-Anexo I-F'!B22+'DCA-Anexo I-F'!B145+'DCA-Anexo I-F'!B103 -> 54275.76 | C21: =+'DCA-Anexo I-F'!C22+'DCA-Anexo I-F'!C145+'DCA-Anexo I-F'!C103 -> 20650.4 | D21: =+'DCA-Anexo I-F'!D22+'DCA-Anexo I-F'!D145+'DCA-Anexo I-F'!D103 -> 20650.4 | E21: =+'DCA-Anexo I-F'!E22+'DCA-Anexo I-F'!E145+'DCA-Anexo I-F'!E103 -> 20650.4 | F21: =+'DCA-Anexo I-F'!F22+'DCA-Anexo I-F'!F145+'DCA-Anexo I-F'!F103 -> 0 | G21: =+'DCA-Anexo I-F'!G22+'DCA-Anexo I-F'!G145+'DCA-Anexo I-F'!G103 -> 636396.89 | H21: =+'DCA-Anexo I-F'!H22+'DCA-Anexo I-F'!H145+'DCA-Anexo I-F'!H103 -> 331717.09 | I21: =+'DCA-Anexo I-F'!I22+'DCA-Anexo I-F'!I145+'DCA-Anexo I-F'!I103 -> 329175.54 | J21: =+'DCA-Anexo I-F'!J22+'DCA-Anexo I-F'!J145+'DCA-Anexo I-F'!J103 -> 0
A22: 3.1.00.00.00 - Pessoal e Encargos Sociais | B22: =+'DCA-Anexo I-F'!B101+'DCA-Anexo I-F'!B30+'DCA-Anexo I-F'!B39+'DCA-Anexo I-F'!B75+'DCA-Anexo I-F'!B26+'DCA-Anexo I-F'!B34+'DCA-Anexo I-F'!B102+'DCA-Anexo I-F'!B44+'DCA-Anexo I-F'!B24+'DCA-Anexo I-F'!B29+'DCA-Anexo I-F'!B25+'DCA-Anexo I-F'!B37+'DCA-Anexo I-F'!B28+'DCA-Anexo I-F'!B27+'DCA-Anexo I-F'!B42+'DCA-Anexo I-F'!B43+'DCA-Anexo I-F'!B99+'DCA-Anexo I-F'!B46+'DCA-Anexo I-F'!B32+'DCA-Anexo I-F'!B100+'DCA-Anexo I-F'!B35+'DCA-Anexo I-F'!B23+'DCA-Anexo I-F'!B41+'DCA-Anexo I-F'!B38+'DCA-Anexo I-F'!B98+'DCA-Anexo I-F'!B31+'DCA-Anexo I-F'!B33+'DCA-Anexo I-F'!B36+'DCA-Anexo I-F'!B45+'DCA-Anexo I-F'!B40+'DCA-Anexo I-F'!B97 -> 0 | C22: =+'DCA-Anexo I-F'!C101+'DCA-Anexo I-F'!C30+'DCA-Anexo I-F'!C39+'DCA-Anexo I-F'!C75+'DCA-Anexo I-F'!C26+'DCA-Anexo I-F'!C34+'DCA-Anexo I-F'!C102+'DCA-Anexo I-F'!C44+'DCA-Anexo I-F'!C24+'DCA-Anexo I-F'!C29+'DCA-Anexo I-F'!C25+'DCA-Anexo I-F'!C37+'DCA-Anexo I-F'!C28+'DCA-Anexo I-F'!C27+'DCA-Anexo I-F'!C42+'DCA-Anexo I-F'!C43+'DCA-Anexo I-F'!C99+'DCA-Anexo I-F'!C46+'DCA-Anexo I-F'!C32+'DCA-Anexo I-F'!C100+'DCA-Anexo I-F'!C35+'DCA-Anexo I-F'!C23+'DCA-Anexo I-F'!C41+'DCA-Anexo I-F'!C38+'DCA-Anexo I-F'!C98+'DCA-Anexo I-F'!C31+'DCA-Anexo I-F'!C33+'DCA-Anexo I-F'!C36+'DCA-Anexo I-F'!C45+'DCA-Anexo I-F'!C40+'DCA-Anexo I-F'!C97 -> 0 | D22: =+'DCA-Anexo I-F'!D101+'DCA-Anexo I-F'!D30+'DCA-Anexo I-F'!D39+'DCA-Anexo I-F'!D75+'DCA-Anexo I-F'!D26+'DCA-Anexo I-F'!D34+'DCA-Anexo I-F'!D102+'DCA-Anexo I-F'!D44+'DCA-Anexo I-F'!D24+'DCA-Anexo I-F'!D29+'DCA-Anexo I-F'!D25+'DCA-Anexo I-F'!D37+'DCA-Anexo I-F'!D28+'DCA-Anexo I-F'!D27+'DCA-Anexo I-F'!D42+'DCA-Anexo I-F'!D43+'DCA-Anexo I-F'!D99+'DCA-Anexo I-F'!D46+'DCA-Anexo I-F'!D32+'DCA-Anexo I-F'!D100+'DCA-Anexo I-F'!D35+'DCA-Anexo I-F'!D23+'DCA-Anexo I-F'!D41+'DCA-Anexo I-F'!D38+'DCA-Anexo I-F'!D98+'DCA-Anexo I-F'!D31+'DCA-Anexo I-F'!D33+'DCA-Anexo I-F'!D36+'DCA-Anexo I-F'!D45+'DCA-Anexo I-F'!D40+'DCA-Anexo I-F'!D97 -> 0 | E22: =+'DCA-Anexo I-F'!E101+'DCA-Anexo I-F'!E30+'DCA-Anexo I-F'!E39+'DCA-Anexo I-F'!E75+'DCA-Anexo I-F'!E26+'DCA-Anexo I-F'!E34+'DCA-Anexo I-F'!E102+'DCA-Anexo I-F'!E44+'DCA-Anexo I-F'!E24+'DCA-Anexo I-F'!E29+'DCA-Anexo I-F'!E25+'DCA-Anexo I-F'!E37+'DCA-Anexo I-F'!E28+'DCA-Anexo I-F'!E27+'DCA-Anexo I-F'!E42+'DCA-Anexo I-F'!E43+'DCA-Anexo I-F'!E99+'DCA-Anexo I-F'!E46+'DCA-Anexo I-F'!E32+'DCA-Anexo I-F'!E100+'DCA-Anexo I-F'!E35+'DCA-Anexo I-F'!E23+'DCA-Anexo I-F'!E41+'DCA-Anexo I-F'!E38+'DCA-Anexo I-F'!E98+'DCA-Anexo I-F'!E31+'DCA-Anexo I-F'!E33+'DCA-Anexo I-F'!E36+'DCA-Anexo I-F'!E45+'DCA-Anexo I-F'!E40+'DCA-Anexo I-F'!E97 -> 0 | F22: =+'DCA-Anexo I-F'!F101+'DCA-Anexo I-F'!F30+'DCA-Anexo I-F'!F39+'DCA-Anexo I-F'!F75+'DCA-Anexo I-F'!F26+'DCA-Anexo I-F'!F34+'DCA-Anexo I-F'!F102+'DCA-Anexo I-F'!F44+'DCA-Anexo I-F'!F24+'DCA-Anexo I-F'!F29+'DCA-Anexo I-F'!F25+'DCA-Anexo I-F'!F37+'DCA-Anexo I-F'!F28+'DCA-Anexo I-F'!F27+'DCA-Anexo I-F'!F42+'DCA-Anexo I-F'!F43+'DCA-Anexo I-F'!F99+'DCA-Anexo I-F'!F46+'DCA-Anexo I-F'!F32+'DCA-Anexo I-F'!F100+'DCA-Anexo I-F'!F35+'DCA-Anexo I-F'!F23+'DCA-Anexo I-F'!F41+'DCA-Anexo I-F'!F38+'DCA-Anexo I-F'!F98+'DCA-Anexo I-F'!F31+'DCA-Anexo I-F'!F33+'DCA-Anexo I-F'!F36+'DCA-Anexo I-F'!F45+'DCA-Anexo I-F'!F40+'DCA-Anexo I-F'!F97 -> 0 | G22: =+'DCA-Anexo I-F'!G101+'DCA-Anexo I-F'!G30+'DCA-Anexo I-F'!G39+'DCA-Anexo I-F'!G75+'DCA-Anexo I-F'!G26+'DCA-Anexo I-F'!G34+'DCA-Anexo I-F'!G102+'DCA-Anexo I-F'!G44+'DCA-Anexo I-F'!G24+'DCA-Anexo I-F'!G29+'DCA-Anexo I-F'!G25+'DCA-Anexo I-F'!G37+'DCA-Anexo I-F'!G28+'DCA-Anexo I-F'!G27+'DCA-Anexo I-F'!G42+'DCA-Anexo I-F'!G43+'DCA-Anexo I-F'!G99+'DCA-Anexo I-F'!G46+'DCA-Anexo I-F'!G32+'DCA-Anexo I-F'!G100+'DCA-Anexo I-F'!G35+'DCA-Anexo I-F'!G23+'DCA-Anexo I-F'!G41+'DCA-Anexo I-F'!G38+'DCA-Anexo I-F'!G98+'DCA-Anexo I-F'!G31+'DCA-Anexo I-F'!G33+'DCA-Anexo I-F'!G36+'DCA-Anexo I-F'!G45+'DCA-Anexo I-F'!G40+'DCA-Anexo I-F'!G97 -> 7130.4 | H22: =+'DCA-Anexo I-F'!H101+'DCA-Anexo I-F'!H30+'DCA-Anexo I-F'!H39+'DCA-Anexo I-F'!H75+'DCA-Anexo I-F'!H26+'DCA-Anexo I-F'!H34+'DCA-Anexo I-F'!H102+'DCA-Anexo I-F'!H44+'DCA-Anexo I-F'!H24+'DCA-Anexo I-F'!H29+'DCA-Anexo I-F'!H25+'DCA-Anexo I-F'!H37+'DCA-Anexo I-F'!H28+'DCA-Anexo I-F'!H27+'DCA-Anexo I-F'!H42+'DCA-Anexo I-F'!H43+'DCA-Anexo I-F'!H99+'DCA-Anexo I-F'!H46+'DCA-Anexo I-F'!H32+'DCA-Anexo I-F'!H100+'DCA-Anexo I-F'!H35+'DCA-Anexo I-F'!H23+'DCA-Anexo I-F'!H41+'DCA-Anexo I-F'!H38+'DCA-Anexo I-F'!H98+'DCA-Anexo I-F'!H31+'DCA-Anexo I-F'!H33+'DCA-Anexo I-F'!H36+'DCA-Anexo I-F'!H45+'DCA-Anexo I-F'!H40+'DCA-Anexo I-F'!H97 -> 75981.93 | I22: =+'DCA-Anexo I-F'!I101+'DCA-Anexo I-F'!I30+'DCA-Anexo I-F'!I39+'DCA-Anexo I-F'!I75+'DCA-Anexo I-F'!I26+'DCA-Anexo I-F'!I34+'DCA-Anexo I-F'!I102+'DCA-Anexo I-F'!I44+'DCA-Anexo I-F'!I24+'DCA-Anexo I-F'!I29+'DCA-Anexo I-F'!I25+'DCA-Anexo I-F'!I37+'DCA-Anexo I-F'!I28+'DCA-Anexo I-F'!I27+'DCA-Anexo I-F'!I42+'DCA-Anexo I-F'!I43+'DCA-Anexo I-F'!I99+'DCA-Anexo I-F'!I46+'DCA-Anexo I-F'!I32+'DCA-Anexo I-F'!I100+'DCA-Anexo I-F'!I35+'DCA-Anexo I-F'!I23+'DCA-Anexo I-F'!I41+'DCA-Anexo I-F'!I38+'DCA-Anexo I-F'!I98+'DCA-Anexo I-F'!I31+'DCA-Anexo I-F'!I33+'DCA-Anexo I-F'!I36+'DCA-Anexo I-F'!I45+'DCA-Anexo I-F'!I40+'DCA-Anexo I-F'!I97 -> 75981.93 | J22: =+'DCA-Anexo I-F'!J101+'DCA-Anexo I-F'!J30+'DCA-Anexo I-F'!J39+'DCA-Anexo I-F'!J75+'DCA-Anexo I-F'!J26+'DCA-Anexo I-F'!J34+'DCA-Anexo I-F'!J102+'DCA-Anexo I-F'!J44+'DCA-Anexo I-F'!J24+'DCA-Anexo I-F'!J29+'DCA-Anexo I-F'!J25+'DCA-Anexo I-F'!J37+'DCA-Anexo I-F'!J28+'DCA-Anexo I-F'!J27+'DCA-Anexo I-F'!J42+'DCA-Anexo I-F'!J43+'DCA-Anexo I-F'!J99+'DCA-Anexo I-F'!J46+'DCA-Anexo I-F'!J32+'DCA-Anexo I-F'!J100+'DCA-Anexo I-F'!J35+'DCA-Anexo I-F'!J23+'DCA-Anexo I-F'!J41+'DCA-Anexo I-F'!J38+'DCA-Anexo I-F'!J98+'DCA-Anexo I-F'!J31+'DCA-Anexo I-F'!J33+'DCA-Anexo I-F'!J36+'DCA-Anexo I-F'!J45+'DCA-Anexo I-F'!J40+'DCA-Anexo I-F'!J97 -> 0
A23: 3.1.20.00.00 - Transferências à União
A24: 3.1.22.00.00 - Execução orçamentária delegada à União
A25: 3.1.30.00.00 - Transferências a Estados e ao Distrito Federal
A26: 3.1.31.00.00 - Transferências a Estados e ao Distrito Federal - fundo a fundo
A27: 3.1.32.00.00 - Execução orçamentária delegada a Estados e ao Distrito Federal
A28: 3.1.35.00.00 - Transferências fundo a fundo aos Estados e ao Distrito Federal à conta de recursos de que tratam os §§ 1º e 2º do art. 24 da Lei Complementar nº 141, de 2012 - Restos a Pagar Cancelados
A29: 3.1.36.00.00 - Transferências fundo a fundo aos Estados e ao Distrito Federal à conta de recursos de que trata o art. 25 da Lei Complementar nº 141, de 2012 - diferença do mínimo não aplicado em exercícios anteriores
A30: 3.1.40.00.00 - Transferências a Municípios
A31: 3.1.41.00.00 - Transferências a Municípios - fundo a fundo
A32: 3.1.42.00.00 - Execução orçamentária delegada a Municípios
A33: 3.1.45.00.00 - Transferências fundo a fundo aos Municípios à conta de recursos de que tratam os §§ 1º e 2º do art. 24 da Lei Complementar nº 141, de 2012 - Restos a Pagar Cancelados
A34: 3.1.46.00.00 - Transferências fundo a fundo aos Municípios à conta de recursos de que trata o art. 25 da Lei Complementar nº 141, de 2012 - diferença do mínimo não aplicado em exercícios anteriores
... A45: 3.1.80.00.00 - Transferências ao Exterior
A46: 3.1.90.00.00 - Aplicações Diretas | B46: =+'DCA-Anexo I-F'!B47+'DCA-Anexo I-F'!B48+'DCA-Anexo I-F'!B49+'DCA-Anexo I-F'!B50+'DCA-Anexo I-F'!B51+'DCA-Anexo I-F'!B52+'DCA-Anexo I-F'!B53+'DCA-Anexo I-F'!B66+'DCA-Anexo I-F'!B67+'DCA-Anexo I-F'!B68+'DCA-Anexo I-F'!B69+'DCA-Anexo I-F'!B70+'DCA-Anexo I-F'!B71+'DCA-Anexo I-F'!B72+'DCA-Anexo I-F'!B73+'DCA-Anexo I-F'!B74+'DCA-Anexo I-F'!B54 -> 0 | C46: =+'DCA-Anexo I-F'!C47+'DCA-Anexo I-F'!C48+'DCA-Anexo I-F'!C49+'DCA-Anexo I-F'!C50+'DCA-Anexo I-F'!C51+'DCA-Anexo I-F'!C52+'DCA-Anexo I-F'!C53+'DCA-Anexo I-F'!C66+'DCA-Anexo I-F'!C67+'DCA-Anexo I-F'!C68+'DCA-Anexo I-F'!C69+'DCA-Anexo I-F'!C70+'DCA-Anexo I-F'!C71+'DCA-Anexo I-F'!C72+'DCA-Anexo I-F'!C73+'DCA-Anexo I-F'!C74+'DCA-Anexo I-F'!C54 -> 0 | D46: =+'DCA-Anexo I-F'!D47+'DCA-Anexo I-F'!D48+'DCA-Anexo I-F'!D49+'DCA-Anexo I-F'!D50+'DCA-Anexo I-F'!D51+'DCA-Anexo I-F'!D52+'DCA-Anexo I-F'!D53+'DCA-Anexo I-F'!D66+'DCA-Anexo I-F'!D67+'DCA-Anexo I-F'!D68+'DCA-Anexo I-F'!D69+'DCA-Anexo I-F'!D70+'DCA-Anexo I-F'!D71+'DCA-Anexo I-F'!D72+'DCA-Anexo I-F'!D73+'DCA-Anexo I-F'!D74+'DCA-Anexo I-F'!D54 -> 0 | E46: =+'DCA-Anexo I-F'!E47+'DCA-Anexo I-F'!E48+'DCA-Anexo I-F'!E49+'DCA-Anexo I-F'!E50+'DCA-Anexo I-F'!E51+'DCA-Anexo I-F'!E52+'DCA-Anexo I-F'!E53+'DCA-Anexo I-F'!E66+'DCA-Anexo I-F'!E67+'DCA-Anexo I-F'!E68+'DCA-Anexo I-F'!E69+'DCA-Anexo I-F'!E70+'DCA-Anexo I-F'!E71+'DCA-Anexo I-F'!E72+'DCA-Anexo I-F'!E73+'DCA-Anexo I-F'!E74+'DCA-Anexo I-F'!E54 -> 0 | F46: =+'DCA-Anexo I-F'!F47+'DCA-Anexo I-F'!F48+'DCA-Anexo I-F'!F49+'DCA-Anexo I-F'!F50+'DCA-Anexo I-F'!F51+'DCA-Anexo I-F'!F52+'DCA-Anexo I-F'!F53+'DCA-Anexo I-F'!F66+'DCA-Anexo I-F'!F67+'DCA-Anexo I-F'!F68+'DCA-Anexo I-F'!F69+'DCA-Anexo I-F'!F70+'DCA-Anexo I-F'!F71+'DCA-Anexo I-F'!F72+'DCA-Anexo I-F'!F73+'DCA-Anexo I-F'!F74+'DCA-Anexo I-F'!F54 -> 0 | G46: =+'DCA-Anexo I-F'!G47+'DCA-Anexo I-F'!G48+'DCA-Anexo I-F'!G49+'DCA-Anexo I-F'!G50+'DCA-Anexo I-F'!G51+'DCA-Anexo I-F'!G52+'DCA-Anexo I-F'!G53+'DCA-Anexo I-F'!G66+'DCA-Anexo I-F'!G67+'DCA-Anexo I-F'!G68+'DCA-Anexo I-F'!G69+'DCA-Anexo I-F'!G70+'DCA-Anexo I-F'!G71+'DCA-Anexo I-F'!G72+'DCA-Anexo I-F'!G73+'DCA-Anexo I-F'!G74+'DCA-Anexo I-F'!G54 -> 7130.4 | H46: =+'DCA-Anexo I-F'!H47+'DCA-Anexo I-F'!H48+'DCA-Anexo I-F'!H49+'DCA-Anexo I-F'!H50+'DCA-Anexo I-F'!H51+'DCA-Anexo I-F'!H52+'DCA-Anexo I-F'!H53+'DCA-Anexo I-F'!H66+'DCA-Anexo I-F'!H67+'DCA-Anexo I-F'!H68+'DCA-Anexo I-F'!H69+'DCA-Anexo I-F'!H70+'DCA-Anexo I-F'!H71+'DCA-Anexo I-F'!H72+'DCA-Anexo I-F'!H73+'DCA-Anexo I-F'!H74+'DCA-Anexo I-F'!H54 -> 75981.93 | I46: =+'DCA-Anexo I-F'!I47+'DCA-Anexo I-F'!I48+'DCA-Anexo I-F'!I49+'DCA-Anexo I-F'!I50+'DCA-Anexo I-F'!I51+'DCA-Anexo I-F'!I52+'DCA-Anexo I-F'!I53+'DCA-Anexo I-F'!I66+'DCA-Anexo I-F'!I67+'DCA-Anexo I-F'!I68+'DCA-Anexo I-F'!I69+'DCA-Anexo I-F'!I70+'DCA-Anexo I-F'!I71+'DCA-Anexo I-F'!I72+'DCA-Anexo I-F'!I73+'DCA-Anexo I-F'!I74+'DCA-Anexo I-F'!I54 -> 75981.93 | J46: =+'DCA-Anexo I-F'!J47+'DCA-Anexo I-F'!J48+'DCA-Anexo I-F'!J49+'DCA-Anexo I-F'!J50+'DCA-Anexo I-F'!J51+'DCA-Anexo I-F'!J52+'DCA-Anexo I-F'!J53+'DCA-Anexo I-F'!J66+'DCA-Anexo I-F'!J67+'DCA-Anexo I-F'!J68+'DCA-Anexo I-F'!J69+'DCA-Anexo I-F'!J70+'DCA-Anexo I-F'!J71+'DCA-Anexo I-F'!J72+'DCA-Anexo I-F'!J73+'DCA-Anexo I-F'!J74+'DCA-Anexo I-F'!J54 -> 0
A47: 3.1.90.01.00 - Aposentadorias do RPPS, Reserva Remunerada e Reformas dos Militares
A48: 3.1.90.03.00 - Pensões do RPPS e do Militar
A49: 3.1.90.04.00 - Contratação por Tempo Determinado | G49: 7130.4
A50: 3.1.90.07.00 - Contribuição a Entidades Fechadas de Previdência
A51: 3.1.90.08.00 - Outros Benefícios Assistenciais do Servidor e do Militar
A52: 3.1.90.11.00 - Vencimentos e Vantagens Fixas - Pessoal Civil | F52: 0 | H52: 75981.93 | I52: 75981.93
A53: 3.1.90.12.00 - Vencimentos e Vantagens Fixas - Pessoal Militar
A54: 3.1.90.13.00 - Obrigações Patronais | B54: =+'DCA-Anexo I-F'!B56+'DCA-Anexo I-F'!B58+'DCA-Anexo I-F'!B59+'DCA-Anexo I-F'!B55+'DCA-Anexo I-F'!B65+'DCA-Anexo I-F'!B57+'DCA-Anexo I-F'!B60+'DCA-Anexo I-F'!B61+'DCA-Anexo I-F'!B62+'DCA-Anexo I-F'!B63+'DCA-Anexo I-F'!B64 -> 0 | C54: =+'DCA-Anexo I-F'!C56+'DCA-Anexo I-F'!C58+'DCA-Anexo I-F'!C59+'DCA-Anexo I-F'!C55+'DCA-Anexo I-F'!C65+'DCA-Anexo I-F'!C57+'DCA-Anexo I-F'!C60+'DCA-Anexo I-F'!C61+'DCA-Anexo I-F'!C62+'DCA-Anexo I-F'!C63+'DCA-Anexo I-F'!C64 -> 0 | D54: =+'DCA-Anexo I-F'!D56+'DCA-Anexo I-F'!D58+'DCA-Anexo I-F'!D59+'DCA-Anexo I-F'!D55+'DCA-Anexo I-F'!D65+'DCA-Anexo I-F'!D57+'DCA-Anexo I-F'!D60+'DCA-Anexo I-F'!D61+'DCA-Anexo I-F'!D62+'DCA-Anexo I-F'!D63+'DCA-Anexo I-F'!D64 -> 0 | E54: =+'DCA-Anexo I-F'!E56+'DCA-Anexo I-F'!E58+'DCA-Anexo I-F'!E59+'DCA-Anexo I-F'!E55+'DCA-Anexo I-F'!E65+'DCA-Anexo I-F'!E57+'DCA-Anexo I-F'!E60+'DCA-Anexo I-F'!E61+'DCA-Anexo I-F'!E62+'DCA-Anexo I-F'!E63+'DCA-Anexo I-F'!E64 -> 0 | F54: =+'DCA-Anexo I-F'!F56+'DCA-Anexo I-F'!F58+'DCA-Anexo I-F'!F59+'DCA-Anexo I-F'!F55+'DCA-Anexo I-F'!F65+'DCA-Anexo I-F'!F57+'DCA-Anexo I-F'!F60+'DCA-Anexo I-F'!F61+'DCA-Anexo I-F'!F62+'DCA-Anexo I-F'!F63+'DCA-Anexo I-F'!F64 -> 0 | G54: =+'DCA-Anexo I-F'!G56+'DCA-Anexo I-F'!G58+'DCA-Anexo I-F'!G59+'DCA-Anexo I-F'!G55+'DCA-Anexo I-F'!G65+'DCA-Anexo I-F'!G57+'DCA-Anexo I-F'!G60+'DCA-Anexo I-F'!G61+'DCA-Anexo I-F'!G62+'DCA-Anexo I-F'!G63+'DCA-Anexo I-F'!G64 -> 0 | H54: =+'DCA-Anexo I-F'!H56+'DCA-Anexo I-F'!H58+'DCA-Anexo I-F'!H59+'DCA-Anexo I-F'!H55+'DCA-Anexo I-F'!H65+'DCA-Anexo I-F'!H57+'DCA-Anexo I-F'!H60+'DCA-Anexo I-F'!H61+'DCA-Anexo I-F'!H62+'DCA-Anexo I-F'!H63+'DCA-Anexo I-F'!H64 -> 0 | I54: =+'DCA-Anexo I-F'!I56+'DCA-Anexo I-F'!I58+'DCA-Anexo I-F'!I59+'DCA-Anexo I-F'!I55+'DCA-Anexo I-F'!I65+'DCA-Anexo I-F'!I57+'DCA-Anexo I-F'!I60+'DCA-Anexo I-F'!I61+'DCA-Anexo I-F'!I62+'DCA-Anexo I-F'!I63+'DCA-Anexo I-F'!I64 -> 0 | J54: =+'DCA-Anexo I-F'!J56+'DCA-Anexo I-F'!J58+'DCA-Anexo I-F'!J59+'DCA-Anexo I-F'!J55+'DCA-Anexo I-F'!J65+'DCA-Anexo I-F'!J57+'DCA-Anexo I-F'!J60+'DCA-Anexo I-F'!J61+'DCA-Anexo I-F'!J62+'DCA-Anexo I-F'!J63+'DCA-Anexo I-F'!J64 -> 0
A55: 3.1.90.13.01 - FGTS
A56: 3.1.90.13.02 - Contribuições Previdenciárias - INSS
A57: 3.1.90.13.04 - Contribuição de salário-educação
A58: 3.1.90.13.07 - Contrato por Tempo Determinado
A59: 3.1.90.13.08 - Contribuições Previdenciárias - RPPS - Pessoal Ativo
A60: 3.1.90.13.09 - Seguros de acidentes do trabalho
A61: 3.1.90.13.10 - Contribuições previdenciárias - RPPS - pessoal inativo
A62: 3.1.90.13.11 - FGTS - PDV
A63: 3.1.90.13.18 - Contribuição para o PIS/PASEP s/ folha Pagto.
A64: 3.1.90.13.40 - Encargos de pessoal requisitado de outros Entes
A65: 3.1.90.13.99 - Outras Obrigações Patronais
A66: 3.1.90.16.00 - Outras Despesas Variáveis - Pessoal Civil
... A74: 3.1.90.99.00 - A Classificar
A75: 3.1.91.00.00 - Aplicação Direta Decorrente de Operação entre Órgãos, Fundos e Entidades Integrantes dos Orçamentos Fiscal e da Seguridade Social | B75: =+'DCA-Anexo I-F'!B94+'DCA-Anexo I-F'!B78+'DCA-Anexo I-F'!B92+'DCA-Anexo I-F'!B95+'DCA-Anexo I-F'!B96+'DCA-Anexo I-F'!B76+'DCA-Anexo I-F'!B93+'DCA-Anexo I-F'!B77+'DCA-Anexo I-F'!B91 -> 0 | C75: =+'DCA-Anexo I-F'!C94+'DCA-Anexo I-F'!C78+'DCA-Anexo I-F'!C92+'DCA-Anexo I-F'!C95+'DCA-Anexo I-F'!C96+'DCA-Anexo I-F'!C76+'DCA-Anexo I-F'!C93+'DCA-Anexo I-F'!C77+'DCA-Anexo I-F'!C91 -> 0 | D75: =+'DCA-Anexo I-F'!D94+'DCA-Anexo I-F'!D78+'DCA-Anexo I-F'!D92+'DCA-Anexo I-F'!D95+'DCA-Anexo I-F'!D96+'DCA-Anexo I-F'!D76+'DCA-Anexo I-F'!D93+'DCA-Anexo I-F'!D77+'DCA-Anexo I-F'!D91 -> 0 | E75: =+'DCA-Anexo I-F'!E94+'DCA-Anexo I-F'!E78+'DCA-Anexo I-F'!E92+'DCA-Anexo I-F'!E95+'DCA-Anexo I-F'!E96+'DCA-Anexo I-F'!E76+'DCA-Anexo I-F'!E93+'DCA-Anexo I-F'!E77+'DCA-Anexo I-F'!E91 -> 0 | F75: =+'DCA-Anexo I-F'!F94+'DCA-Anexo I-F'!F78+'DCA-Anexo I-F'!F92+'DCA-Anexo I-F'!F95+'DCA-Anexo I-F'!F96+'DCA-Anexo I-F'!F76+'DCA-Anexo I-F'!F93+'DCA-Anexo I-F'!F77+'DCA-Anexo I-F'!F91 -> 0 | G75: =+'DCA-Anexo I-F'!G94+'DCA-Anexo I-F'!G78+'DCA-Anexo I-F'!G92+'DCA-Anexo I-F'!G95+'DCA-Anexo I-F'!G96+'DCA-Anexo I-F'!G76+'DCA-Anexo I-F'!G93+'DCA-Anexo I-F'!G77+'DCA-Anexo I-F'!G91 -> 0 | H75: =+'DCA-Anexo I-F'!H94+'DCA-Anexo I-F'!H78+'DCA-Anexo I-F'!H92+'DCA-Anexo I-F'!H95+'DCA-Anexo I-F'!H96+'DCA-Anexo I-F'!H76+'DCA-Anexo I-F'!H93+'DCA-Anexo I-F'!H77+'DCA-Anexo I-F'!H91 -> 0 | I75: =+'DCA-Anexo I-F'!I94+'DCA-Anexo I-F'!I78+'DCA-Anexo I-F'!I92+'DCA-Anexo I-F'!I95+'DCA-Anexo I-F'!I96+'DCA-Anexo I-F'!I76+'DCA-Anexo I-F'!I93+'DCA-Anexo I-F'!I77+'DCA-Anexo I-F'!I91 -> 0 | J75: =+'DCA-Anexo I-F'!J94+'DCA-Anexo I-F'!J78+'DCA-Anexo I-F'!J92+'DCA-Anexo I-F'!J95+'DCA-Anexo I-F'!J96+'DCA-Anexo I-F'!J76+'DCA-Anexo I-F'!J93+'DCA-Anexo I-F'!J77+'DCA-Anexo I-F'!J91 -> 0
A76: 3.1.91.04.00 - Contratação por Tempo Determinado
A77: 3.1.91.08.00 - Outros Benefícios Assistenciais do Servidor e do Militar
A78: 3.1.91.13.00 - Contribuições Patronais | B78: =+'DCA-Anexo I-F'!B79+'DCA-Anexo I-F'!B80+'DCA-Anexo I-F'!B81+'DCA-Anexo I-F'!B82+'DCA-Anexo I-F'!B83+'DCA-Anexo I-F'!B84+'DCA-Anexo I-F'!B85+'DCA-Anexo I-F'!B86+'DCA-Anexo I-F'!B87+'DCA-Anexo I-F'!B88+'DCA-Anexo I-F'!B89+'DCA-Anexo I-F'!B90 -> 0 | C78: =+'DCA-Anexo I-F'!C79+'DCA-Anexo I-F'!C80+'DCA-Anexo I-F'!C81+'DCA-Anexo I-F'!C82+'DCA-Anexo I-F'!C83+'DCA-Anexo I-F'!C84+'DCA-Anexo I-F'!C85+'DCA-Anexo I-F'!C86+'DCA-Anexo I-F'!C87+'DCA-Anexo I-F'!C88+'DCA-Anexo I-F'!C89+'DCA-Anexo I-F'!C90 -> 0 | D78: =+'DCA-Anexo I-F'!D79+'DCA-Anexo I-F'!D80+'DCA-Anexo I-F'!D81+'DCA-Anexo I-F'!D82+'DCA-Anexo I-F'!D83+'DCA-Anexo I-F'!D84+'DCA-Anexo I-F'!D85+'DCA-Anexo I-F'!D86+'DCA-Anexo I-F'!D87+'DCA-Anexo I-F'!D88+'DCA-Anexo I-F'!D89+'DCA-Anexo I-F'!D90 -> 0 | E78: =+'DCA-Anexo I-F'!E79+'DCA-Anexo I-F'!E80+'DCA-Anexo I-F'!E81+'DCA-Anexo I-F'!E82+'DCA-Anexo I-F'!E83+'DCA-Anexo I-F'!E84+'DCA-Anexo I-F'!E85+'DCA-Anexo I-F'!E86+'DCA-Anexo I-F'!E87+'DCA-Anexo I-F'!E88+'DCA-Anexo I-F'!E89+'DCA-Anexo I-F'!E90 -> 0 | F78: =+'DCA-Anexo I-F'!F79+'DCA-Anexo I-F'!F80+'DCA-Anexo I-F'!F81+'DCA-Anexo I-F'!F82+'DCA-Anexo I-F'!F83+'DCA-Anexo I-F'!F84+'DCA-Anexo I-F'!F85+'DCA-Anexo I-F'!F86+'DCA-Anexo I-F'!F87+'DCA-Anexo I-F'!F88+'DCA-Anexo I-F'!F89+'DCA-Anexo I-F'!F90 -> 0 | G78: =+'DCA-Anexo I-F'!G79+'DCA-Anexo I-F'!G80+'DCA-Anexo I-F'!G81+'DCA-Anexo I-F'!G82+'DCA-Anexo I-F'!G83+'DCA-Anexo I-F'!G84+'DCA-Anexo I-F'!G85+'DCA-Anexo I-F'!G86+'DCA-Anexo I-F'!G87+'DCA-Anexo I-F'!G88+'DCA-Anexo I-F'!G89+'DCA-Anexo I-F'!G90 -> 0 | H78: =+'DCA-Anexo I-F'!H79+'DCA-Anexo I-F'!H80+'DCA-Anexo I-F'!H81+'DCA-Anexo I-F'!H82+'DCA-Anexo I-F'!H83+'DCA-Anexo I-F'!H84+'DCA-Anexo I-F'!H85+'DCA-Anexo I-F'!H86+'DCA-Anexo I-F'!H87+'DCA-Anexo I-F'!H88+'DCA-Anexo I-F'!H89+'DCA-Anexo I-F'!H90 -> 0 | I78: =+'DCA-Anexo I-F'!I79+'DCA-Anexo I-F'!I80+'DCA-Anexo I-F'!I81+'DCA-Anexo I-F'!I82+'DCA-Anexo I-F'!I83+'DCA-Anexo I-F'!I84+'DCA-Anexo I-F'!I85+'DCA-Anexo I-F'!I86+'DCA-Anexo I-F'!I87+'DCA-Anexo I-F'!I88+'DCA-Anexo I-F'!I89+'DCA-Anexo I-F'!I90 -> 0 | J78: =+'DCA-Anexo I-F'!J79+'DCA-Anexo I-F'!J80+'DCA-Anexo I-F'!J81+'DCA-Anexo I-F'!J82+'DCA-Anexo I-F'!J83+'DCA-Anexo I-F'!J84+'DCA-Anexo I-F'!J85+'DCA-Anexo I-F'!J86+'DCA-Anexo I-F'!J87+'DCA-Anexo I-F'!J88+'DCA-Anexo I-F'!J89+'DCA-Anexo I-F'!J90 -> 0
A79: 3.1.91.13.02 - Contribuições previdenciárias - INSS
A80: 3.1.91.13.04 - Contribuição de salário-educação
A81: 3.1.91.13.08 - Contribuições previdenciárias - RPPS - pessoal ativo - plano previdenciário
A82: 3.1.91.13.09 - Seguros de acidentes do trabalho
A83: 3.1.91.13.10 - Contribuições previdenciárias - RPPS - pessoal inativo e pensionista - plano previdenciário
A84: 3.1.91.13.11 - Contribuições previdenciárias - RPPS - pessoal ativo - plano financeiro
A85: 3.1.91.13.12 - Contribuições previdenciárias - RPPS - pessoal inativo e pensionista - plano financeiro
A86: 3.1.91.13.20 - Alíquota suplementar de contribuição previdenciária - pessoal ativo - plano previdenciário
A87: 3.1.91.13.21 - Alíquota suplementar de contribuição previdenciária - pessoal inativo e pensionista - plano previdenciário
A88: 3.1.91.13.22 - Alíquota suplementar de contribuição previdenciária - pessoal ativo - plano financeiro
A89: 3.1.91.13.23 - Alíquota suplementar de contribuição previdenciária - pessoal inativo e pensionista - plano financeiro
A90: 3.1.91.13.99 - Outras Obrigações Patronais - Intraorçamentária
... A102: 3.1.99.00.00 - A Definir
A103: 3.2.00.00.00 - Juros e Encargos da Dívida | B103: =+'DCA-Anexo I-F'!B104+'DCA-Anexo I-F'!B105+'DCA-Anexo I-F'!B106+'DCA-Anexo I-F'!B107+'DCA-Anexo I-F'!B108+'DCA-Anexo I-F'!B109+'DCA-Anexo I-F'!B110+'DCA-Anexo I-F'!B111+'DCA-Anexo I-F'!B112+'DCA-Anexo I-F'!B113+'DCA-Anexo I-F'!B114+'DCA-Anexo I-F'!B115+'DCA-Anexo I-F'!B116+'DCA-Anexo I-F'!B117+'DCA-Anexo I-F'!B118+'DCA-Anexo I-F'!B119+'DCA-Anexo I-F'!B121+'DCA-Anexo I-F'!B124+'DCA-Anexo I-F'!B125+'DCA-Anexo I-F'!B126+'DCA-Anexo I-F'!B138+'DCA-Anexo I-F'!B140+'DCA-Anexo I-F'!B141+'DCA-Anexo I-F'!B127+'DCA-Anexo I-F'!B142+'DCA-Anexo I-F'!B143+'DCA-Anexo I-F'!B144+'DCA-Anexo I-F'!B120+'DCA-Anexo I-F'!B122+'DCA-Anexo I-F'!B123+'DCA-Anexo I-F'!B139 -> 0 | C103: =+'DCA-Anexo I-F'!C104+'DCA-Anexo I-F'!C105+'DCA-Anexo I-F'!C106+'DCA-Anexo I-F'!C107+'DCA-Anexo I-F'!C108+'DCA-Anexo I-F'!C109+'DCA-Anexo I-F'!C110+'DCA-Anexo I-F'!C111+'DCA-Anexo I-F'!C112+'DCA-Anexo I-F'!C113+'DCA-Anexo I-F'!C114+'DCA-Anexo I-F'!C115+'DCA-Anexo I-F'!C116+'DCA-Anexo I-F'!C117+'DCA-Anexo I-F'!C118+'DCA-Anexo I-F'!C119+'DCA-Anexo I-F'!C121+'DCA-Anexo I-F'!C124+'DCA-Anexo I-F'!C125+'DCA-Anexo I-F'!C126+'DCA-Anexo I-F'!C138+'DCA-Anexo I-F'!C140+'DCA-Anexo I-F'!C141+'DCA-Anexo I-F'!C127+'DCA-Anexo I-F'!C142+'DCA-Anexo I-F'!C143+'DCA-Anexo I-F'!C144+'DCA-Anexo I-F'!C120+'DCA-Anexo I-F'!C122+'DCA-Anexo I-F'!C123+'DCA-Anexo I-F'!C139 -> 0 | D103: =+'DCA-Anexo I-F'!D104+'DCA-Anexo I-F'!D105+'DCA-Anexo I-F'!D106+'DCA-Anexo I-F'!D107+'DCA-Anexo I-F'!D108+'DCA-Anexo I-F'!D109+'DCA-Anexo I-F'!D110+'DCA-Anexo I-F'!D111+'DCA-Anexo I-F'!D112+'DCA-Anexo I-F'!D113+'DCA-Anexo I-F'!D114+'DCA-Anexo I-F'!D115+'DCA-Anexo I-F'!D116+'DCA-Anexo I-F'!D117+'DCA-Anexo I-F'!D118+'DCA-Anexo I-F'!D119+'DCA-Anexo I-F'!D121+'DCA-Anexo I-F'!D124+'DCA-Anexo I-F'!D125+'DCA-Anexo I-F'!D126+'DCA-Anexo I-F'!D138+'DCA-Anexo I-F'!D140+'DCA-Anexo I-F'!D141+'DCA-Anexo I-F'!D127+'DCA-Anexo I-F'!D142+'DCA-Anexo I-F'!D143+'DCA-Anexo I-F'!D144+'DCA-Anexo I-F'!D120+'DCA-Anexo I-F'!D122+'DCA-Anexo I-F'!D123+'DCA-Anexo I-F'!D139 -> 0 | E103: =+'DCA-Anexo I-F'!E104+'DCA-Anexo I-F'!E105+'DCA-Anexo I-F'!E106+'DCA-Anexo I-F'!E107+'DCA-Anexo I-F'!E108+'DCA-Anexo I-F'!E109+'DCA-Anexo I-F'!E110+'DCA-Anexo I-F'!E111+'DCA-Anexo I-F'!E112+'DCA-Anexo I-F'!E113+'DCA-Anexo I-F'!E114+'DCA-Anexo I-F'!E115+'DCA-Anexo I-F'!E116+'DCA-Anexo I-F'!E117+'DCA-Anexo I-F'!E118+'DCA-Anexo I-F'!E119+'DCA-Anexo I-F'!E121+'DCA-Anexo I-F'!E124+'DCA-Anexo I-F'!E125+'DCA-Anexo I-F'!E126+'DCA-Anexo I-F'!E138+'DCA-Anexo I-F'!E140+'DCA-Anexo I-F'!E141+'DCA-Anexo I-F'!E127+'DCA-Anexo I-F'!E142+'DCA-Anexo I-F'!E143+'DCA-Anexo I-F'!E144+'DCA-Anexo I-F'!E120+'DCA-Anexo I-F'!E122+'DCA-Anexo I-F'!E123+'DCA-Anexo I-F'!E139 -> 0 | F103: =+'DCA-Anexo I-F'!F104+'DCA-Anexo I-F'!F105+'DCA-Anexo I-F'!F106+'DCA-Anexo I-F'!F107+'DCA-Anexo I-F'!F108+'DCA-Anexo I-F'!F109+'DCA-Anexo I-F'!F110+'DCA-Anexo I-F'!F111+'DCA-Anexo I-F'!F112+'DCA-Anexo I-F'!F113+'DCA-Anexo I-F'!F114+'DCA-Anexo I-F'!F115+'DCA-Anexo I-F'!F116+'DCA-Anexo I-F'!F117+'DCA-Anexo I-F'!F118+'DCA-Anexo I-F'!F119+'DCA-Anexo I-F'!F121+'DCA-Anexo I-F'!F124+'DCA-Anexo I-F'!F125+'DCA-Anexo I-F'!F126+'DCA-Anexo I-F'!F138+'DCA-Anexo I-F'!F140+'DCA-Anexo I-F'!F141+'DCA-Anexo I-F'!F127+'DCA-Anexo I-F'!F142+'DCA-Anexo I-F'!F143+'DCA-Anexo I-F'!F144+'DCA-Anexo I-F'!F120+'DCA-Anexo I-F'!F122+'DCA-Anexo I-F'!F123+'DCA-Anexo I-F'!F139 -> 0 | G103: =+'DCA-Anexo I-F'!G104+'DCA-Anexo I-F'!G105+'DCA-Anexo I-F'!G106+'DCA-Anexo I-F'!G107+'DCA-Anexo I-F'!G108+'DCA-Anexo I-F'!G109+'DCA-Anexo I-F'!G110+'DCA-Anexo I-F'!G111+'DCA-Anexo I-F'!G112+'DCA-Anexo I-F'!G113+'DCA-Anexo I-F'!G114+'DCA-Anexo I-F'!G115+'DCA-Anexo I-F'!G116+'DCA-Anexo I-F'!G117+'DCA-Anexo I-F'!G118+'DCA-Anexo I-F'!G119+'DCA-Anexo I-F'!G121+'DCA-Anexo I-F'!G124+'DCA-Anexo I-F'!G125+'DCA-Anexo I-F'!G126+'DCA-Anexo I-F'!G138+'DCA-Anexo I-F'!G140+'DCA-Anexo I-F'!G141+'DCA-Anexo I-F'!G127+'DCA-Anexo I-F'!G142+'DCA-Anexo I-F'!G143+'DCA-Anexo I-F'!G144+'DCA-Anexo I-F'!G120+'DCA-Anexo I-F'!G122+'DCA-Anexo I-F'!G123+'DCA-Anexo I-F'!G139 -> 0 | H103: =+'DCA-Anexo I-F'!H104+'DCA-Anexo I-F'!H105+'DCA-Anexo I-F'!H106+'DCA-Anexo I-F'!H107+'DCA-Anexo I-F'!H108+'DCA-Anexo I-F'!H109+'DCA-Anexo I-F'!H110+'DCA-Anexo I-F'!H111+'DCA-Anexo I-F'!H112+'DCA-Anexo I-F'!H113+'DCA-Anexo I-F'!H114+'DCA-Anexo I-F'!H115+'DCA-Anexo I-F'!H116+'DCA-Anexo I-F'!H117+'DCA-Anexo I-F'!H118+'DCA-Anexo I-F'!H119+'DCA-Anexo I-F'!H121+'DCA-Anexo I-F'!H124+'DCA-Anexo I-F'!H125+'DCA-Anexo I-F'!H126+'DCA-Anexo I-F'!H138+'DCA-Anexo I-F'!H140+'DCA-Anexo I-F'!H141+'DCA-Anexo I-F'!H127+'DCA-Anexo I-F'!H142+'DCA-Anexo I-F'!H143+'DCA-Anexo I-F'!H144+'DCA-Anexo I-F'!H120+'DCA-Anexo I-F'!H122+'DCA-Anexo I-F'!H123+'DCA-Anexo I-F'!H139 -> 0 | I103: =+'DCA-Anexo I-F'!I104+'DCA-Anexo I-F'!I105+'DCA-Anexo I-F'!I106+'DCA-Anexo I-F'!I107+'DCA-Anexo I-F'!I108+'DCA-Anexo I-F'!I109+'DCA-Anexo I-F'!I110+'DCA-Anexo I-F'!I111+'DCA-Anexo I-F'!I112+'DCA-Anexo I-F'!I113+'DCA-Anexo I-F'!I114+'DCA-Anexo I-F'!I115+'DCA-Anexo I-F'!I116+'DCA-Anexo I-F'!I117+'DCA-Anexo I-F'!I118+'DCA-Anexo I-F'!I119+'DCA-Anexo I-F'!I121+'DCA-Anexo I-F'!I124+'DCA-Anexo I-F'!I125+'DCA-Anexo I-F'!I126+'DCA-Anexo I-F'!I138+'DCA-Anexo I-F'!I140+'DCA-Anexo I-F'!I141+'DCA-Anexo I-F'!I127+'DCA-Anexo I-F'!I142+'DCA-Anexo I-F'!I143+'DCA-Anexo I-F'!I144+'DCA-Anexo I-F'!I120+'DCA-Anexo I-F'!I122+'DCA-Anexo I-F'!I123+'DCA-Anexo I-F'!I139 -> 0 | J103: =+'DCA-Anexo I-F'!J104+'DCA-Anexo I-F'!J105+'DCA-Anexo I-F'!J106+'DCA-Anexo I-F'!J107+'DCA-Anexo I-F'!J108+'DCA-Anexo I-F'!J109+'DCA-Anexo I-F'!J110+'DCA-Anexo I-F'!J111+'DCA-Anexo I-F'!J112+'DCA-Anexo I-F'!J113+'DCA-Anexo I-F'!J114+'DCA-Anexo I-F'!J115+'DCA-Anexo I-F'!J116+'DCA-Anexo I-F'!J117+'DCA-Anexo I-F'!J118+'DCA-Anexo I-F'!J119+'DCA-Anexo I-F'!J121+'DCA-Anexo I-F'!J124+'DCA-Anexo I-F'!J125+'DCA-Anexo I-F'!J126+'DCA-Anexo I-F'!J138+'DCA-Anexo I-F'!J140+'DCA-Anexo I-F'!J141+'DCA-Anexo I-F'!J127+'DCA-Anexo I-F'!J142+'DCA-Anexo I-F'!J143+'DCA-Anexo I-F'!J144+'DCA-Anexo I-F'!J120+'DCA-Anexo I-F'!J122+'DCA-Anexo I-F'!J123+'DCA-Anexo I-F'!J139 -> 0
A104: 3.2.20.00.00 - Transferências à União
A105: 3.2.22.00.00 - Execução orçamentária delegada à União
A106: 3.2.30.00.00 - Transferências a Estados e ao Distrito Federal
A107: 3.2.31.00.00 - Transferências a Estados e ao Distrito Federal - fundo a fundo
A108: 3.2.32.00.00 - Execução orçamentária delegada a Estados e ao Distrito Federal
A109: 3.2.35.00.00 - Transferências fundo a fundo aos Estados e ao Distrito Federal à conta de recursos de que tratam os §§ 1º e 2º do Art. 24 da Lei Complementar nº 141, de 2012
A110: 3.2.36.00.00 - Transferências fundo a fundo aos Estados e ao Distrito Federal à conta de recursos de que trata o Art. 25 da Lei Complementar nº 141, de 2012
A111: 3.2.40.00.00 - Transferências a Municípios
A112: 3.2.41.00.00 - Transferências a Municípios - fundo a fundo
A113: 3.2.42.00.00 - Execução orçamentária delegada a Municípios
A114: 3.2.45.00.00 - Transferências fundo a fundo aos Municípios à conta de recursos de que tratam os §§ 1º e 2º do Art. 24 da Lei Complementar nº 141, de 2012
A115: 3.2.46.00.00 - Transferências fundo a fundo aos Municípios à conta de recursos de que trata o Art. 25 da Lei Complementar nº 141, de 2012
... A126: 3.2.80.00.00 - Transferências ao exterior
A127: 3.2.90.00.00 - Aplicações Diretas | B127: =+'DCA-Anexo I-F'!B129+'DCA-Anexo I-F'!B137+'DCA-Anexo I-F'!B132+'DCA-Anexo I-F'!B133+'DCA-Anexo I-F'!B128+'DCA-Anexo I-F'!B131+'DCA-Anexo I-F'!B135+'DCA-Anexo I-F'!B130+'DCA-Anexo I-F'!B136+'DCA-Anexo I-F'!B134 -> 0 | C127: =+'DCA-Anexo I-F'!C129+'DCA-Anexo I-F'!C137+'DCA-Anexo I-F'!C132+'DCA-Anexo I-F'!C133+'DCA-Anexo I-F'!C128+'DCA-Anexo I-F'!C131+'DCA-Anexo I-F'!C135+'DCA-Anexo I-F'!C130+'DCA-Anexo I-F'!C136+'DCA-Anexo I-F'!C134 -> 0 | D127: =+'DCA-Anexo I-F'!D129+'DCA-Anexo I-F'!D137+'DCA-Anexo I-F'!D132+'DCA-Anexo I-F'!D133+'DCA-Anexo I-F'!D128+'DCA-Anexo I-F'!D131+'DCA-Anexo I-F'!D135+'DCA-Anexo I-F'!D130+'DCA-Anexo I-F'!D136+'DCA-Anexo I-F'!D134 -> 0 | E127: =+'DCA-Anexo I-F'!E129+'DCA-Anexo I-F'!E137+'DCA-Anexo I-F'!E132+'DCA-Anexo I-F'!E133+'DCA-Anexo I-F'!E128+'DCA-Anexo I-F'!E131+'DCA-Anexo I-F'!E135+'DCA-Anexo I-F'!E130+'DCA-Anexo I-F'!E136+'DCA-Anexo I-F'!E134 -> 0 | F127: =+'DCA-Anexo I-F'!F129+'DCA-Anexo I-F'!F137+'DCA-Anexo I-F'!F132+'DCA-Anexo I-F'!F133+'DCA-Anexo I-F'!F128+'DCA-Anexo I-F'!F131+'DCA-Anexo I-F'!F135+'DCA-Anexo I-F'!F130+'DCA-Anexo I-F'!F136+'DCA-Anexo I-F'!F134 -> 0 | G127: =+'DCA-Anexo I-F'!G129+'DCA-Anexo I-F'!G137+'DCA-Anexo I-F'!G132+'DCA-Anexo I-F'!G133+'DCA-Anexo I-F'!G128+'DCA-Anexo I-F'!G131+'DCA-Anexo I-F'!G135+'DCA-Anexo I-F'!G130+'DCA-Anexo I-F'!G136+'DCA-Anexo I-F'!G134 -> 0 | H127: =+'DCA-Anexo I-F'!H129+'DCA-Anexo I-F'!H137+'DCA-Anexo I-F'!H132+'DCA-Anexo I-F'!H133+'DCA-Anexo I-F'!H128+'DCA-Anexo I-F'!H131+'DCA-Anexo I-F'!H135+'DCA-Anexo I-F'!H130+'DCA-Anexo I-F'!H136+'DCA-Anexo I-F'!H134 -> 0 | I127: =+'DCA-Anexo I-F'!I129+'DCA-Anexo I-F'!I137+'DCA-Anexo I-F'!I132+'DCA-Anexo I-F'!I133+'DCA-Anexo I-F'!I128+'DCA-Anexo I-F'!I131+'DCA-Anexo I-F'!I135+'DCA-Anexo I-F'!I130+'DCA-Anexo I-F'!I136+'DCA-Anexo I-F'!I134 -> 0 | J127: =+'DCA-Anexo I-F'!J129+'DCA-Anexo I-F'!J137+'DCA-Anexo I-F'!J132+'DCA-Anexo I-F'!J133+'DCA-Anexo I-F'!J128+'DCA-Anexo I-F'!J131+'DCA-Anexo I-F'!J135+'DCA-Anexo I-F'!J130+'DCA-Anexo I-F'!J136+'DCA-Anexo I-F'!J134 -> 0
A128: 3.2.90.21.00 - Juros sobre a Dívida por Contrato
A129: 3.2.90.22.00 - Outros Encargos sobre a Dívida por Contrato
A130: 3.2.90.23.00 - Juros, Deságios e Descontos da Dívida Mobiliária
A131: 3.2.90.24.00 - Outros Encargos sobre a Dívida Mobiliária
A132: 3.2.90.25.00 - Encargos sobre Operações de Crédito por Antecipação da Receita
A133: 3.2.90.26.00 - Obrigações Decorrentes de Política Monetária
A134: 3.2.90.91.00 - Sentenças Judiciais
A135: 3.2.90.92.00 - Despesas de Exercícios Anteriores
A136: 3.2.90.93.00 - Indenizações e Restituições
A137: 3.2.90.99.00 - A Classificar
A138: 3.2.91.00.00 - Aplicação direta decorrente de operação entre Órgãos, fundos e entidades integrantes dos OFSS
A139: 3.2.92.00.00 - Aplicação Direta de Recursos Recebidos de Outros Entes da Federação Decorrentes de Delegação ou Descentralização
... A144: 3.2.99.00.00 - A Definir
A145: 3.3.00.00.00 - Outras Despesas Correntes | B145: =+'DCA-Anexo I-F'!B180+'DCA-Anexo I-F'!B158+'DCA-Anexo I-F'!B157+'DCA-Anexo I-F'!B232+'DCA-Anexo I-F'!B148+'DCA-Anexo I-F'!B178+'DCA-Anexo I-F'!B234+'DCA-Anexo I-F'!B231+'DCA-Anexo I-F'!B167+'DCA-Anexo I-F'!B172+'DCA-Anexo I-F'!B156+'DCA-Anexo I-F'!B169+'DCA-Anexo I-F'!B175+'DCA-Anexo I-F'!B168+'DCA-Anexo I-F'!B146+'DCA-Anexo I-F'!B165+'DCA-Anexo I-F'!B154+'DCA-Anexo I-F'!B230+'DCA-Anexo I-F'!B147+'DCA-Anexo I-F'!B174+'DCA-Anexo I-F'!B233+'DCA-Anexo I-F'!B177+'DCA-Anexo I-F'!B166+'DCA-Anexo I-F'!B170+'DCA-Anexo I-F'!B155+'DCA-Anexo I-F'!B179+'DCA-Anexo I-F'!B173+'DCA-Anexo I-F'!B176+'DCA-Anexo I-F'!B171+'DCA-Anexo I-F'!B228+'DCA-Anexo I-F'!B229 -> 54275.76 | C145: =+'DCA-Anexo I-F'!C180+'DCA-Anexo I-F'!C158+'DCA-Anexo I-F'!C157+'DCA-Anexo I-F'!C232+'DCA-Anexo I-F'!C148+'DCA-Anexo I-F'!C178+'DCA-Anexo I-F'!C234+'DCA-Anexo I-F'!C231+'DCA-Anexo I-F'!C167+'DCA-Anexo I-F'!C172+'DCA-Anexo I-F'!C156+'DCA-Anexo I-F'!C169+'DCA-Anexo I-F'!C175+'DCA-Anexo I-F'!C168+'DCA-Anexo I-F'!C146+'DCA-Anexo I-F'!C165+'DCA-Anexo I-F'!C154+'DCA-Anexo I-F'!C230+'DCA-Anexo I-F'!C147+'DCA-Anexo I-F'!C174+'DCA-Anexo I-F'!C233+'DCA-Anexo I-F'!C177+'DCA-Anexo I-F'!C166+'DCA-Anexo I-F'!C170+'DCA-Anexo I-F'!C155+'DCA-Anexo I-F'!C179+'DCA-Anexo I-F'!C173+'DCA-Anexo I-F'!C176+'DCA-Anexo I-F'!C171+'DCA-Anexo I-F'!C228+'DCA-Anexo I-F'!C229 -> 20650.4 | D145: =+'DCA-Anexo I-F'!D180+'DCA-Anexo I-F'!D158+'DCA-Anexo I-F'!D157+'DCA-Anexo I-F'!D232+'DCA-Anexo I-F'!D148+'DCA-Anexo I-F'!D178+'DCA-Anexo I-F'!D234+'DCA-Anexo I-F'!D231+'DCA-Anexo I-F'!D167+'DCA-Anexo I-F'!D172+'DCA-Anexo I-F'!D156+'DCA-Anexo I-F'!D169+'DCA-Anexo I-F'!D175+'DCA-Anexo I-F'!D168+'DCA-Anexo I-F'!D146+'DCA-Anexo I-F'!D165+'DCA-Anexo I-F'!D154+'DCA-Anexo I-F'!D230+'DCA-Anexo I-F'!D147+'DCA-Anexo I-F'!D174+'DCA-Anexo I-F'!D233+'DCA-Anexo I-F'!D177+'DCA-Anexo I-F'!D166+'DCA-Anexo I-F'!D170+'DCA-Anexo I-F'!D155+'DCA-Anexo I-F'!D179+'DCA-Anexo I-F'!D173+'DCA-Anexo I-F'!D176+'DCA-Anexo I-F'!D171+'DCA-Anexo I-F'!D228+'DCA-Anexo I-F'!D229 -> 20650.4 | E145: =+'DCA-Anexo I-F'!E180+'DCA-Anexo I-F'!E158+'DCA-Anexo I-F'!E157+'DCA-Anexo I-F'!E232+'DCA-Anexo I-F'!E148+'DCA-Anexo I-F'!E178+'DCA-Anexo I-F'!E234+'DCA-Anexo I-F'!E231+'DCA-Anexo I-F'!E167+'DCA-Anexo I-F'!E172+'DCA-Anexo I-F'!E156+'DCA-Anexo I-F'!E169+'DCA-Anexo I-F'!E175+'DCA-Anexo I-F'!E168+'DCA-Anexo I-F'!E146+'DCA-Anexo I-F'!E165+'DCA-Anexo I-F'!E154+'DCA-Anexo I-F'!E230+'DCA-Anexo I-F'!E147+'DCA-Anexo I-F'!E174+'DCA-Anexo I-F'!E233+'DCA-Anexo I-F'!E177+'DCA-Anexo I-F'!E166+'DCA-Anexo I-F'!E170+'DCA-Anexo I-F'!E155+'DCA-Anexo I-F'!E179+'DCA-Anexo I-F'!E173+'DCA-Anexo I-F'!E176+'DCA-Anexo I-F'!E171+'DCA-Anexo I-F'!E228+'DCA-Anexo I-F'!E229 -> 20650.4 | F145: =+'DCA-Anexo I-F'!F180+'DCA-Anexo I-F'!F158+'DCA-Anexo I-F'!F157+'DCA-Anexo I-F'!F232+'DCA-Anexo I-F'!F148+'DCA-Anexo I-F'!F178+'DCA-Anexo I-F'!F234+'DCA-Anexo I-F'!F231+'DCA-Anexo I-F'!F167+'DCA-Anexo I-F'!F172+'DCA-Anexo I-F'!F156+'DCA-Anexo I-F'!F169+'DCA-Anexo I-F'!F175+'DCA-Anexo I-F'!F168+'DCA-Anexo I-F'!F146+'DCA-Anexo I-F'!F165+'DCA-Anexo I-F'!F154+'DCA-Anexo I-F'!F230+'DCA-Anexo I-F'!F147+'DCA-Anexo I-F'!F174+'DCA-Anexo I-F'!F233+'DCA-Anexo I-F'!F177+'DCA-Anexo I-F'!F166+'DCA-Anexo I-F'!F170+'DCA-Anexo I-F'!F155+'DCA-Anexo I-F'!F179+'DCA-Anexo I-F'!F173+'DCA-Anexo I-F'!F176+'DCA-Anexo I-F'!F171+'DCA-Anexo I-F'!F228+'DCA-Anexo I-F'!F229 -> 0 | G145: =+'DCA-Anexo I-F'!G180+'DCA-Anexo I-F'!G158+'DCA-Anexo I-F'!G157+'DCA-Anexo I-F'!G232+'DCA-Anexo I-F'!G148+'DCA-Anexo I-F'!G178+'DCA-Anexo I-F'!G234+'DCA-Anexo I-F'!G231+'DCA-Anexo I-F'!G167+'DCA-Anexo I-F'!G172+'DCA-Anexo I-F'!G156+'DCA-Anexo I-F'!G169+'DCA-Anexo I-F'!G175+'DCA-Anexo I-F'!G168+'DCA-Anexo I-F'!G146+'DCA-Anexo I-F'!G165+'DCA-Anexo I-F'!G154+'DCA-Anexo I-F'!G230+'DCA-Anexo I-F'!G147+'DCA-Anexo I-F'!G174+'DCA-Anexo I-F'!G233+'DCA-Anexo I-F'!G177+'DCA-Anexo I-F'!G166+'DCA-Anexo I-F'!G170+'DCA-Anexo I-F'!G155+'DCA-Anexo I-F'!G179+'DCA-Anexo I-F'!G173+'DCA-Anexo I-F'!G176+'DCA-Anexo I-F'!G171+'DCA-Anexo I-F'!G228+'DCA-Anexo I-F'!G229 -> 629266.49 | H145: =+'DCA-Anexo I-F'!H180+'DCA-Anexo I-F'!H158+'DCA-Anexo I-F'!H157+'DCA-Anexo I-F'!H232+'DCA-Anexo I-F'!H148+'DCA-Anexo I-F'!H178+'DCA-Anexo I-F'!H234+'DCA-Anexo I-F'!H231+'DCA-Anexo I-F'!H167+'DCA-Anexo I-F'!H172+'DCA-Anexo I-F'!H156+'DCA-Anexo I-F'!H169+'DCA-Anexo I-F'!H175+'DCA-Anexo I-F'!H168+'DCA-Anexo I-F'!H146+'DCA-Anexo I-F'!H165+'DCA-Anexo I-F'!H154+'DCA-Anexo I-F'!H230+'DCA-Anexo I-F'!H147+'DCA-Anexo I-F'!H174+'DCA-Anexo I-F'!H233+'DCA-Anexo I-F'!H177+'DCA-Anexo I-F'!H166+'DCA-Anexo I-F'!H170+'DCA-Anexo I-F'!H155+'DCA-Anexo I-F'!H179+'DCA-Anexo I-F'!H173+'DCA-Anexo I-F'!H176+'DCA-Anexo I-F'!H171+'DCA-Anexo I-F'!H228+'DCA-Anexo I-F'!H229 -> 255735.16 | I145: =+'DCA-Anexo I-F'!I180+'DCA-Anexo I-F'!I158+'DCA-Anexo I-F'!I157+'DCA-Anexo I-F'!I232+'DCA-Anexo I-F'!I148+'DCA-Anexo I-F'!I178+'DCA-Anexo I-F'!I234+'DCA-Anexo I-F'!I231+'DCA-Anexo I-F'!I167+'DCA-Anexo I-F'!I172+'DCA-Anexo I-F'!I156+'DCA-Anexo I-F'!I169+'DCA-Anexo I-F'!I175+'DCA-Anexo I-F'!I168+'DCA-Anexo I-F'!I146+'DCA-Anexo I-F'!I165+'DCA-Anexo I-F'!I154+'DCA-Anexo I-F'!I230+'DCA-Anexo I-F'!I147+'DCA-Anexo I-F'!I174+'DCA-Anexo I-F'!I233+'DCA-Anexo I-F'!I177+'DCA-Anexo I-F'!I166+'DCA-Anexo I-F'!I170+'DCA-Anexo I-F'!I155+'DCA-Anexo I-F'!I179+'DCA-Anexo I-F'!I173+'DCA-Anexo I-F'!I176+'DCA-Anexo I-F'!I171+'DCA-Anexo I-F'!I228+'DCA-Anexo I-F'!I229 -> 253193.61 | J145: =+'DCA-Anexo I-F'!J180+'DCA-Anexo I-F'!J158+'DCA-Anexo I-F'!J157+'DCA-Anexo I-F'!J232+'DCA-Anexo I-F'!J148+'DCA-Anexo I-F'!J178+'DCA-Anexo I-F'!J234+'DCA-Anexo I-F'!J231+'DCA-Anexo I-F'!J167+'DCA-Anexo I-F'!J172+'DCA-Anexo I-F'!J156+'DCA-Anexo I-F'!J169+'DCA-Anexo I-F'!J175+'DCA-Anexo I-F'!J168+'DCA-Anexo I-F'!J146+'DCA-Anexo I-F'!J165+'DCA-Anexo I-F'!J154+'DCA-Anexo I-F'!J230+'DCA-Anexo I-F'!J147+'DCA-Anexo I-F'!J174+'DCA-Anexo I-F'!J233+'DCA-Anexo I-F'!J177+'DCA-Anexo I-F'!J166+'DCA-Anexo I-F'!J170+'DCA-Anexo I-F'!J155+'DCA-Anexo I-F'!J179+'DCA-Anexo I-F'!J173+'DCA-Anexo I-F'!J176+'DCA-Anexo I-F'!J171+'DCA-Anexo I-F'!J228+'DCA-Anexo I-F'!J229 -> 0
...

Sheet DCA-Anexo I-G
A2: QDCC
A3: BALANÇO ANUAL (DCA)
A4: VERSÃO: v14
A5: VIGÊNCIA: 05/01/2026
A7: Ente: 2908101 - Cocos/BA
A8: Poder: E - Executivo
A9: Instituição: 4063 - Prefeitura Municipal de Cocos - BA
A10: Exercício: 2025
A11: Periodicidade: ANUAL
A12: Período: Período único (anual)
A14: Grupo: Balanço Orçamentário - Despesas por Função - Sub Quadro - Execução dos Restos a Pagar
A15: Quadro: Despesas por Função
A16: Rótulo: Total Geral da Despesa por Função
A17: Despesas por Função | B17: Execução da Despesa
B18: Restos a Pagar Não Processados Inscritos em Exercícios Anteriores | C18: Restos a Pagar Não Processados Inscritos em 31 de Dezembro do Exercício Anterior | D18: Restos a Pagar Não Processados Liquidados | E18: Restos a Pagar Não Processados Pagos | F18: Restos a Pagar Não Processados Cancelados | G18: Restos a Pagar Processados Inscritos em Exercícios Anteriores | H18: Restos a Pagar Processados Inscritos em 31 de Dezembro do Exercício Anterior | I18: Restos a Pagar Processados Pagos | J18: Restos a Pagar Processados Cancelados
A19: Despesas Exceto Intraorçamentárias | B19: =+'DCA-Anexo I-G'!B20+'DCA-Anexo I-G'!B25+'DCA-Anexo I-G'!B30+'DCA-Anexo I-G'!B35+'DCA-Anexo I-G'!B48+'DCA-Anexo I-G'!B54+'DCA-Anexo I-G'!B60+'DCA-Anexo I-G'!B65+'DCA-Anexo I-G'!B74+'DCA-Anexo I-G'!B81+'DCA-Anexo I-G'!B90+'DCA-Anexo I-G'!B97+'DCA-Anexo I-G'!B108+'DCA-Anexo I-G'!B113+'DCA-Anexo I-G'!B119+'DCA-Anexo I-G'!B125+'DCA-Anexo I-G'!B130+'DCA-Anexo I-G'!B135+'DCA-Anexo I-G'!B143+'DCA-Anexo I-G'!B149+'DCA-Anexo I-G'!B157+'DCA-Anexo I-G'!B162+'DCA-Anexo I-G'!B170+'DCA-Anexo I-G'!B178+'DCA-Anexo I-G'!B183+'DCA-Anexo I-G'!B190+'DCA-Anexo I-G'!B198+'DCA-Anexo I-G'!B204 -> 62175.76 | C19: =+'DCA-Anexo I-G'!C20+'DCA-Anexo I-G'!C25+'DCA-Anexo I-G'!C30+'DCA-Anexo I-G'!C35+'DCA-Anexo I-G'!C48+'DCA-Anexo I-G'!C54+'DCA-Anexo I-G'!C60+'DCA-Anexo I-G'!C65+'DCA-Anexo I-G'!C74+'DCA-Anexo I-G'!C81+'DCA-Anexo I-G'!C90+'DCA-Anexo I-G'!C97+'DCA-Anexo I-G'!C108+'DCA-Anexo I-G'!C113+'DCA-Anexo I-G'!C119+'DCA-Anexo I-G'!C125+'DCA-Anexo I-G'!C130+'DCA-Anexo I-G'!C135+'DCA-Anexo I-G'!C143+'DCA-Anexo I-G'!C149+'DCA-Anexo I-G'!C157+'DCA-Anexo I-G'!C162+'DCA-Anexo I-G'!C170+'DCA-Anexo I-G'!C178+'DCA-Anexo I-G'!C183+'DCA-Anexo I-G'!C190+'DCA-Anexo I-G'!C198+'DCA-Anexo I-G'!C204 -> 20650.4 | D19: =+'DCA-Anexo I-G'!D20+'DCA-Anexo I-G'!D25+'DCA-Anexo I-G'!D30+'DCA-Anexo I-G'!D35+'DCA-Anexo I-G'!D48+'DCA-Anexo I-G'!D54+'DCA-Anexo I-G'!D60+'DCA-Anexo I-G'!D65+'DCA-Anexo I-G'!D74+'DCA-Anexo I-G'!D81+'DCA-Anexo I-G'!D90+'DCA-Anexo I-G'!D97+'DCA-Anexo I-G'!D108+'DCA-Anexo I-G'!D113+'DCA-Anexo I-G'!D119+'DCA-Anexo I-G'!D125+'DCA-Anexo I-G'!D130+'DCA-Anexo I-G'!D135+'DCA-Anexo I-G'!D143+'DCA-Anexo I-G'!D149+'DCA-Anexo I-G'!D157+'DCA-Anexo I-G'!D162+'DCA-Anexo I-G'!D170+'DCA-Anexo I-G'!D178+'DCA-Anexo I-G'!D183+'DCA-Anexo I-G'!D190+'DCA-Anexo I-G'!D198+'DCA-Anexo I-G'!D204 -> 20650.4 | E19: =+'DCA-Anexo I-G'!E20+'DCA-Anexo I-G'!E25+'DCA-Anexo I-G'!E30+'DCA-Anexo I-G'!E35+'DCA-Anexo I-G'!E48+'DCA-Anexo I-G'!E54+'DCA-Anexo I-G'!E60+'DCA-Anexo I-G'!E65+'DCA-Anexo I-G'!E74+'DCA-Anexo I-G'!E81+'DCA-Anexo I-G'!E90+'DCA-Anexo I-G'!E97+'DCA-Anexo I-G'!E108+'DCA-Anexo I-G'!E113+'DCA-Anexo I-G'!E119+'DCA-Anexo I-G'!E125+'DCA-Anexo I-G'!E130+'DCA-Anexo I-G'!E135+'DCA-Anexo I-G'!E143+'DCA-Anexo I-G'!E149+'DCA-Anexo I-G'!E157+'DCA-Anexo I-G'!E162+'DCA-Anexo I-G'!E170+'DCA-Anexo I-G'!E178+'DCA-Anexo I-G'!E183+'DCA-Anexo I-G'!E190+'DCA-Anexo I-G'!E198+'DCA-Anexo I-G'!E204 -> 20650.4 | F19: =+'DCA-Anexo I-G'!F20+'DCA-Anexo I-G'!F25+'DCA-Anexo I-G'!F30+'DCA-Anexo I-G'!F35+'DCA-Anexo I-G'!F48+'DCA-Anexo I-G'!F54+'DCA-Anexo I-G'!F60+'DCA-Anexo I-G'!F65+'DCA-Anexo I-G'!F74+'DCA-Anexo I-G'!F81+'DCA-Anexo I-G'!F90+'DCA-Anexo I-G'!F97+'DCA-Anexo I-G'!F108+'DCA-Anexo I-G'!F113+'DCA-Anexo I-G'!F119+'DCA-Anexo I-G'!F125+'DCA-Anexo I-G'!F130+'DCA-Anexo I-G'!F135+'DCA-Anexo I-G'!F143+'DCA-Anexo I-G'!F149+'DCA-Anexo I-G'!F157+'DCA-Anexo I-G'!F162+'DCA-Anexo I-G'!F170+'DCA-Anexo I-G'!F178+'DCA-Anexo I-G'!F183+'DCA-Anexo I-G'!F190+'DCA-Anexo I-G'!F198+'DCA-Anexo I-G'!F204 -> 0 | G19: =+'DCA-Anexo I-G'!G20+'DCA-Anexo I-G'!G25+'DCA-Anexo I-G'!G30+'DCA-Anexo I-G'!G35+'DCA-Anexo I-G'!G48+'DCA-Anexo I-G'!G54+'DCA-Anexo I-G'!G60+'DCA-Anexo I-G'!G65+'DCA-Anexo I-G'!G74+'DCA-Anexo I-G'!G81+'DCA-Anexo I-G'!G90+'DCA-Anexo I-G'!G97+'DCA-Anexo I-G'!G108+'DCA-Anexo I-G'!G113+'DCA-Anexo I-G'!G119+'DCA-Anexo I-G'!G125+'DCA-Anexo I-G'!G130+'DCA-Anexo I-G'!G135+'DCA-Anexo I-G'!G143+'DCA-Anexo I-G'!G149+'DCA-Anexo I-G'!G157+'DCA-Anexo I-G'!G162+'DCA-Anexo I-G'!G170+'DCA-Anexo I-G'!G178+'DCA-Anexo I-G'!G183+'DCA-Anexo I-G'!G190+'DCA-Anexo I-G'!G198+'DCA-Anexo I-G'!G204 -> 678963.1 | H19: =+'DCA-Anexo I-G'!H20+'DCA-Anexo I-G'!H25+'DCA-Anexo I-G'!H30+'DCA-Anexo I-G'!H35+'DCA-Anexo I-G'!H48+'DCA-Anexo I-G'!H54+'DCA-Anexo I-G'!H60+'DCA-Anexo I-G'!H65+'DCA-Anexo I-G'!H74+'DCA-Anexo I-G'!H81+'DCA-Anexo I-G'!H90+'DCA-Anexo I-G'!H97+'DCA-Anexo I-G'!H108+'DCA-Anexo I-G'!H113+'DCA-Anexo I-G'!H119+'DCA-Anexo I-G'!H125+'DCA-Anexo I-G'!H130+'DCA-Anexo I-G'!H135+'DCA-Anexo I-G'!H143+'DCA-Anexo I-G'!H149+'DCA-Anexo I-G'!H157+'DCA-Anexo I-G'!H162+'DCA-Anexo I-G'!H170+'DCA-Anexo I-G'!H178+'DCA-Anexo I-G'!H183+'DCA-Anexo I-G'!H190+'DCA-Anexo I-G'!H198+'DCA-Anexo I-G'!H204 -> 513963.84 | I19: =+'DCA-Anexo I-G'!I20+'DCA-Anexo I-G'!I25+'DCA-Anexo I-G'!I30+'DCA-Anexo I-G'!I35+'DCA-Anexo I-G'!I48+'DCA-Anexo I-G'!I54+'DCA-Anexo I-G'!I60+'DCA-Anexo I-G'!I65+'DCA-Anexo I-G'!I74+'DCA-Anexo I-G'!I81+'DCA-Anexo I-G'!I90+'DCA-Anexo I-G'!I97+'DCA-Anexo I-G'!I108+'DCA-Anexo I-G'!I113+'DCA-Anexo I-G'!I119+'DCA-Anexo I-G'!I125+'DCA-Anexo I-G'!I130+'DCA-Anexo I-G'!I135+'DCA-Anexo I-G'!I143+'DCA-Anexo I-G'!I149+'DCA-Anexo I-G'!I157+'DCA-Anexo I-G'!I162+'DCA-Anexo I-G'!I170+'DCA-Anexo I-G'!I178+'DCA-Anexo I-G'!I183+'DCA-Anexo I-G'!I190+'DCA-Anexo I-G'!I198+'DCA-Anexo I-G'!I204 -> 511422.29 | J19: =+'DCA-Anexo I-G'!J20+'DCA-Anexo I-G'!J25+'DCA-Anexo I-G'!J30+'DCA-Anexo I-G'!J35+'DCA-Anexo I-G'!J48+'DCA-Anexo I-G'!J54+'DCA-Anexo I-G'!J60+'DCA-Anexo I-G'!J65+'DCA-Anexo I-G'!J74+'DCA-Anexo I-G'!J81+'DCA-Anexo I-G'!J90+'DCA-Anexo I-G'!J97+'DCA-Anexo I-G'!J108+'DCA-Anexo I-G'!J113+'DCA-Anexo I-G'!J119+'DCA-Anexo I-G'!J125+'DCA-Anexo I-G'!J130+'DCA-Anexo I-G'!J135+'DCA-Anexo I-G'!J143+'DCA-Anexo I-G'!J149+'DCA-Anexo I-G'!J157+'DCA-Anexo I-G'!J162+'DCA-Anexo I-G'!J170+'DCA-Anexo I-G'!J178+'DCA-Anexo I-G'!J183+'DCA-Anexo I-G'!J190+'DCA-Anexo I-G'!J198+'DCA-Anexo I-G'!J204 -> 0
A20: 01 - Legislativa | B20: =+'DCA-Anexo I-G'!B21+'DCA-Anexo I-G'!B22+'DCA-Anexo I-G'!B24+'DCA-Anexo I-G'!B23 -> 0 | C20: =+'DCA-Anexo I-G'!C21+'DCA-Anexo I-G'!C22+'DCA-Anexo I-G'!C24+'DCA-Anexo I-G'!C23 -> 0 | D20: =+'DCA-Anexo I-G'!D21+'DCA-Anexo I-G'!D22+'DCA-Anexo I-G'!D24+'DCA-Anexo I-G'!D23 -> 0 | E20: =+'DCA-Anexo I-G'!E21+'DCA-Anexo I-G'!E22+'DCA-Anexo I-G'!E24+'DCA-Anexo I-G'!E23 -> 0 | F20: =+'DCA-Anexo I-G'!F21+'DCA-Anexo I-G'!F22+'DCA-Anexo I-G'!F24+'DCA-Anexo I-G'!F23 -> 0 | G20: =+'DCA-Anexo I-G'!G21+'DCA-Anexo I-G'!G22+'DCA-Anexo I-G'!G24+'DCA-Anexo I-G'!G23 -> 0 | H20: =+'DCA-Anexo I-G'!H21+'DCA-Anexo I-G'!H22+'DCA-Anexo I-G'!H24+'DCA-Anexo I-G'!H23 -> 0 | I20: =+'DCA-Anexo I-G'!I21+'DCA-Anexo I-G'!I22+'DCA-Anexo I-G'!I24+'DCA-Anexo I-G'!I23 -> 0 | J20: =+'DCA-Anexo I-G'!J21+'DCA-Anexo I-G'!J22+'DCA-Anexo I-G'!J24+'DCA-Anexo I-G'!J23 -> 0
A21: 01.031 - Ação Legislativa
A22: 01.032 - Controle Externo
A23: 01.122 - Administração Geral
A24: FU01 - Demais Subfunções
A25: 02 - Judiciária | B25: =+'DCA-Anexo I-G'!B26+'DCA-Anexo I-G'!B27+'DCA-Anexo I-G'!B29+'DCA-Anexo I-G'!B28 -> 0 | C25: =+'DCA-Anexo I-G'!C26+'DCA-Anexo I-G'!C27+'DCA-Anexo I-G'!C29+'DCA-Anexo I-G'!C28 -> 0 | D25: =+'DCA-Anexo I-G'!D26+'DCA-Anexo I-G'!D27+'DCA-Anexo I-G'!D29+'DCA-Anexo I-G'!D28 -> 0 | E25: =+'DCA-Anexo I-G'!E26+'DCA-Anexo I-G'!E27+'DCA-Anexo I-G'!E29+'DCA-Anexo I-G'!E28 -> 0 | F25: =+'DCA-Anexo I-G'!F26+'DCA-Anexo I-G'!F27+'DCA-Anexo I-G'!F29+'DCA-Anexo I-G'!F28 -> 0 | G25: =+'DCA-Anexo I-G'!G26+'DCA-Anexo I-G'!G27+'DCA-Anexo I-G'!G29+'DCA-Anexo I-G'!G28 -> 0 | H25: =+'DCA-Anexo I-G'!H26+'DCA-Anexo I-G'!H27+'DCA-Anexo I-G'!H29+'DCA-Anexo I-G'!H28 -> 0 | I25: =+'DCA-Anexo I-G'!I26+'DCA-Anexo I-G'!I27+'DCA-Anexo I-G'!I29+'DCA-Anexo I-G'!I28 -> 0 | J25: =+'DCA-Anexo I-G'!J26+'DCA-Anexo I-G'!J27+'DCA-Anexo I-G'!J29+'DCA-Anexo I-G'!J28 -> 0
A26: 02.061 - Ação Judiciária
A27: 02.062 - Defesa do Interesse Público no Processo Judiciário
A28: 02.122 - Administração Geral
A29: FU02 - Demais Subfunções
A30: 03 - Essencial à Justiça | B30: =+'DCA-Anexo I-G'!B31+'DCA-Anexo I-G'!B32+'DCA-Anexo I-G'!B34+'DCA-Anexo I-G'!B33 -> 0 | C30: =+'DCA-Anexo I-G'!C31+'DCA-Anexo I-G'!C32+'DCA-Anexo I-G'!C34+'DCA-Anexo I-G'!C33 -> 0 | D30: =+'DCA-Anexo I-G'!D31+'DCA-Anexo I-G'!D32+'DCA-Anexo I-G'!D34+'DCA-Anexo I-G'!D33 -> 0 | E30: =+'DCA-Anexo I-G'!E31+'DCA-Anexo I-G'!E32+'DCA-Anexo I-G'!E34+'DCA-Anexo I-G'!E33 -> 0 | F30: =+'DCA-Anexo I-G'!F31+'DCA-Anexo I-G'!F32+'DCA-Anexo I-G'!F34+'DCA-Anexo I-G'!F33 -> 0 | G30: =+'DCA-Anexo I-G'!G31+'DCA-Anexo I-G'!G32+'DCA-Anexo I-G'!G34+'DCA-Anexo I-G'!G33 -> 0 | H30: =+'DCA-Anexo I-G'!H31+'DCA-Anexo I-G'!H32+'DCA-Anexo I-G'!H34+'DCA-Anexo I-G'!H33 -> 0 | I30: =+'DCA-Anexo I-G'!I31+'DCA-Anexo I-G'!I32+'DCA-Anexo I-G'!I34+'DCA-Anexo I-G'!I33 -> 0 | J30: =+'DCA-Anexo I-G'!J31+'DCA-Anexo I-G'!J32+'DCA-Anexo I-G'!J34+'DCA-Anexo I-G'!J33 -> 0
A31: 03.091 - Defesa da Ordem Jurídica
A32: 03.092 - Representação Judicial e Extrajudicial
A33: 03.122 - Administração Geral
A34: FU03 - Demais Subfunções
A35: 04 - Administração | B35: =+'DCA-Anexo I-G'!B36+'DCA-Anexo I-G'!B37+'DCA-Anexo I-G'!B38+'DCA-Anexo I-G'!B39+'DCA-Anexo I-G'!B40+'DCA-Anexo I-G'!B41+'DCA-Anexo I-G'!B42+'DCA-Anexo I-G'!B43+'DCA-Anexo I-G'!B44+'DCA-Anexo I-G'!B45+'DCA-Anexo I-G'!B46+'DCA-Anexo I-G'!B47 -> 62175.76 | C35: =+'DCA-Anexo I-G'!C36+'DCA-Anexo I-G'!C37+'DCA-Anexo I-G'!C38+'DCA-Anexo I-G'!C39+'DCA-Anexo I-G'!C40+'DCA-Anexo I-G'!C41+'DCA-Anexo I-G'!C42+'DCA-Anexo I-G'!C43+'DCA-Anexo I-G'!C44+'DCA-Anexo I-G'!C45+'DCA-Anexo I-G'!C46+'DCA-Anexo I-G'!C47 -> 20650.4 | D35: =+'DCA-Anexo I-G'!D36+'DCA-Anexo I-G'!D37+'DCA-Anexo I-G'!D38+'DCA-Anexo I-G'!D39+'DCA-Anexo I-G'!D40+'DCA-Anexo I-G'!D41+'DCA-Anexo I-G'!D42+'DCA-Anexo I-G'!D43+'DCA-Anexo I-G'!D44+'DCA-Anexo I-G'!D45+'DCA-Anexo I-G'!D46+'DCA-Anexo I-G'!D47 -> 20650.4 | E35: =+'DCA-Anexo I-G'!E36+'DCA-Anexo I-G'!E37+'DCA-Anexo I-G'!E38+'DCA-Anexo I-G'!E39+'DCA-Anexo I-G'!E40+'DCA-Anexo I-G'!E41+'DCA-Anexo I-G'!E42+'DCA-Anexo I-G'!E43+'DCA-Anexo I-G'!E44+'DCA-Anexo I-G'!E45+'DCA-Anexo I-G'!E46+'DCA-Anexo I-G'!E47 -> 20650.4 | F35: =+'DCA-Anexo I-G'!F36+'DCA-Anexo I-G'!F37+'DCA-Anexo I-G'!F38+'DCA-Anexo I-G'!F39+'DCA-Anexo I-G'!F40+'DCA-Anexo I-G'!F41+'DCA-Anexo I-G'!F42+'DCA-Anexo I-G'!F43+'DCA-Anexo I-G'!F44+'DCA-Anexo I-G'!F45+'DCA-Anexo I-G'!F46+'DCA-Anexo I-G'!F47 -> 0 | G35: =+'DCA-Anexo I-G'!G36+'DCA-Anexo I-G'!G37+'DCA-Anexo I-G'!G38+'DCA-Anexo I-G'!G39+'DCA-Anexo I-G'!G40+'DCA-Anexo I-G'!G41+'DCA-Anexo I-G'!G42+'DCA-Anexo I-G'!G43+'DCA-Anexo I-G'!G44+'DCA-Anexo I-G'!G45+'DCA-Anexo I-G'!G46+'DCA-Anexo I-G'!G47 -> 678963.1 | H35: =+'DCA-Anexo I-G'!H36+'DCA-Anexo I-G'!H37+'DCA-Anexo I-G'!H38+'DCA-Anexo I-G'!H39+'DCA-Anexo I-G'!H40+'DCA-Anexo I-G'!H41+'DCA-Anexo I-G'!H42+'DCA-Anexo I-G'!H43+'DCA-Anexo I-G'!H44+'DCA-Anexo I-G'!H45+'DCA-Anexo I-G'!H46+'DCA-Anexo I-G'!H47 -> 513963.84 | I35: =+'DCA-Anexo I-G'!I36+'DCA-Anexo I-G'!I37+'DCA-Anexo I-G'!I38+'DCA-Anexo I-G'!I39+'DCA-Anexo I-G'!I40+'DCA-Anexo I-G'!I41+'DCA-Anexo I-G'!I42+'DCA-Anexo I-G'!I43+'DCA-Anexo I-G'!I44+'DCA-Anexo I-G'!I45+'DCA-Anexo I-G'!I46+'DCA-Anexo I-G'!I47 -> 511422.29 | J35: =+'DCA-Anexo I-G'!J36+'DCA-Anexo I-G'!J37+'DCA-Anexo I-G'!J38+'DCA-Anexo I-G'!J39+'DCA-Anexo I-G'!J40+'DCA-Anexo I-G'!J41+'DCA-Anexo I-G'!J42+'DCA-Anexo I-G'!J43+'DCA-Anexo I-G'!J44+'DCA-Anexo I-G'!J45+'DCA-Anexo I-G'!J46+'DCA-Anexo I-G'!J47 -> 0
A36: 04.121 - Planejamento e Orçamento
A37: 04.122 - Administração Geral | B37: 62175.76 | C37: 20650.4 | D37: 20650.4 | E37: 20650.4 | F37: 0 | G37: 678963.1 | H37: 513963.84 | I37: 511422.29 | J37: 0
A38: 04.123 - Administração Financeira
A39: 04.124 - Controle Interno
A40: 04.125 - Normatização e Fiscalização
A41: 04.126 - Tecnologia da Informação
A42: 04.127 - Ordenamento Territorial
A43: 04.128 - Formação de Recursos Humanos
A44: 04.129 - Administração de Receitas
A45: 04.130 - Administração de Concessões
A46: 04.131 - Comunicação Social
A47: FU04 - Demais Subfunções
A48: 05 - Defesa Nacional | B48: =+'DCA-Anexo I-G'!B49+'DCA-Anexo I-G'!B50+'DCA-Anexo I-G'!B51+'DCA-Anexo I-G'!B53+'DCA-Anexo I-G'!B52 -> 0 | C48: =+'DCA-Anexo I-G'!C49+'DCA-Anexo I-G'!C50+'DCA-Anexo I-G'!C51+'DCA-Anexo I-G'!C53+'DCA-Anexo I-G'!C52 -> 0 | D48: =+'DCA-Anexo I-G'!D49+'DCA-Anexo I-G'!D50+'DCA-Anexo I-G'!D51+'DCA-Anexo I-G'!D53+'DCA-Anexo I-G'!D52 -> 0 | E48: =+'DCA-Anexo I-G'!E49+'DCA-Anexo I-G'!E50+'DCA-Anexo I-G'!E51+'DCA-Anexo I-G'!E53+'DCA-Anexo I-G'!E52 -> 0 | F48: =+'DCA-Anexo I-G'!F49+'DCA-Anexo I-G'!F50+'DCA-Anexo I-G'!F51+'DCA-Anexo I-G'!F53+'DCA-Anexo I-G'!F52 -> 0 | G48: =+'DCA-Anexo I-G'!G49+'DCA-Anexo I-G'!G50+'DCA-Anexo I-G'!G51+'DCA-Anexo I-G'!G53+'DCA-Anexo I-G'!G52 -> 0 | H48: =+'DCA-Anexo I-G'!H49+'DCA-Anexo I-G'!H50+'DCA-Anexo I-G'!H51+'DCA-Anexo I-G'!H53+'DCA-Anexo I-G'!H52 -> 0 | I48: =+'DCA-Anexo I-G'!I49+'DCA-Anexo I-G'!I50+'DCA-Anexo I-G'!I51+'DCA-Anexo I-G'!I53+'DCA-Anexo I-G'!I52 -> 0 | J48: =+'DCA-Anexo I-G'!J49+'DCA-Anexo I-G'!J50+'DCA-Anexo I-G'!J51+'DCA-Anexo I-G'!J53+'DCA-Anexo I-G'!J52 -> 0
A49: 05.151 - Defesa Aérea
A50: 05.152 - Defesa Naval
A51: 05.153 - Defesa Terrestre
A52: 05.122 - Administração Geral
A53: FU05 - Demais Subfunções
A54: 06 - Segurança Pública | B54: =+'DCA-Anexo I-G'!B55+'DCA-Anexo I-G'!B56+'DCA-Anexo I-G'!B57+'DCA-Anexo I-G'!B59+'DCA-Anexo I-G'!B58 -> 0 | C54: =+'DCA-Anexo I-G'!C55+'DCA-Anexo I-G'!C56+'DCA-Anexo I-G'!C57+'DCA-Anexo I-G'!C59+'DCA-Anexo I-G'!C58 -> 0 | D54: =+'DCA-Anexo I-G'!D55+'DCA-Anexo I-G'!D56+'DCA-Anexo I-G'!D57+'DCA-Anexo I-G'!D59+'DCA-Anexo I-G'!D58 -> 0 | E54: =+'DCA-Anexo I-G'!E55+'DCA-Anexo I-G'!E56+'DCA-Anexo I-G'!E57+'DCA-Anexo I-G'!E59+'DCA-Anexo I-G'!E58 -> 0 | F54: =+'DCA-Anexo I-G'!F55+'DCA-Anexo I-G'!F56+'DCA-Anexo I-G'!F57+'DCA-Anexo I-G'!F59+'DCA-Anexo I-G'!F58 -> 0 | G54: =+'DCA-Anexo I-G'!G55+'DCA-Anexo I-G'!G56+'DCA-Anexo I-G'!G57+'DCA-Anexo I-G'!G59+'DCA-Anexo I-G'!G58 -> 0 | H54: =+'DCA-Anexo I-G'!H55+'DCA-Anexo I-G'!H56+'DCA-Anexo I-G'!H57+'DCA-Anexo I-G'!H59+'DCA-Anexo I-G'!H58 -> 0 | I54: =+'DCA-Anexo I-G'!I55+'DCA-Anexo I-G'!I56+'DCA-Anexo I-G'!I57+'DCA-Anexo I-G'!I59+'DCA-Anexo I-G'!I58 -> 0 | J54: =+'DCA-Anexo I-G'!J55+'DCA-Anexo I-G'!J56+'DCA-Anexo I-G'!J57+'DCA-Anexo I-G'!J59+'DCA-Anexo I-G'!J58 -> 0
A55: 06.181 - Policiamento
A56: 06.182 - Defesa Civil
A57: 06.183 - Informação e Inteligência
A58: 06.122 - Administração Geral
A59: FU06 - Demais Subfunções
A60: 07 - Relações Exteriores | B60: =+'DCA-Anexo I-G'!B61+'DCA-Anexo I-G'!B62+'DCA-Anexo I-G'!B64+'DCA-Anexo I-G'!B63 -> 0 | C60: =+'DCA-Anexo I-G'!C61+'DCA-Anexo I-G'!C62+'DCA-Anexo I-G'!C64+'DCA-Anexo I-G'!C63 -> 0 | D60: =+'DCA-Anexo I-G'!D61+'DCA-Anexo I-G'!D62+'DCA-Anexo I-G'!D64+'DCA-Anexo I-G'!D63 -> 0 | E60: =+'DCA-Anexo I-G'!E61+'DCA-Anexo I-G'!E62+'DCA-Anexo I-G'!E64+'DCA-Anexo I-G'!E63 -> 0 | F60: =+'DCA-Anexo I-G'!F61+'DCA-Anexo I-G'!F62+'DCA-Anexo I-G'!F64+'DCA-Anexo I-G'!F63 -> 0 | G60: =+'DCA-Anexo I-G'!G61+'DCA-Anexo I-G'!G62+'DCA-Anexo I-G'!G64+'DCA-Anexo I-G'!G63 -> 0 | H60: =+'DCA-Anexo I-G'!H61+'DCA-Anexo I-G'!H62+'DCA-Anexo I-G'!H64+'DCA-Anexo I-G'!H63 -> 0 | I60: =+'DCA-Anexo I-G'!I61+'DCA-Anexo I-G'!I62+'DCA-Anexo I-G'!I64+'DCA-Anexo I-G'!I63 -> 0 | J60: =+'DCA-Anexo I-G'!J61+'DCA-Anexo I-G'!J62+'DCA-Anexo I-G'!J64+'DCA-Anexo I-G'!J63 -> 0
A61: 07.211 - Relações Diplomáticas
A62: 07.212 - Cooperação Internacional
A63: 07.122 - Administração Geral
A64: FU07 - Demais Subfunções
A65: 08 - Assistência Social | B65: =+'DCA-Anexo I-G'!B66+'DCA-Anexo I-G'!B67+'DCA-Anexo I-G'!B68+'DCA-Anexo I-G'!B69+'DCA-Anexo I-G'!B73+'DCA-Anexo I-G'!B72+'DCA-Anexo I-G'!B70+'DCA-Anexo I-G'!B71 -> 0 | C65: =+'DCA-Anexo I-G'!C66+'DCA-Anexo I-G'!C67+'DCA-Anexo I-G'!C68+'DCA-Anexo I-G'!C69+'DCA-Anexo I-G'!C73+'DCA-Anexo I-G'!C72+'DCA-Anexo I-G'!C70+'DCA-Anexo I-G'!C71 -> 0 | D65: =+'DCA-Anexo I-G'!D66+'DCA-Anexo I-G'!D67+'DCA-Anexo I-G'!D68+'DCA-Anexo I-G'!D69+'DCA-Anexo I-G'!D73+'DCA-Anexo I-G'!D72+'DCA-Anexo I-G'!D70+'DCA-Anexo I-G'!D71 -> 0 | E65: =+'DCA-Anexo I-G'!E66+'DCA-Anexo I-G'!E67+'DCA-Anexo I-G'!E68+'DCA-Anexo I-G'!E69+'DCA-Anexo I-G'!E73+'DCA-Anexo I-G'!E72+'DCA-Anexo I-G'!E70+'DCA-Anexo I-G'!E71 -> 0 | F65: =+'DCA-Anexo I-G'!F66+'DCA-Anexo I-G'!F67+'DCA-Anexo I-G'!F68+'DCA-Anexo I-G'!F69+'DCA-Anexo I-G'!F73+'DCA-Anexo I-G'!F72+'DCA-Anexo I-G'!F70+'DCA-Anexo I-G'!F71 -> 0 | G65: =+'DCA-Anexo I-G'!G66+'DCA-Anexo I-G'!G67+'DCA-Anexo I-G'!G68+'DCA-Anexo I-G'!G69+'DCA-Anexo I-G'!G73+'DCA-Anexo I-G'!G72+'DCA-Anexo I-G'!G70+'DCA-Anexo I-G'!G71 -> 0 | H65: =+'DCA-Anexo I-G'!H66+'DCA-Anexo I-G'!H67+'DCA-Anexo I-G'!H68+'DCA-Anexo I-G'!H69+'DCA-Anexo I-G'!H73+'DCA-Anexo I-G'!H72+'DCA-Anexo I-G'!H70+'DCA-Anexo I-G'!H71 -> 0 | I65: =+'DCA-Anexo I-G'!I66+'DCA-Anexo I-G'!I67+'DCA-Anexo I-G'!I68+'DCA-Anexo I-G'!I69+'DCA-Anexo I-G'!I73+'DCA-Anexo I-G'!I72+'DCA-Anexo I-G'!I70+'DCA-Anexo I-G'!I71 -> 0 | J65: =+'DCA-Anexo I-G'!J66+'DCA-Anexo I-G'!J67+'DCA-Anexo I-G'!J68+'DCA-Anexo I-G'!J69+'DCA-Anexo I-G'!J73+'DCA-Anexo I-G'!J72+'DCA-Anexo I-G'!J70+'DCA-Anexo I-G'!J71 -> 0
A66: 08.241 - Assistência à Pessoa Idosa
A67: 08.242 - Assistência à Pessoa com Deficiência
A68: 08.243 - Assistência à Criança e ao Adolescente
A69: 08.244 - Assistência Comunitária
A70: 08.245 - Serviços Socioassistenciais
A71: 08.246 - Segurança e Renda
A72: 08.122 - Administração Geral
A73: FU08 - Demais Subfunções
A74: 09 - Previdência Social | B74: =+'DCA-Anexo I-G'!B75+'DCA-Anexo I-G'!B76+'DCA-Anexo I-G'!B77+'DCA-Anexo I-G'!B78+'DCA-Anexo I-G'!B80+'DCA-Anexo I-G'!B79 -> 0 | C74: =+'DCA-Anexo I-G'!C75+'DCA-Anexo I-G'!C76+'DCA-Anexo I-G'!C77+'DCA-Anexo I-G'!C78+'DCA-Anexo I-G'!C80+'DCA-Anexo I-G'!C79 -> 0 | D74: =+'DCA-Anexo I-G'!D75+'DCA-Anexo I-G'!D76+'DCA-Anexo I-G'!D77+'DCA-Anexo I-G'!D78+'DCA-Anexo I-G'!D80+'DCA-Anexo I-G'!D79 -> 0 | E74: =+'DCA-Anexo I-G'!E75+'DCA-Anexo I-G'!E76+'DCA-Anexo I-G'!E77+'DCA-Anexo I-G'!E78+'DCA-Anexo I-G'!E80+'DCA-Anexo I-G'!E79 -> 0 | F74: =+'DCA-Anexo I-G'!F75+'DCA-Anexo I-G'!F76+'DCA-Anexo I-G'!F77+'DCA-Anexo I-G'!F78+'DCA-Anexo I-G'!F80+'DCA-Anexo I-G'!F79 -> 0 | G74: =+'DCA-Anexo I-G'!G75+'DCA-Anexo I-G'!G76+'DCA-Anexo I-G'!G77+'DCA-Anexo I-G'!G78+'DCA-Anexo I-G'!G80+'DCA-Anexo I-G'!G79 -> 0 | H74: =+'DCA-Anexo I-G'!H75+'DCA-Anexo I-G'!H76+'DCA-Anexo I-G'!H77+'DCA-Anexo I-G'!H78+'DCA-Anexo I-G'!H80+'DCA-Anexo I-G'!H79 -> 0 | I74: =+'DCA-Anexo I-G'!I75+'DCA-Anexo I-G'!I76+'DCA-Anexo I-G'!I77+'DCA-Anexo I-G'!I78+'DCA-Anexo I-G'!I80+'DCA-Anexo I-G'!I79 -> 0 | J74: =+'DCA-Anexo I-G'!J75+'DCA-Anexo I-G'!J76+'DCA-Anexo I-G'!J77+'DCA-Anexo I-G'!J78+'DCA-Anexo I-G'!J80+'DCA-Anexo I-G'!J79 -> 0
A75: 09.271 - Previdência Básica
A76: 09.272 - Previdência do Regime Estatutário
A77: 09.273 - Previdência Complementar
A78: 09.274 - Previdência Especial
A79: 09.122 - Administração Geral
A80: FU09 - Demais Subfunções
A81: 10 - Saúde | B81: =+'DCA-Anexo I-G'!B82+'DCA-Anexo I-G'!B83+'DCA-Anexo I-G'!B84+'DCA-Anexo I-G'!B85+'DCA-Anexo I-G'!B86+'DCA-Anexo I-G'!B87+'DCA-Anexo I-G'!B89+'DCA-Anexo I-G'!B88 -> 0 | C81: =+'DCA-Anexo I-G'!C82+'DCA-Anexo I-G'!C83+'DCA-Anexo I-G'!C84+'DCA-Anexo I-G'!C85+'DCA-Anexo I-G'!C86+'DCA-Anexo I-G'!C87+'DCA-Anexo I-G'!C89+'DCA-Anexo I-G'!C88 -> 0 | D81: =+'DCA-Anexo I-G'!D82+'DCA-Anexo I-G'!D83+'DCA-Anexo I-G'!D84+'DCA-Anexo I-G'!D85+'DCA-Anexo I-G'!D86+'DCA-Anexo I-G'!D87+'DCA-Anexo I-G'!D89+'DCA-Anexo I-G'!D88 -> 0 | E81: =+'DCA-Anexo I-G'!E82+'DCA-Anexo I-G'!E83+'DCA-Anexo I-G'!E84+'DCA-Anexo I-G'!E85+'DCA-Anexo I-G'!E86+'DCA-Anexo I-G'!E87+'DCA-Anexo I-G'!E89+'DCA-Anexo I-G'!E88 -> 0 | F81: =+'DCA-Anexo I-G'!F82+'DCA-Anexo I-G'!F83+'DCA-Anexo I-G'!F84+'DCA-Anexo I-G'!F85+'DCA-Anexo I-G'!F86+'DCA-Anexo I-G'!F87+'DCA-Anexo I-G'!F89+'DCA-Anexo I-G'!F88 -> 0 | G81: =+'DCA-Anexo I-G'!G82+'DCA-Anexo I-G'!G83+'DCA-Anexo I-G'!G84+'DCA-Anexo I-G'!G85+'DCA-Anexo I-G'!G86+'DCA-Anexo I-G'!G87+'DCA-Anexo I-G'!G89+'DCA-Anexo I-G'!G88 -> 0 | H81: =+'DCA-Anexo I-G'!H82+'DCA-Anexo I-G'!H83+'DCA-Anexo I-G'!H84+'DCA-Anexo I-G'!H85+'DCA-Anexo I-G'!H86+'DCA-Anexo I-G'!H87+'DCA-Anexo I-G'!H89+'DCA-Anexo I-G'!H88 -> 0 | I81: =+'DCA-Anexo I-G'!I82+'DCA-Anexo I-G'!I83+'DCA-Anexo I-G'!I84+'DCA-Anexo I-G'!I85+'DCA-Anexo I-G'!I86+'DCA-Anexo I-G'!I87+'DCA-Anexo I-G'!I89+'DCA-Anexo I-G'!I88 -> 0 | J81: =+'DCA-Anexo I-G'!J82+'DCA-Anexo I-G'!J83+'DCA-Anexo I-G'!J84+'DCA-Anexo I-G'!J85+'DCA-Anexo I-G'!J86+'DCA-Anexo I-G'!J87+'DCA-Anexo I-G'!J89+'DCA-Anexo I-G'!J88 -> 0
A82: 10.301 - Atenção Básica
A83: 10.302 - Assistência Hospitalar e Ambulatorial
A84: 10.303 - Suporte Profilático e Terapêutico
A85: 10.304 - Vigilância Sanitária
A86: 10.305 - Vigilância Epidemiológica
A87: 10.306 - Alimentação e Nutrição
A88: 10.122 - Administração Geral
A89: FU10 - Demais Subfunções
A90: 11 - Trabalho | B90: =+'DCA-Anexo I-G'!B91+'DCA-Anexo I-G'!B92+'DCA-Anexo I-G'!B93+'DCA-Anexo I-G'!B94+'DCA-Anexo I-G'!B96+'DCA-Anexo I-G'!B95 -> 0 | C90: =+'DCA-Anexo I-G'!C91+'DCA-Anexo I-G'!C92+'DCA-Anexo I-G'!C93+'DCA-Anexo I-G'!C94+'DCA-Anexo I-G'!C96+'DCA-Anexo I-G'!C95 -> 0 | D90: =+'DCA-Anexo I-G'!D91+'DCA-Anexo I-G'!D92+'DCA-Anexo I-G'!D93+'DCA-Anexo I-G'!D94+'DCA-Anexo I-G'!D96+'DCA-Anexo I-G'!D95 -> 0 | E90: =+'DCA-Anexo I-G'!E91+'DCA-Anexo I-G'!E92+'DCA-Anexo I-G'!E93+'DCA-Anexo I-G'!E94+'DCA-Anexo I-G'!E96+'DCA-Anexo I-G'!E95 -> 0 | F90: =+'DCA-Anexo I-G'!F91+'DCA-Anexo I-G'!F92+'DCA-Anexo I-G'!F93+'DCA-Anexo I-G'!F94+'DCA-Anexo I-G'!F96+'DCA-Anexo I-G'!F95 -> 0 | G90: =+'DCA-Anexo I-G'!G91+'DCA-Anexo I-G'!G92+'DCA-Anexo I-G'!G93+'DCA-Anexo I-G'!G94+'DCA-Anexo I-G'!G96+'DCA-Anexo I-G'!G95 -> 0 | H90: =+'DCA-Anexo I-G'!H91+'DCA-Anexo I-G'!H92+'DCA-Anexo I-G'!H93+'DCA-Anexo I-G'!H94+'DCA-Anexo I-G'!H96+'DCA-Anexo I-G'!H95 -> 0 | I90: =+'DCA-Anexo I-G'!I91+'DCA-Anexo I-G'!I92+'DCA-Anexo I-G'!I93+'DCA-Anexo I-G'!I94+'DCA-Anexo I-G'!I96+'DCA-Anexo I-G'!I95 -> 0 | J90: =+'DCA-Anexo I-G'!J91+'DCA-Anexo I-G'!J92+'DCA-Anexo I-G'!J93+'DCA-Anexo I-G'!J94+'DCA-Anexo I-G'!J96+'DCA-Anexo I-G'!J95 -> 0
A91: 11.331 - Proteção e Benefícios ao Trabalhador
A92: 11.332 - Relações de Trabalho
A93: 11.333 - Empregabilidade
A94: 11.334 - Fomento ao Trabalho
A95: 11.122 - Administração Geral
A96: FU11 - Demais Subfunções
A97: 12 - Educação | B97: =+'DCA-Anexo I-G'!B98+'DCA-Anexo I-G'!B99+'DCA-Anexo I-G'!B100+'DCA-Anexo I-G'!B101+'DCA-Anexo I-G'!B102+'DCA-Anexo I-G'!B103+'DCA-Anexo I-G'!B104+'DCA-Anexo I-G'!B105+'DCA-Anexo I-G'!B107+'DCA-Anexo I-G'!B106 -> 0 | C97: =+'DCA-Anexo I-G'!C98+'DCA-Anexo I-G'!C99+'DCA-Anexo I-G'!C100+'DCA-Anexo I-G'!C101+'DCA-Anexo I-G'!C102+'DCA-Anexo I-G'!C103+'DCA-Anexo I-G'!C104+'DCA-Anexo I-G'!C105+'DCA-Anexo I-G'!C107+'DCA-Anexo I-G'!C106 -> 0 | D97: =+'DCA-Anexo I-G'!D98+'DCA-Anexo I-G'!D99+'DCA-Anexo I-G'!D100+'DCA-Anexo I-G'!D101+'DCA-Anexo I-G'!D102+'DCA-Anexo I-G'!D103+'DCA-Anexo I-G'!D104+'DCA-Anexo I-G'!D105+'DCA-Anexo I-G'!D107+'DCA-Anexo I-G'!D106 -> 0 | E97: =+'DCA-Anexo I-G'!E98+'DCA-Anexo I-G'!E99+'DCA-Anexo I-G'!E100+'DCA-Anexo I-G'!E101+'DCA-Anexo I-G'!E102+'DCA-Anexo I-G'!E103+'DCA-Anexo I-G'!E104+'DCA-Anexo I-G'!E105+'DCA-Anexo I-G'!E107+'DCA-Anexo I-G'!E106 -> 0 | F97: =+'DCA-Anexo I-G'!F98+'DCA-Anexo I-G'!F99+'DCA-Anexo I-G'!F100+'DCA-Anexo I-G'!F101+'DCA-Anexo I-G'!F102+'DCA-Anexo I-G'!F103+'DCA-Anexo I-G'!F104+'DCA-Anexo I-G'!F105+'DCA-Anexo I-G'!F107+'DCA-Anexo I-G'!F106 -> 0 | G97: =+'DCA-Anexo I-G'!G98+'DCA-Anexo I-G'!G99+'DCA-Anexo I-G'!G100+'DCA-Anexo I-G'!G101+'DCA-Anexo I-G'!G102+'DCA-Anexo I-G'!G103+'DCA-Anexo I-G'!G104+'DCA-Anexo I-G'!G105+'DCA-Anexo I-G'!G107+'DCA-Anexo I-G'!G106 -> 0 | H97: =+'DCA-Anexo I-G'!H98+'DCA-Anexo I-G'!H99+'DCA-Anexo I-G'!H100+'DCA-Anexo I-G'!H101+'DCA-Anexo I-G'!H102+'DCA-Anexo I-G'!H103+'DCA-Anexo I-G'!H104+'DCA-Anexo I-G'!H105+'DCA-Anexo I-G'!H107+'DCA-Anexo I-G'!H106 -> 0 | I97: =+'DCA-Anexo I-G'!I98+'DCA-Anexo I-G'!I99+'DCA-Anexo I-G'!I100+'DCA-Anexo I-G'!I101+'DCA-Anexo I-G'!I102+'DCA-Anexo I-G'!I103+'DCA-Anexo I-G'!I104+'DCA-Anexo I-G'!I105+'DCA-Anexo I-G'!I107+'DCA-Anexo I-G'!I106 -> 0 | J97: =+'DCA-Anexo I-G'!J98+'DCA-Anexo I-G'!J99+'DCA-Anexo I-G'!J100+'DCA-Anexo I-G'!J101+'DCA-Anexo I-G'!J102+'DCA-Anexo I-G'!J103+'DCA-Anexo I-G'!J104+'DCA-Anexo I-G'!J105+'DCA-Anexo I-G'!J107+'DCA-Anexo I-G'!J106 -> 0
A98: 12.361 - Ensino Fundamental
A99: 12.362 - Ensino Médio
A100: 12.363 - Ensino Profissional
A101: 12.364 - Ensino Superior
A102: 12.365 - Educação Infantil
A103: 12.366 - Educação de Jovens e Adultos
...

Sheet DCA-Anexo I-HI
A2: QDCC
A3: BALANÇO ANUAL (DCA)
A4: VERSÃO: v14
A5: VIGÊNCIA: 05/01/2026
A7: Ente: 2908101 - Cocos/BA
A8: Poder: E - Executivo
A9: Instituição: 4063 - Prefeitura Municipal de Cocos - BA
A10: Exercício: 2025
A11: Periodicidade: ANUAL
A12: Período: Período único (anual)
A14: Grupo: Demonstrativo das Variações Patrimoniais Quantitativas e Resultado Patrimonial do Período
A15: Quadro: Demonstrativo das Variações Patrimoniais e Resultado Patrimonial
A16: Rótulo: Padrão
A17: Demonstrativo das Variações Patrimoniais e Resultado Patrimonial | B17: Valores
B18: 31/12/2025
A19: Variação Patrimonial Diminutiva
A20: Variação Patrimonial Diminutiva
A21: 3.0.0.0.0.00.00 - Variação Patrimonial Diminutiva | B21: =+'DCA-Anexo I-HI'!B22+'DCA-Anexo I-HI'!B302+'DCA-Anexo I-HI'!B360+'DCA-Anexo I-HI'!B493+'DCA-Anexo I-HI'!B131+'DCA-Anexo I-HI'!B80+'DCA-Anexo I-HI'!B426+'DCA-Anexo I-HI'!B165+'DCA-Anexo I-HI'!B471 -> 1.9104898e+08
A22: 3.1.0.0.0.00.00 - Pessoal e Encargos | B22: =+'DCA-Anexo I-HI'!B23+'DCA-Anexo I-HI'!B58+'DCA-Anexo I-HI'!B31+'DCA-Anexo I-HI'!B65 -> 59168230
A23: 3.1.1.0.0.00.00 - Remuneração a Pessoal | B23: =+'DCA-Anexo I-HI'!B24+'DCA-Anexo I-HI'!B27+'DCA-Anexo I-HI'!B29 -> 53305380
A24: 3.1.1.1.0.00.00 - Remuneração a Pessoal Ativo Civil – Abrangidos pelo RPPS | B24: =+'DCA-Anexo I-HI'!B25+'DCA-Anexo I-HI'!B26 -> 53305380
A25: 3.1.1.1.1.00.00 - Remuneração a Pessoal Ativo Civil – Abrangidos pelo RPPS - Consolidação | B25: 53305380
A26: 3.1.1.1.2.00.00 - Remuneração a Pessoal Ativo Civil – Abrangidos pelo RPPS - Intra OFSS | B26: 0
A27: 3.1.1.2.0.00.00 - Remuneração a Pessoal Ativo Civil - Abrangidos pelo RGPS | B27: =+'DCA-Anexo I-HI'!B28 -> 0
A28: 3.1.1.2.1.00.00 - Remuneração a Pessoal Ativo Civil - Abrangidos pelo RGPS - Consolidação | B28: 0
A29: 3.1.1.3.0.00.00 - Remuneração a Pessoal Ativo Militar | B29: =+'DCA-Anexo I-HI'!B30 -> 0
A30: 3.1.1.3.1.00.00 - Remuneração a Pessoal Ativo Militar - Consolidação | B30: 0
A31: 3.1.2.0.0.00.00 - Encargos Patronais | B31: =+'DCA-Anexo I-HI'!B32+'DCA-Anexo I-HI'!B52+'DCA-Anexo I-HI'!B43+'DCA-Anexo I-HI'!B49+'DCA-Anexo I-HI'!B37+'DCA-Anexo I-HI'!B41 -> 5842845.2
A32: 3.1.2.1.0.00.00 - Encargos Patronais - RPPS | B32: =+'DCA-Anexo I-HI'!B33+'DCA-Anexo I-HI'!B35+'DCA-Anexo I-HI'!B34+'DCA-Anexo I-HI'!B36 -> 0
A33: 3.1.2.1.2.00.00 - Encargos Patronais - RPPS - Intra OFSS | B33: 0
A34: 3.1.2.1.3.00.00 - Encargos Patronais - RPPS - Inter OFSS - União | B34: 0
A35: 3.1.2.1.4.00.00 - Encargos Patronais - RPPS - Inter OFSS - Estado | B35: 0
A36: 3.1.2.1.5.00.00 - Encargos Patronais - RPPS - Inter OFSS - Município | B36: 0
A37: 3.1.2.2.0.00.00 - Encargos Patronais - RGPS | B37: =+'DCA-Anexo I-HI'!B38+'DCA-Anexo I-HI'!B39+'DCA-Anexo I-HI'!B40 -> 5842845.2
A38: 3.1.2.2.1.00.00 - Encargos Patronais - RGPS - Consolidação | B38: 0
A39: 3.1.2.2.2.00.00 - Encargos Patronais - RGPS - Intra OFSS | B39: 0
A40: 3.1.2.2.3.00.00 - Encargos Patronais - RGPS - Inter OFSS - União | B40: 5842845.2
A41: 3.1.2.3.0.00.00 - Encargos Patronais - FGTS | B41: =+'DCA-Anexo I-HI'!B42 -> 0
A42: 3.1.2.3.1.00.00 - Encargos Patronais - FGTS - Consolidação | B42: 0
A43: 3.1.2.4.0.00.00 - Contribuições Sociais Gerais | B43: =+'DCA-Anexo I-HI'!B44+'DCA-Anexo I-HI'!B45+'DCA-Anexo I-HI'!B46+'DCA-Anexo I-HI'!B47+'DCA-Anexo I-HI'!B48 -> 0
A44: 3.1.2.4.1.00.00 - Contribuições Sociais Gerais - Consolidação | B44: 0
A45: 3.1.2.4.2.00.00 - Contribuições Sociais Gerais - Intra OFSS | B45: 0
A46: 3.1.2.4.3.00.00 - Contribuições Sociais Gerais - Inter OFSS - União | B46: 0
A47: 3.1.2.4.4.00.00 - Contribuições Sociais Gerais - Inter OFSS - Estado | B47: 0
A48: 3.1.2.4.5.00.00 - Contribuições Sociais Gerais - Inter OFSS - Município | B48: 0
A49: 3.1.2.5.0.00.00 - Contribuições a Entidades Fechadas de Previdência | B49: =+'DCA-Anexo I-HI'!B50+'DCA-Anexo I-HI'!B51 -> 0
A50: 3.1.2.5.1.00.00 - Contribuições a Entidades Fechadas de Previdência - Consolidação | B50: 0
A51: 3.1.2.5.4.00.00 - Contribuições a Entidades Fechadas de Previdência - Inter OFSS - Estado | B51: 0
A52: 3.1.2.9.0.00.00 - Outros Encargos Patronais | B52: =+'DCA-Anexo I-HI'!B53+'DCA-Anexo I-HI'!B56+'DCA-Anexo I-HI'!B55+'DCA-Anexo I-HI'!B57+'DCA-Anexo I-HI'!B54 -> 0
A53: 3.1.2.9.1.00.00 - Outros Encargos Patronais - Consolidação | B53: 0
A54: 3.1.2.9.2.00.00 - Outros Encargos Patronais - Intra OFSS | B54: 0
A55: 3.1.2.9.3.00.00 - Outros Encargos Patronais - Inter OFSS - União | B55: 0
A56: 3.1.2.9.4.00.00 - Outros Encargos Patronais - Inter OFSS - Estado | B56: 0
A57: 3.1.2.9.5.00.00 - Outros Encargos Patronais - Inter OFSS - Município | B57: 0
A58: 3.1.3.0.0.00.00 - Benefícios a Pessoal | B58: =+'DCA-Anexo I-HI'!B63+'DCA-Anexo I-HI'!B59+'DCA-Anexo I-HI'!B61 -> 0
A59: 3.1.3.1.0.00.00 - Benefícios a Pessoal - RPPS | B59: =+'DCA-Anexo I-HI'!B60 -> 0
A60: 3.1.3.1.1.00.00 - Benefícios a Pessoal - RPPS - Consolidação | B60: 0
A61: 3.1.3.2.0.00.00 - Benefícios a Pessoal - RGPS | B61: =+'DCA-Anexo I-HI'!B62 -> 0
A62: 3.1.3.2.1.00.00 - Benefícios a Pessoal - RGPS - Consolidação | B62: 0
A63: 3.1.3.3.0.00.00 - Benefícios a Pessoal - Militar | B63: =+'DCA-Anexo I-HI'!B64 -> 0
A64: 3.1.3.3.1.00.00 - Benefícios a Pessoal - Militar - Consolidação | B64: 0
A65: 3.1.9.0.0.00.00 - Outras Variações Patrimoniais Diminutivas - Pessoal e Encargos | B65: =+'DCA-Anexo I-HI'!B68+'DCA-Anexo I-HI'!B66+'DCA-Anexo I-HI'!B74 -> 20004.99
A66: 3.1.9.1.0.00.00 - Indenizações e Restituições Trabalhistas | B66: =+'DCA-Anexo I-HI'!B67 -> 20004.99
A67: 3.1.9.1.1.00.00 - Indenizações e Restituições Trabalhistas - Consolidação | B67: 20004.99
A68: 3.1.9.2.0.00.00 - Pessoal Requisitado de Outros Órgãos e Entes | B68: =+'DCA-Anexo I-HI'!B69+'DCA-Anexo I-HI'!B70+'DCA-Anexo I-HI'!B71+'DCA-Anexo I-HI'!B72+'DCA-Anexo I-HI'!B73 -> 0
A69: 3.1.9.2.1.00.00 - Pessoal Requisitado de Outros Órgãos e Entes - Consolidação | B69: 0
A70: 3.1.9.2.2.00.00 - Pessoal Requisitado de Outros Órgãos e Entes - Intra OFSS | B70: 0
A71: 3.1.9.2.3.00.00 - Pessoal Requisitado de Outros Órgãos e Entes - Inter OFSS - União | B71: 0
A72: 3.1.9.2.4.00.00 - Pessoal Requisitado de Outros Órgãos e Entes - Inter OFSS - Estado | B72: 0
A73: 3.1.9.2.5.00.00 - Pessoal Requisitado de Outros Órgãos e Entes - Inter OFSS - Município | B73: 0
A74: 3.1.9.9.0.00.00 - Outras VPD de Pessoal e Encargos | B74: =+'DCA-Anexo I-HI'!B75+'DCA-Anexo I-HI'!B76+'DCA-Anexo I-HI'!B77+'DCA-Anexo I-HI'!B78+'DCA-Anexo I-HI'!B79 -> 0
A75: 3.1.9.9.1.00.00 - Outras VPD de Pessoal e Encargos - Consolidação | B75: 0
A76: 3.1.9.9.2.00.00 - Outras VPD de Pessoal e Encargos - Intra OFSS | B76: 0
A77: 3.1.9.9.3.00.00 - Outras VPD de Pessoal e Encargos - Inter OFSS - União | B77: 0
A78: 3.1.9.9.4.00.00 - Outras VPD de Pessoal e Encargos - Inter OFSS - Estado | B78: 0
A79: 3.1.9.9.5.00.00 - Outras VPD de Pessoal e Encargos - Inter OFSS - Município | B79: 0
A80: 3.2.0.0.0.00.00 - Benefícios Previdenciários e Assistenciais | B80: =+'DCA-Anexo I-HI'!B108+'DCA-Anexo I-HI'!B120+'DCA-Anexo I-HI'!B101+'DCA-Anexo I-HI'!B81+'DCA-Anexo I-HI'!B92+'DCA-Anexo I-HI'!B117 -> 0
A81: 3.2.1.0.0.00.00 - Aposentadorias e Reformas | B81: =+'DCA-Anexo I-HI'!B82+'DCA-Anexo I-HI'!B84+'DCA-Anexo I-HI'!B86+'DCA-Anexo I-HI'!B88+'DCA-Anexo I-HI'!B90 -> 0
A82: 3.2.1.1.0.00.00 - Aposentadorias - RPPS | B82: =+'DCA-Anexo I-HI'!B83 -> 0
A83: 3.2.1.1.1.00.00 - Aposentadorias - RPPS - Consolidação | B83: 0
A84: 3.2.1.2.0.00.00 - Aposentadorias - RGPS | B84: =+'DCA-Anexo I-HI'!B85 -> 0
A85: 3.2.1.2.1.00.00 - Aposentadorias - RGPS - Consolidação | B85: 0
A86: 3.2.1.3.0.00.00 - Reserva Remunerada - Pessoal Militar | B86: =+'DCA-Anexo I-HI'!B87 -> 0
A87: 3.2.1.3.1.00.00 - Reserva Remunerada - Pessoal Militar - Consolidação | B87: 0
A88: 3.2.1.4.0.00.00 - Reforma - Pessoal Militar | B88: =+'DCA-Anexo I-HI'!B89 -> 0
A89: 3.2.1.4.1.00.00 - Reforma - Pessoal Militar - Consolidação | B89: 0
A90: 3.2.1.9.0.00.00 - Outras Aposentadorias | B90: =+'DCA-Anexo I-HI'!B91 -> 0
A91: 3.2.1.9.1.00.00 - Outras Aposentadorias - Consolidação | B91: 0
A92: 3.2.2.0.0.00.00 - Pensões | B92: =+'DCA-Anexo I-HI'!B97+'DCA-Anexo I-HI'!B93+'DCA-Anexo I-HI'!B95+'DCA-Anexo I-HI'!B99 -> 0
A93: 3.2.2.1.0.00.00 - Pensões - RPPS | B93: =+'DCA-Anexo I-HI'!B94 -> 0
A94: 3.2.2.1.1.00.00 - Pensões - RPPS - Consolidação | B94: 0
A95: 3.2.2.2.0.00.00 - Pensões - RGPS | B95: =+'DCA-Anexo I-HI'!B96 -> 0
A96: 3.2.2.2.1.00.00 - Pensões - RGPS - Consolidação | B96: 0
A97: 3.2.2.3.0.00.00 - Pensões - Pessoal Militar | B97: =+'DCA-Anexo I-HI'!B98 -> 0
A98: 3.2.2.3.1.00.00 - Pensões - Pessoal Militar - Consolidação | B98: 0
A99: 3.2.2.9.0.00.00 - Outras Pensões | B99: =+'DCA-Anexo I-HI'!B100 -> 0
A100: 3.2.2.9.1.00.00 - Outras Pensões - Consolidação | B100: 0
A101: 3.2.3.0.0.00.00 - Benefícios de Prestação Continuada | B101: =+'DCA-Anexo I-HI'!B106+'DCA-Anexo I-HI'!B104+'DCA-Anexo I-HI'!B102 -> 0
A102: 3.2.3.1.0.00.00 - Benefícios de Prestação Continuada ao Idoso | B102: =+'DCA-Anexo I-HI'!B103 -> 0
A103: 3.2.3.1.1.00.00 - Benefícios de Prestação Continuada ao Idoso - Consolidação | B103: 0
...
